Workbook

Sheet Сводка
A1: Aros — регрессионные тест-кейсы витрины (роль: Мастер)
A2: Клиентская часть сайта, UI. Сверено с PRD в Confluence и staging 28.10.2026. Админ-панель — отдельный набор.
A4: Окружение | B4: https://staging.aros.uz/ru
A5: Роль | B5: Мастер
A6: Тестовый аккаунт | B6: Логин: +998998987882 Пароль: <пароль в .env> в .env>
A7: Документация | B7: Confluence → Aros Market (PRD); ссылки на листе «Источники»
A8: Автотесты | B8: Репозиторий aros-ui: Java 21 + Playwright + JUnit5 + Allure
A9: Релиз / версия | J9: ← жёлтые поля заполняются перед каждым прогоном
A10: Дата прогона
A11: Тестировщик
A12: Покрытие по модулям
A13: Модуль | B13: Всего | C13: P1 | D13: P2 | E13: P3 | F13: Можно авто: Да | G13: Частично | H13: Нет | I13: Автоматизировано | J13: % покрытия автотестами | K13: Passed | L13: Failed | M13: Blocked | N13: Skipped | O13: Не выполнен
A14: AUTH — Авторизация и сессия | B14: =COUNTIF('Тест-кейсы'!$B$2:$B$197,"Авторизация и сессия") | C14: =COUNTIFS('Тест-кейсы'!$B$2:$B$197,"Авторизация и сессия",'Тест-кейсы'!$E$2:$E$197,"P1") | D14: =COUNTIFS('Тест-кейсы'!$B$2:$B$197,"Авторизация и сессия",'Тест-кейсы'!$E$2:$E$197,"P2") | E14: =COUNTIFS('Тест-кейсы'!$B$2:$B$197,"Авторизация и сессия",'Тест-кейсы'!$E$2:$E$197,"P3") | F14: =COUNTIFS('Тест-кейсы'!$B$2:$B$197,"Авторизация и сессия",'Тест-кейсы'!$L$2:$L$197,"Да") | G14: =COUNTIFS('Тест-кейсы'!$B$2:$B$197,"Авторизация и сессия",'Тест-кейсы'!$L$2:$L$197,"Частично") | H14: =COUNTIFS('Тест-кейсы'!$B$2:$B$197,"Авторизация и сессия",'Тест-кейсы'!$L$2:$L$197,"Нет") | I14: =COUNTIFS('Тест-кейсы'!$B$2:$B$197,"Авторизация и сессия",'Тест-кейсы'!$N$2:$N$197,"Автоматизирован") | J14: =IF(B14=0,0,I14/B14) | K14: =COUNTIFS('Тест-кейсы'!$B$2:$B$197,"Авторизация и сессия",'Тест-кейсы'!$P$2:$P$197,"Passed") | L14: =COUNTIFS('Тест-кейсы'!$B$2:$B$197,"Авторизация и сессия",'Тест-кейсы'!$P$2:$P$197,"Failed") | M14: =COUNTIFS('Тест-кейсы'!$B$2:$B$197,"Авторизация и сессия",'Тест-кейсы'!$P$2:$P$197,"Blocked") | N14: =COUNTIFS('Тест-кейсы'!$B$2:$B$197,"Авторизация и сессия",'Тест-кейсы'!$P$2:$P$197,"Skipped") | O14: =COUNTIFS('Тест-кейсы'!$B$2:$B$197,"Авторизация и сессия",'Тест-кейсы'!$P$2:$P$197,"Не выполнен")
A15: HDR — Шапка, футер и навигация | B15: =COUNTIF('Тест-кейсы'!$B$2:$B$197,"Шапка, футер и навигация") | C15: =COUNTIFS('Тест-кейсы'!$B$2:$B$197,"Шапка, футер и навигация",'Тест-кейсы'!$E$2:$E$197,"P1") | D15: =COUNTIFS('Тест-кейсы'!$B$2:$B$197,"Шапка, футер и навигация",'Тест-кейсы'!$E$2:$E$197,"P2") | E15: =COUNTIFS('Тест-кейсы'!$B$2:$B$197,"Шапка, футер и навигация",'Тест-кейсы'!$E$2:$E$197,"P3") | F15: =COUNTIFS('Тест-кейсы'!$B$2:$B$197,"Шапка, футер и навигация",'Тест-кейсы'!$L$2:$L$197,"Да") | G15: =COUNTIFS('Тест-кейсы'!$B$2:$B$197,"Шапка, футер и навигация",'Тест-кейсы'!$L$2:$L$197,"Частично") | H15: =COUNTIFS('Тест-кейсы'!$B$2:$B$197,"Шапка, футер и навигация",'Тест-кейсы'!$L$2:$L$197,"Нет") | I15: =COUNTIFS('Тест-кейсы'!$B$2:$B$197,"Шапка, футер и навигация",'Тест-кейсы'!$N$2:$N$197,"Автоматизирован") | J15: =IF(B15=0,0,I15/B15) | K15: =COUNTIFS('Тест-кейсы'!$B$2:$B$197,"Шапка, футер и навигация",'Тест-кейсы'!$P$2:$P$197,"Passed") | L15: =COUNTIFS('Тест-кейсы'!$B$2:$B$197,"Шапка, футер и навигация",'Тест-кейсы'!$P$2:$P$197,"Failed") | M15: =COUNTIFS('Тест-кейсы'!$B$2:$B$197,"Шапка, футер и навигация",'Тест-кейсы'!$P$2:$P$197,"Blocked") | N15: =COUNTIFS('Тест-кейсы'!$B$2:$B$197,"Шапка, футер и навигация",'Тест-кейсы'!$P$2:$P$197,"Skipped") | O15: =COUNTIFS('Тест-кейсы'!$B$2:$B$197,"Шапка, футер и навигация",'Тест-кейсы'!$P$2:$P$197,"Не выполнен")
A16: HOME — Главная страница | B16: =COUNTIF('Тест-кейсы'!$B$2:$B$197,"Главная страница") | C16: =COUNTIFS('Тест-кейсы'!$B$2:$B$197,"Главная страница",'Тест-кейсы'!$E$2:$E$197,"P1") | D16: =COUNTIFS('Тест-кейсы'!$B$2:$B$197,"Главная страница",'Тест-кейсы'!$E$2:$E$197,"P2") | E16: =COUNTIFS('Тест-кейсы'!$B$2:$B$197,"Главная страница",'Тест-кейсы'!$E$2:$E$197,"P3") | F16: =COUNTIFS('Тест-кейсы'!$B$2:$B$197,"Главная страница",'Тест-кейсы'!$L$2:$L$197,"Да") | G16: =COUNTIFS('Тест-кейсы'!$B$2:$B$197,"Главная страница",'Тест-кейсы'!$L$2:$L$197,"Частично") | H16: =COUNTIFS('Тест-кейсы'!$B$2:$B$197,"Главная страница",'Тест-кейсы'!$L$2:$L$197,"Нет") | I16: =COUNTIFS('Тест-кейсы'!$B$2:$B$197,"Главная страница",'Тест-кейсы'!$N$2:$N$197,"Автоматизирован") | J16: =IF(B16=0,0,I16/B16) | K16: =COUNTIFS('Тест-кейсы'!$B$2:$B$197,"Главная страница",'Тест-кейсы'!$P$2:$P$197,"Passed") | L16: =COUNTIFS('Тест-кейсы'!$B$2:$B$197,"Главная страница",'Тест-кейсы'!$P$2:$P$197,"Failed") | M16: =COUNTIFS('Тест-кейсы'!$B$2:$B$197,"Главная страница",'Тест-кейсы'!$P$2:$P$197,"Blocked") | N16: =COUNTIFS('Тест-кейсы'!$B$2:$B$197,"Главная страница",'Тест-кейсы'!$P$2:$P$197,"Skipped") | O16: =COUNTIFS('Тест-кейсы'!$B$2:$B$197,"Главная страница",'Тест-кейсы'!$P$2:$P$197,"Не выполнен")
A17: CAT — Каталог, категории и фильтры | B17: =COUNTIF('Тест-кейсы'!$B$2:$B$197,"Каталог, категории и фильтры") | C17: =COUNTIFS('Тест-кейсы'!$B$2:$B$197,"Каталог, категории и фильтры",'Тест-кейсы'!$E$2:$E$197,"P1") | D17: =COUNTIFS('Тест-кейсы'!$B$2:$B$197,"Каталог, категории и фильтры",'Тест-кейсы'!$E$2:$E$197,"P2") | E17: =COUNTIFS('Тест-кейсы'!$B$2:$B$197,"Каталог, категории и фильтры",'Тест-кейсы'!$E$2:$E$197,"P3") | F17: =COUNTIFS('Тест-кейсы'!$B$2:$B$197,"Каталог, категории и фильтры",'Тест-кейсы'!$L$2:$L$197,"Да") | G17: =COUNTIFS('Тест-кейсы'!$B$2:$B$197,"Каталог, категории и фильтры",'Тест-кейсы'!$L$2:$L$197,"Частично") | H17: =COUNTIFS('Тест-кейсы'!$B$2:$B$197,"Каталог, категории и фильтры",'Тест-кейсы'!$L$2:$L$197,"Нет") | I17: =COUNTIFS('Тест-кейсы'!$B$2:$B$197,"Каталог, категории и фильтры",'Тест-кейсы'!$N$2:$N$197,"Автоматизирован") | J17: =IF(B17=0,0,I17/B17) | K17: =COUNTIFS('Тест-кейсы'!$B$2:$B$197,"Каталог, категории и фильтры",'Тест-кейсы'!$P$2:$P$197,"Passed") | L17: =COUNTIFS('Тест-кейсы'!$B$2:$B$197,"Каталог, категории и фильтры",'Тест-кейсы'!$P$2:$P$197,"Failed") | M17: =COUNTIFS('Тест-кейсы'!$B$2:$B$197,"Каталог, категории и фильтры",'Тест-кейсы'!$P$2:$P$197,"Blocked") | N17: =COUNTIFS('Тест-кейсы'!$B$2:$B$197,"Каталог, категории и фильтры",'Тест-кейсы'!$P$2:$P$197,"Skipped") | O17: =COUNTIFS('Тест-кейсы'!$B$2:$B$197,"Каталог, категории и фильтры",'Тест-кейсы'!$P$2:$P$197,"Не выполнен")
A18: MDL — Подбор по модели устройства | B18: =COUNTIF('Тест-кейсы'!$B$2:$B$197,"Подбор по модели устройства") | C18: =COUNTIFS('Тест-кейсы'!$B$2:$B$197,"Подбор по модели устройства",'Тест-кейсы'!$E$2:$E$197,"P1") | D18: =COUNTIFS('Тест-кейсы'!$B$2:$B$197,"Подбор по модели устройства",'Тест-кейсы'!$E$2:$E$197,"P2") | E18: =COUNTIFS('Тест-кейсы'!$B$2:$B$197,"Подбор по модели устройства",'Тест-кейсы'!$E$2:$E$197,"P3") | F18: =COUNTIFS('Тест-кейсы'!$B$2:$B$197,"Подбор по модели устройства",'Тест-кейсы'!$L$2:$L$197,"Да") | G18: =COUNTIFS('Тест-кейсы'!$B$2:$B$197,"Подбор по модели устройства",'Тест-кейсы'!$L$2:$L$197,"Частично") | H18: =COUNTIFS('Тест-кейсы'!$B$2:$B$197,"Подбор по модели устройства",'Тест-кейсы'!$L$2:$L$197,"Нет") | I18: =COUNTIFS('Тест-кейсы'!$B$2:$B$197,"Подбор по модели устройства",'Тест-кейсы'!$N$2:$N$197,"Автоматизирован") | J18: =IF(B18=0,0,I18/B18) | K18: =COUNTIFS('Тест-кейсы'!$B$2:$B$197,"Подбор по модели устройства",'Тест-кейсы'!$P$2:$P$197,"Passed") | L18: =COUNTIFS('Тест-кейсы'!$B$2:$B$197,"Подбор по модели устройства",'Тест-кейсы'!$P$2:$P$197,"Failed") | M18: =COUNTIFS('Тест-кейсы'!$B$2:$B$197,"Подбор по модели устройства",'Тест-кейсы'!$P$2:$P$197,"Blocked") | N18: =COUNTIFS('Тест-кейсы'!$B$2:$B$197,"Подбор по модели устройства",'Тест-кейсы'!$P$2:$P$197,"Skipped") | O18: =COUNTIFS('Тест-кейсы'!$B$2:$B$197,"Подбор по модели устройства",'Тест-кейсы'!$P$2:$P$197,"Не выполнен")
A19: SRCH — Поиск | B19: =COUNTIF('Тест-кейсы'!$B$2:$B$197,"Поиск") | C19: =COUNTIFS('Тест-кейсы'!$B$2:$B$197,"Поиск",'Тест-кейсы'!$E$2:$E$197,"P1") | D19: =COUNTIFS('Тест-кейсы'!$B$2:$B$197,"Поиск",'Тест-кейсы'!$E$2:$E$197,"P2") | E19: =COUNTIFS('Тест-кейсы'!$B$2:$B$197,"Поиск",'Тест-кейсы'!$E$2:$E$197,"P3") | F19: =COUNTIFS('Тест-кейсы'!$B$2:$B$197,"Поиск",'Тест-кейсы'!$L$2:$L$197,"Да") | G19: =COUNTIFS('Тест-кейсы'!$B$2:$B$197,"Поиск",'Тест-кейсы'!$L$2:$L$197,"Частично") | H19: =COUNTIFS('Тест-кейсы'!$B$2:$B$197,"Поиск",'Тест-кейсы'!$L$2:$L$197,"Нет") | I19: =COUNTIFS('Тест-кейсы'!$B$2:$B$197,"Поиск",'Тест-кейсы'!$N$2:$N$197,"Автоматизирован") | J19: =IF(B19=0,0,I19/B19) | K19: =COUNTIFS('Тест-кейсы'!$B$2:$B$197,"Поиск",'Тест-кейсы'!$P$2:$P$197,"Passed") | L19: =COUNTIFS('Тест-кейсы'!$B$2:$B$197,"Поиск",'Тест-кейсы'!$P$2:$P$197,"Failed") | M19: =COUNTIFS('Тест-кейсы'!$B$2:$B$197,"Поиск",'Тест-кейсы'!$P$2:$P$197,"Blocked") | N19: =COUNTIFS('Тест-кейсы'!$B$2:$B$197,"Поиск",'Тест-кейсы'!$P$2:$P$197,"Skipped") | O19: =COUNTIFS('Тест-кейсы'!$B$2:$B$197,"Поиск",'Тест-кейсы'!$P$2:$P$197,"Не выполнен")
A20: PDP — Карточка товара | B20: =COUNTIF('Тест-кейсы'!$B$2:$B$197,"Карточка товара") | C20: =COUNTIFS('Тест-кейсы'!$B$2:$B$197,"Карточка товара",'Тест-кейсы'!$E$2:$E$197,"P1") | D20: =COUNTIFS('Тест-кейсы'!$B$2:$B$197,"Карточка товара",'Тест-кейсы'!$E$2:$E$197,"P2") | E20: =COUNTIFS('Тест-кейсы'!$B$2:$B$197,"Карточка товара",'Тест-кейсы'!$E$2:$E$197,"P3") | F20: =COUNTIFS('Тест-кейсы'!$B$2:$B$197,"Карточка товара",'Тест-кейсы'!$L$2:$L$197,"Да") | G20: =COUNTIFS('Тест-кейсы'!$B$2:$B$197,"Карточка товара",'Тест-кейсы'!$L$2:$L$197,"Частично") | H20: =COUNTIFS('Тест-кейсы'!$B$2:$B$197,"Карточка товара",'Тест-кейсы'!$L$2:$L$197,"Нет") | I20: =COUNTIFS('Тест-кейсы'!$B$2:$B$197,"Карточка товара",'Тест-кейсы'!$N$2:$N$197,"Автоматизирован") | J20: =IF(B20=0,0,I20/B20) | K20: =COUNTIFS('Тест-кейсы'!$B$2:$B$197,"Карточка товара",'Тест-кейсы'!$P$2:$P$197,"Passed") | L20: =COUNTIFS('Тест-кейсы'!$B$2:$B$197,"Карточка товара",'Тест-кейсы'!$P$2:$P$197,"Failed") | M20: =COUNTIFS('Тест-кейсы'!$B$2:$B$197,"Карточка товара",'Тест-кейсы'!$P$2:$P$197,"Blocked") | N20: =COUNTIFS('Тест-кейсы'!$B$2:$B$197,"Карточка товара",'Тест-кейсы'!$P$2:$P$197,"Skipped") | O20: =COUNTIFS('Тест-кейсы'!$B$2:$B$197,"Карточка товара",'Тест-кейсы'!$P$2:$P$197,"Не выполнен")
A21: FAV — Избранное | B21: =COUNTIF('Тест-кейсы'!$B$2:$B$197,"Избранное") | C21: =COUNTIFS('Тест-кейсы'!$B$2:$B$197,"Избранное",'Тест-кейсы'!$E$2:$E$197,"P1") | D21: =COUNTIFS('Тест-кейсы'!$B$2:$B$197,"Избранное",'Тест-кейсы'!$E$2:$E$197,"P2") | E21: =COUNTIFS('Тест-кейсы'!$B$2:$B$197,"Избранное",'Тест-кейсы'!$E$2:$E$197,"P3") | F21: =COUNTIFS('Тест-кейсы'!$B$2:$B$197,"Избранное",'Тест-кейсы'!$L$2:$L$197,"Да") | G21: =COUNTIFS('Тест-кейсы'!$B$2:$B$197,"Избранное",'Тест-кейсы'!$L$2:$L$197,"Частично") | H21: =COUNTIFS('Тест-кейсы'!$B$2:$B$197,"Избранное",'Тест-кейсы'!$L$2:$L$197,"Нет") | I21: =COUNTIFS('Тест-кейсы'!$B$2:$B$197,"Избранное",'Тест-кейсы'!$N$2:$N$197,"Автоматизирован") | J21: =IF(B21=0,0,I21/B21) | K21: =COUNTIFS('Тест-кейсы'!$B$2:$B$197,"Избранное",'Тест-кейсы'!$P$2:$P$197,"Passed") | L21: =COUNTIFS('Тест-кейсы'!$B$2:$B$197,"Избранное",'Тест-кейсы'!$P$2:$P$197,"Failed") | M21: =COUNTIFS('Тест-кейсы'!$B$2:$B$197,"Избранное",'Тест-кейсы'!$P$2:$P$197,"Blocked") | N21: =COUNTIFS('Тест-кейсы'!$B$2:$B$197,"Избранное",'Тест-кейсы'!$P$2:$P$197,"Skipped") | O21: =COUNTIFS('Тест-кейсы'!$B$2:$B$197,"Избранное",'Тест-кейсы'!$P$2:$P$197,"Не выполнен")
A22: CART — Корзина | B22: =COUNTIF('Тест-кейсы'!$B$2:$B$197,"Корзина") | C22: =COUNTIFS('Тест-кейсы'!$B$2:$B$197,"Корзина",'Тест-кейсы'!$E$2:$E$197,"P1") | D22: =COUNTIFS('Тест-кейсы'!$B$2:$B$197,"Корзина",'Тест-кейсы'!$E$2:$E$197,"P2") | E22: =COUNTIFS('Тест-кейсы'!$B$2:$B$197,"Корзина",'Тест-кейсы'!$E$2:$E$197,"P3") | F22: =COUNTIFS('Тест-кейсы'!$B$2:$B$197,"Корзина",'Тест-кейсы'!$L$2:$L$197,"Да") | G22: =COUNTIFS('Тест-кейсы'!$B$2:$B$197,"Корзина",'Тест-кейсы'!$L$2:$L$197,"Частично") | H22: =COUNTIFS('Тест-кейсы'!$B$2:$B$197,"Корзина",'Тест-кейсы'!$L$2:$L$197,"Нет") | I22: =COUNTIFS('Тест-кейсы'!$B$2:$B$197,"Корзина",'Тест-кейсы'!$N$2:$N$197,"Автоматизирован") | J22: =IF(B22=0,0,I22/B22) | K22: =COUNTIFS('Тест-кейсы'!$B$2:$B$197,"Корзина",'Тест-кейсы'!$P$2:$P$197,"Passed") | L22: =COUNTIFS('Тест-кейсы'!$B$2:$B$197,"Корзина",'Тест-кейсы'!$P$2:$P$197,"Failed") | M22: =COUNTIFS('Тест-кейсы'!$B$2:$B$197,"Корзина",'Тест-кейсы'!$P$2:$P$197,"Blocked") | N22: =COUNTIFS('Тест-кейсы'!$B$2:$B$197,"Корзина",'Тест-кейсы'!$P$2:$P$197,"Skipped") | O22: =COUNTIFS('Тест-кейсы'!$B$2:$B$197,"Корзина",'Тест-кейсы'!$P$2:$P$197,"Не выполнен")
A23: CHK — Оформление заказа | B23: =COUNTIF('Тест-кейсы'!$B$2:$B$197,"Оформление заказа") | C23: =COUNTIFS('Тест-кейсы'!$B$2:$B$197,"Оформление заказа",'Тест-кейсы'!$E$2:$E$197,"P1") | D23: =COUNTIFS('Тест-кейсы'!$B$2:$B$197,"Оформление заказа",'Тест-кейсы'!$E$2:$E$197,"P2") | E23: =COUNTIFS('Тест-кейсы'!$B$2:$B$197,"Оформление заказа",'Тест-кейсы'!$E$2:$E$197,"P3") | F23: =COUNTIFS('Тест-кейсы'!$B$2:$B$197,"Оформление заказа",'Тест-кейсы'!$L$2:$L$197,"Да") | G23: =COUNTIFS('Тест-кейсы'!$B$2:$B$197,"Оформление заказа",'Тест-кейсы'!$L$2:$L$197,"Частично") | H23: =COUNTIFS('Тест-кейсы'!$B$2:$B$197,"Оформление заказа",'Тест-кейсы'!$L$2:$L$197,"Нет") | I23: =COUNTIFS('Тест-кейсы'!$B$2:$B$197,"Оформление заказа",'Тест-кейсы'!$N$2:$N$197,"Автоматизирован") | J23: =IF(B23=0,0,I23/B23) | K23: =COUNTIFS('Тест-кейсы'!$B$2:$B$197,"Оформление заказа",'Тест-кейсы'!$P$2:$P$197,"Passed") | L23: =COUNTIFS('Тест-кейсы'!$B$2:$B$197,"Оформление заказа",'Тест-кейсы'!$P$2:$P$197,"Failed") | M23: =COUNTIFS('Тест-кейсы'!$B$2:$B$197,"Оформление заказа",'Тест-кейсы'!$P$2:$P$197,"Blocked") | N23: =COUNTIFS('Тест-кейсы'!$B$2:$B$197,"Оформление заказа",'Тест-кейсы'!$P$2:$P$197,"Skipped") | O23: =COUNTIFS('Тест-кейсы'!$B$2:$B$197,"Оформление заказа",'Тест-кейсы'!$P$2:$P$197,"Не выполнен")
A24: ORD — Мои заказы | B24: =COUNTIF('Тест-кейсы'!$B$2:$B$197,"Мои заказы") | C24: =COUNTIFS('Тест-кейсы'!$B$2:$B$197,"Мои заказы",'Тест-кейсы'!$E$2:$E$197,"P1") | D24: =COUNTIFS('Тест-кейсы'!$B$2:$B$197,"Мои заказы",'Тест-кейсы'!$E$2:$E$197,"P2") | E24: =COUNTIFS('Тест-кейсы'!$B$2:$B$197,"Мои заказы",'Тест-кейсы'!$E$2:$E$197,"P3") | F24: =COUNTIFS('Тест-кейсы'!$B$2:$B$197,"Мои заказы",'Тест-кейсы'!$L$2:$L$197,"Да") | G24: =COUNTIFS('Тест-кейсы'!$B$2:$B$197,"Мои заказы",'Тест-кейсы'!$L$2:$L$197,"Частично") | H24: =COUNTIFS('Тест-кейсы'!$B$2:$B$197,"Мои заказы",'Тест-кейсы'!$L$2:$L$197,"Нет") | I24: =COUNTIFS('Тест-кейсы'!$B$2:$B$197,"Мои заказы",'Тест-кейсы'!$N$2:$N$197,"Автоматизирован") | J24: =IF(B24=0,0,I24/B24) | K24: =COUNTIFS('Тест-кейсы'!$B$2:$B$197,"Мои заказы",'Тест-кейсы'!$P$2:$P$197,"Passed") | L24: =COUNTIFS('Тест-кейсы'!$B$2:$B$197,"Мои заказы",'Тест-кейсы'!$P$2:$P$197,"Failed") | M24: =COUNTIFS('Тест-кейсы'!$B$2:$B$197,"Мои заказы",'Тест-кейсы'!$P$2:$P$197,"Blocked") | N24: =COUNTIFS('Тест-кейсы'!$B$2:$B$197,"Мои заказы",'Тест-кейсы'!$P$2:$P$197,"Skipped") | O24: =COUNTIFS('Тест-кейсы'!$B$2:$B$197,"Мои заказы",'Тест-кейсы'!$P$2:$P$197,"Не выполнен")
A25: PRF — Личные данные и адреса | B25: =COUNTIF('Тест-кейсы'!$B$2:$B$197,"Личные данные и адреса") | C25: =COUNTIFS('Тест-кейсы'!$B$2:$B$197,"Личные данные и адреса",'Тест-кейсы'!$E$2:$E$197,"P1") | D25: =COUNTIFS('Тест-кейсы'!$B$2:$B$197,"Личные данные и адреса",'Тест-кейсы'!$E$2:$E$197,"P2") | E25: =COUNTIFS('Тест-кейсы'!$B$2:$B$197,"Личные данные и адреса",'Тест-кейсы'!$E$2:$E$197,"P3") | F25: =COUNTIFS('Тест-кейсы'!$B$2:$B$197,"Личные данные и адреса",'Тест-кейсы'!$L$2:$L$197,"Да") | G25: =COUNTIFS('Тест-кейсы'!$B$2:$B$197,"Личные данные и адреса",'Тест-кейсы'!$L$2:$L$197,"Частично") | H25: =COUNTIFS('Тест-кейсы'!$B$2:$B$197,"Личные данные и адреса",'Тест-кейсы'!$L$2:$L$197,"Нет") | I25: =COUNTIFS('Тест-кейсы'!$B$2:$B$197,"Личные данные и адреса",'Тест-кейсы'!$N$2:$N$197,"Автоматизирован") | J25: =IF(B25=0,0,I25/B25) | K25: =COUNTIFS('Тест-кейсы'!$B$2:$B$197,"Личные данные и адреса",'Тест-кейсы'!$P$2:$P$197,"Passed") | L25: =COUNTIFS('Тест-кейсы'!$B$2:$B$197,"Личные данные и адреса",'Тест-кейсы'!$P$2:$P$197,"Failed") | M25: =COUNTIFS('Тест-кейсы'!$B$2:$B$197,"Личные данные и адреса",'Тест-кейсы'!$P$2:$P$197,"Blocked") | N25: =COUNTIFS('Тест-кейсы'!$B$2:$B$197,"Личные данные и адреса",'Тест-кейсы'!$P$2:$P$197,"Skipped") | O25: =COUNTIFS('Тест-кейсы'!$B$2:$B$197,"Личные данные и адреса",'Тест-кейсы'!$P$2:$P$197,"Не выполнен")
A26: PTS — Баллы | B26: =COUNTIF('Тест-кейсы'!$B$2:$B$197,"Баллы") | C26: =COUNTIFS('Тест-кейсы'!$B$2:$B$197,"Баллы",'Тест-кейсы'!$E$2:$E$197,"P1") | D26: =COUNTIFS('Тест-кейсы'!$B$2:$B$197,"Баллы",'Тест-кейсы'!$E$2:$E$197,"P2") | E26: =COUNTIFS('Тест-кейсы'!$B$2:$B$197,"Баллы",'Тест-кейсы'!$E$2:$E$197,"P3") | F26: =COUNTIFS('Тест-кейсы'!$B$2:$B$197,"Баллы",'Тест-кейсы'!$L$2:$L$197,"Да") | G26: =COUNTIFS('Тест-кейсы'!$B$2:$B$197,"Баллы",'Тест-кейсы'!$L$2:$L$197,"Частично") | H26: =COUNTIFS('Тест-кейсы'!$B$2:$B$197,"Баллы",'Тест-кейсы'!$L$2:$L$197,"Нет") | I26: =COUNTIFS('Тест-кейсы'!$B$2:$B$197,"Баллы",'Тест-кейсы'!$N$2:$N$197,"Автоматизирован") | J26: =IF(B26=0,0,I26/B26) | K26: =COUNTIFS('Тест-кейсы'!$B$2:$B$197,"Баллы",'Тест-кейсы'!$P$2:$P$197,"Passed") | L26: =COUNTIFS('Тест-кейсы'!$B$2:$B$197,"Баллы",'Тест-кейсы'!$P$2:$P$197,"Failed") | M26: =COUNTIFS('Тест-кейсы'!$B$2:$B$197,"Баллы",'Тест-кейсы'!$P$2:$P$197,"Blocked") | N26: =COUNTIFS('Тест-кейсы'!$B$2:$B$197,"Баллы",'Тест-кейсы'!$P$2:$P$197,"Skipped") | O26: =COUNTIFS('Тест-кейсы'!$B$2:$B$197,"Баллы",'Тест-кейсы'!$P$2:$P$197,"Не выполнен")
A27: WLT — Мой кошелёк (долг) | B27: =COUNTIF('Тест-кейсы'!$B$2:$B$197,"Мой кошелёк (долг)") | C27: =COUNTIFS('Тест-кейсы'!$B$2:$B$197,"Мой кошелёк (долг)",'Тест-кейсы'!$E$2:$E$197,"P1") | D27: =COUNTIFS('Тест-кейсы'!$B$2:$B$197,"Мой кошелёк (долг)",'Тест-кейсы'!$E$2:$E$197,"P2") | E27: =COUNTIFS('Тест-кейсы'!$B$2:$B$197,"Мой кошелёк (долг)",'Тест-кейсы'!$E$2:$E$197,"P3") | F27: =COUNTIFS('Тест-кейсы'!$B$2:$B$197,"Мой кошелёк (долг)",'Тест-кейсы'!$L$2:$L$197,"Да") | G27: =COUNTIFS('Тест-кейсы'!$B$2:$B$197,"Мой кошелёк (долг)",'Тест-кейсы'!$L$2:$L$197,"Частично") | H27: =COUNTIFS('Тест-кейсы'!$B$2:$B$197,"Мой кошелёк (долг)",'Тест-кейсы'!$L$2:$L$197,"Нет") | I27: =COUNTIFS('Тест-кейсы'!$B$2:$B$197,"Мой кошелёк (долг)",'Тест-кейсы'!$N$2:$N$197,"Автоматизирован") | J27: =IF(B27=0,0,I27/B27) | K27: =COUNTIFS('Тест-кейсы'!$B$2:$B$197,"Мой кошелёк (долг)",'Тест-кейсы'!$P$2:$P$197,"Passed") | L27: =COUNTIFS('Тест-кейсы'!$B$2:$B$197,"Мой кошелёк (долг)",'Тест-кейсы'!$P$2:$P$197,"Failed") | M27: =COUNTIFS('Тест-кейсы'!$B$2:$B$197,"Мой кошелёк (долг)",'Тест-кейсы'!$P$2:$P$197,"Blocked") | N27: =COUNTIFS('Тест-кейсы'!$B$2:$B$197,"Мой кошелёк (долг)",'Тест-кейсы'!$P$2:$P$197,"Skipped") | O27: =COUNTIFS('Тест-кейсы'!$B$2:$B$197,"Мой кошелёк (долг)",'Тест-кейсы'!$P$2:$P$197,"Не выполнен")
A28: NTF — Уведомления | B28: =COUNTIF('Тест-кейсы'!$B$2:$B$197,"Уведомления") | C28: =COUNTIFS('Тест-кейсы'!$B$2:$B$197,"Уведомления",'Тест-кейсы'!$E$2:$E$197,"P1") | D28: =COUNTIFS('Тест-кейсы'!$B$2:$B$197,"Уведомления",'Тест-кейсы'!$E$2:$E$197,"P2") | E28: =COUNTIFS('Тест-кейсы'!$B$2:$B$197,"Уведомления",'Тест-кейсы'!$E$2:$E$197,"P3") | F28: =COUNTIFS('Тест-кейсы'!$B$2:$B$197,"Уведомления",'Тест-кейсы'!$L$2:$L$197,"Да") | G28: =COUNTIFS('Тест-кейсы'!$B$2:$B$197,"Уведомления",'Тест-кейсы'!$L$2:$L$197,"Частично") | H28: =COUNTIFS('Тест-кейсы'!$B$2:$B$197,"Уведомления",'Тест-кейсы'!$L$2:$L$197,"Нет") | I28: =COUNTIFS('Тест-кейсы'!$B$2:$B$197,"Уведомления",'Тест-кейсы'!$N$2:$N$197,"Автоматизирован") | J28: =IF(B28=0,0,I28/B28) | K28: =COUNTIFS('Тест-кейсы'!$B$2:$B$197,"Уведомления",'Тест-кейсы'!$P$2:$P$197,"Passed") | L28: =COUNTIFS('Тест-кейсы'!$B$2:$B$197,"Уведомления",'Тест-кейсы'!$P$2:$P$197,"Failed") | M28: =COUNTIFS('Тест-кейсы'!$B$2:$B$197,"Уведомления",'Тест-кейсы'!$P$2:$P$197,"Blocked") | N28: =COUNTIFS('Тест-кейсы'!$B$2:$B$197,"Уведомления",'Тест-кейсы'!$P$2:$P$197,"Skipped") | O28: =COUNTIFS('Тест-кейсы'!$B$2:$B$197,"Уведомления",'Тест-кейсы'!$P$2:$P$197,"Не выполнен")
A29: REQ — Мои запросы | B29: =COUNTIF('Тест-кейсы'!$B$2:$B$197,"Мои запросы") | C29: =COUNTIFS('Тест-кейсы'!$B$2:$B$197,"Мои запросы",'Тест-кейсы'!$E$2:$E$197,"P1") | D29: =COUNTIFS('Тест-кейсы'!$B$2:$B$197,"Мои запросы",'Тест-кейсы'!$E$2:$E$197,"P2") | E29: =COUNTIFS('Тест-кейсы'!$B$2:$B$197,"Мои запросы",'Тест-кейсы'!$E$2:$E$197,"P3") | F29: =COUNTIFS('Тест-кейсы'!$B$2:$B$197,"Мои запросы",'Тест-кейсы'!$L$2:$L$197,"Да") | G29: =COUNTIFS('Тест-кейсы'!$B$2:$B$197,"Мои запросы",'Тест-кейсы'!$L$2:$L$197,"Частично") | H29: =COUNTIFS('Тест-кейсы'!$B$2:$B$197,"Мои запросы",'Тест-кейсы'!$L$2:$L$197,"Нет") | I29: =COUNTIFS('Тест-кейсы'!$B$2:$B$197,"Мои запросы",'Тест-кейсы'!$N$2:$N$197,"Автоматизирован") | J29: =IF(B29=0,0,I29/B29) | K29: =COUNTIFS('Тест-кейсы'!$B$2:$B$197,"Мои запросы",'Тест-кейсы'!$P$2:$P$197,"Passed") | L29: =COUNTIFS('Тест-кейсы'!$B$2:$B$197,"Мои запросы",'Тест-кейсы'!$P$2:$P$197,"Failed") | M29: =COUNTIFS('Тест-кейсы'!$B$2:$B$197,"Мои запросы",'Тест-кейсы'!$P$2:$P$197,"Blocked") | N29: =COUNTIFS('Тест-кейсы'!$B$2:$B$197,"Мои запросы",'Тест-кейсы'!$P$2:$P$197,"Skipped") | O29: =COUNTIFS('Тест-кейсы'!$B$2:$B$197,"Мои запросы",'Тест-кейсы'!$P$2:$P$197,"Не выполнен")
A30: SPC — Спецзаказ | B30: =COUNTIF('Тест-кейсы'!$B$2:$B$197,"Спецзаказ") | C30: =COUNTIFS('Тест-кейсы'!$B$2:$B$197,"Спецзаказ",'Тест-кейсы'!$E$2:$E$197,"P1") | D30: =COUNTIFS('Тест-кейсы'!$B$2:$B$197,"Спецзаказ",'Тест-кейсы'!$E$2:$E$197,"P2") | E30: =COUNTIFS('Тест-кейсы'!$B$2:$B$197,"Спецзаказ",'Тест-кейсы'!$E$2:$E$197,"P3") | F30: =COUNTIFS('Тест-кейсы'!$B$2:$B$197,"Спецзаказ",'Тест-кейсы'!$L$2:$L$197,"Да") | G30: =COUNTIFS('Тест-кейсы'!$B$2:$B$197,"Спецзаказ",'Тест-кейсы'!$L$2:$L$197,"Частично") | H30: =COUNTIFS('Тест-кейсы'!$B$2:$B$197,"Спецзаказ",'Тест-кейсы'!$L$2:$L$197,"Нет") | I30: =COUNTIFS('Тест-кейсы'!$B$2:$B$197,"Спецзаказ",'Тест-кейсы'!$N$2:$N$197,"Автоматизирован") | J30: =IF(B30=0,0,I30/B30) | K30: =COUNTIFS('Тест-кейсы'!$B$2:$B$197,"Спецзаказ",'Тест-кейсы'!$P$2:$P$197,"Passed") | L30: =COUNTIFS('Тест-кейсы'!$B$2:$B$197,"Спецзаказ",'Тест-кейсы'!$P$2:$P$197,"Failed") | M30: =COUNTIFS('Тест-кейсы'!$B$2:$B$197,"Спецзаказ",'Тест-кейсы'!$P$2:$P$197,"Blocked") | N30: =COUNTIFS('Тест-кейсы'!$B$2:$B$197,"Спецзаказ",'Тест-кейсы'!$P$2:$P$197,"Skipped") | O30: =COUNTIFS('Тест-кейсы'!$B$2:$B$197,"Спецзаказ",'Тест-кейсы'!$P$2:$P$197,"Не выполнен")
A31: MST — Особенности роли «Мастер» | B31: =COUNTIF('Тест-кейсы'!$B$2:$B$197,"Особенности роли «Мастер»") | C31: =COUNTIFS('Тест-кейсы'!$B$2:$B$197,"Особенности роли «Мастер»",'Тест-кейсы'!$E$2:$E$197,"P1") | D31: =COUNTIFS('Тест-кейсы'!$B$2:$B$197,"Особенности роли «Мастер»",'Тест-кейсы'!$E$2:$E$197,"P2") | E31: =COUNTIFS('Тест-кейсы'!$B$2:$B$197,"Особенности роли «Мастер»",'Тест-кейсы'!$E$2:$E$197,"P3") | F31: =COUNTIFS('Тест-кейсы'!$B$2:$B$197,"Особенности роли «Мастер»",'Тест-кейсы'!$L$2:$L$197,"Да") | G31: =COUNTIFS('Тест-кейсы'!$B$2:$B$197,"Особенности роли «Мастер»",'Тест-кейсы'!$L$2:$L$197,"Частично") | H31: =COUNTIFS('Тест-кейсы'!$B$2:$B$197,"Особенности роли «Мастер»",'Тест-кейсы'!$L$2:$L$197,"Нет") | I31: =COUNTIFS('Тест-кейсы'!$B$2:$B$197,"Особенности роли «Мастер»",'Тест-кейсы'!$N$2:$N$197,"Автоматизирован") | J31: =IF(B31=0,0,I31/B31) | K31: =COUNTIFS('Тест-кейсы'!$B$2:$B$197,"Особенности роли «Мастер»",'Тест-кейсы'!$P$2:$P$197,"Passed") | L31: =COUNTIFS('Тест-кейсы'!$B$2:$B$197,"Особенности роли «Мастер»",'Тест-кейсы'!$P$2:$P$197,"Failed") | M31: =COUNTIFS('Тест-кейсы'!$B$2:$B$197,"Особенности роли «Мастер»",'Тест-кейсы'!$P$2:$P$197,"Blocked") | N31: =COUNTIFS('Тест-кейсы'!$B$2:$B$197,"Особенности роли «Мастер»",'Тест-кейсы'!$P$2:$P$197,"Skipped") | O31: =COUNTIFS('Тест-кейсы'!$B$2:$B$197,"Особенности роли «Мастер»",'Тест-кейсы'!$P$2:$P$197,"Не выполнен")
A32: L10N — Локализация | B32: =COUNTIF('Тест-кейсы'!$B$2:$B$197,"Локализация") | C32: =COUNTIFS('Тест-кейсы'!$B$2:$B$197,"Локализация",'Тест-кейсы'!$E$2:$E$197,"P1") | D32: =COUNTIFS('Тест-кейсы'!$B$2:$B$197,"Локализация",'Тест-кейсы'!$E$2:$E$197,"P2") | E32: =COUNTIFS('Тест-кейсы'!$B$2:$B$197,"Локализация",'Тест-кейсы'!$E$2:$E$197,"P3") | F32: =COUNTIFS('Тест-кейсы'!$B$2:$B$197,"Локализация",'Тест-кейсы'!$L$2:$L$197,"Да") | G32: =COUNTIFS('Тест-кейсы'!$B$2:$B$197,"Локализация",'Тест-кейсы'!$L$2:$L$197,"Частично") | H32: =COUNTIFS('Тест-кейсы'!$B$2:$B$197,"Локализация",'Тест-кейсы'!$L$2:$L$197,"Нет") | I32: =COUNTIFS('Тест-кейсы'!$B$2:$B$197,"Локализация",'Тест-кейсы'!$N$2:$N$197,"Автоматизирован") | J32: =IF(B32=0,0,I32/B32) | K32: =COUNTIFS('Тест-кейсы'!$B$2:$B$197,"Локализация",'Тест-кейсы'!$P$2:$P$197,"Passed") | L32: =COUNTIFS('Тест-кейсы'!$B$2:$B$197,"Локализация",'Тест-кейсы'!$P$2:$P$197,"Failed") | M32: =COUNTIFS('Тест-кейсы'!$B$2:$B$197,"Локализация",'Тест-кейсы'!$P$2:$P$197,"Blocked") | N32: =COUNTIFS('Тест-кейсы'!$B$2:$B$197,"Локализация",'Тест-кейсы'!$P$2:$P$197,"Skipped") | O32: =COUNTIFS('Тест-кейсы'!$B$2:$B$197,"Локализация",'Тест-кейсы'!$P$2:$P$197,"Не выполнен")
A33: MOB — Мобильная версия | B33: =COUNTIF('Тест-кейсы'!$B$2:$B$197,"Мобильная версия") | C33: =COUNTIFS('Тест-кейсы'!$B$2:$B$197,"Мобильная версия",'Тест-кейсы'!$E$2:$E$197,"P1") | D33: =COUNTIFS('Тест-кейсы'!$B$2:$B$197,"Мобильная версия",'Тест-кейсы'!$E$2:$E$197,"P2") | E33: =COUNTIFS('Тест-кейсы'!$B$2:$B$197,"Мобильная версия",'Тест-кейсы'!$E$2:$E$197,"P3") | F33: =COUNTIFS('Тест-кейсы'!$B$2:$B$197,"Мобильная версия",'Тест-кейсы'!$L$2:$L$197,"Да") | G33: =COUNTIFS('Тест-кейсы'!$B$2:$B$197,"Мобильная версия",'Тест-кейсы'!$L$2:$L$197,"Частично") | H33: =COUNTIFS('Тест-кейсы'!$B$2:$B$197,"Мобильная версия",'Тест-кейсы'!$L$2:$L$197,"Нет") | I33: =COUNTIFS('Тест-кейсы'!$B$2:$B$197,"Мобильная версия",'Тест-кейсы'!$N$2:$N$197,"Автоматизирован") | J33: =IF(B33=0,0,I33/B33) | K33: =COUNTIFS('Тест-кейсы'!$B$2:$B$197,"Мобильная версия",'Тест-кейсы'!$P$2:$P$197,"Passed") | L33: =COUNTIFS('Тест-кейсы'!$B$2:$B$197,"Мобильная версия",'Тест-кейсы'!$P$2:$P$197,"Failed") | M33: =COUNTIFS('Тест-кейсы'!$B$2:$B$197,"Мобильная версия",'Тест-кейсы'!$P$2:$P$197,"Blocked") | N33: =COUNTIFS('Тест-кейсы'!$B$2:$B$197,"Мобильная версия",'Тест-кейсы'!$P$2:$P$197,"Skipped") | O33: =COUNTIFS('Тест-кейсы'!$B$2:$B$197,"Мобильная версия",'Тест-кейсы'!$P$2:$P$197,"Не выполнен")
A34: GEN — Общие проверки | B34: =COUNTIF('Тест-кейсы'!$B$2:$B$197,"Общие проверки") | C34: =COUNTIFS('Тест-кейсы'!$B$2:$B$197,"Общие проверки",'Тест-кейсы'!$E$2:$E$197,"P1") | D34: =COUNTIFS('Тест-кейсы'!$B$2:$B$197,"Общие проверки",'Тест-кейсы'!$E$2:$E$197,"P2") | E34: =COUNTIFS('Тест-кейсы'!$B$2:$B$197,"Общие проверки",'Тест-кейсы'!$E$2:$E$197,"P3") | F34: =COUNTIFS('Тест-кейсы'!$B$2:$B$197,"Общие проверки",'Тест-кейсы'!$L$2:$L$197,"Да") | G34: =COUNTIFS('Тест-кейсы'!$B$2:$B$197,"Общие проверки",'Тест-кейсы'!$L$2:$L$197,"Частично") | H34: =COUNTIFS('Тест-кейсы'!$B$2:$B$197,"Общие проверки",'Тест-кейсы'!$L$2:$L$197,"Нет") | I34: =COUNTIFS('Тест-кейсы'!$B$2:$B$197,"Общие проверки",'Тест-кейсы'!$N$2:$N$197,"Автоматизирован") | J34: =IF(B34=0,0,I34/B34) | K34: =COUNTIFS('Тест-кейсы'!$B$2:$B$197,"Общие проверки",'Тест-кейсы'!$P$2:$P$197,"Passed") | L34: =COUNTIFS('Тест-кейсы'!$B$2:$B$197,"Общие проверки",'Тест-кейсы'!$P$2:$P$197,"Failed") | M34: =COUNTIFS('Тест-кейсы'!$B$2:$B$197,"Общие проверки",'Тест-кейсы'!$P$2:$P$197,"Blocked") | N34: =COUNTIFS('Тест-кейсы'!$B$2:$B$197,"Общие проверки",'Тест-кейсы'!$P$2:$P$197,"Skipped") | O34: =COUNTIFS('Тест-кейсы'!$B$2:$B$197,"Общие проверки",'Тест-кейсы'!$P$2:$P$197,"Не выполнен")
A35: ИТОГО | B35: =SUM(B14:B34) | C35: =SUM(C14:C34) | D35: =SUM(D14:D34) | E35: =SUM(E14:E34) | F35: =SUM(F14:F34) | G35: =SUM(G14:G34) | H35: =SUM(H14:H34) | I35: =SUM(I14:I34) | J35: =IF(B35=0,0,I35/B35) | K35: =SUM(K14:K34) | L35: =SUM(L14:L34) | M35: =SUM(M14:M34) | N35: =SUM(N14:N34) | O35: =SUM(O14:O34)
A37: Легенда
A38: P1 — критичный | B38: Блокирует релиз. Smoke-набор: прогоняется всегда.
A39: P2 — высокий | B39: Важный функционал, прогоняется в полном регрессе.
A40: P3 — средний | B40: UI/второстепенное, при нехватке времени можно отложить.
A41: Можно автоматизировать: Да | B41: Сценарий стабилен и полностью проверяется через UI (Playwright).
A42: Можно автоматизировать: Частично | B42: Нужны SMS/OTP, админка/API для подготовки данных или визуальная оценка.
A43: Можно автоматизировать: Нет | B43: Требует реального устройства или деструктивно — только вручную.
A44: Статус: Автоматизирован | B44: Есть автотест в репозитории aros-ui (колонка «Автотест»).
A45: Результат прогона | B45: Выбирается из списка: Passed / Failed / Blocked / Skipped / Не выполнен.
A46: Тип | B46: Smoke, Functional, Negative, UI, Security, Integration, Technical, Non-functional.
A47: Требование / источник | B47: PRD из Confluence (лист «Источники») или «Проверено на staging». Integration — нужен шаг в админке.

Sheet Тест-кейсы
A1: ID | B1: Модуль | C1: Подмодуль | D1: Название тест-кейса | E1: Приоритет | F1: Тип | G1: Предусловия | H1: Шаги | I1: Тестовые данные | J1: Ожидаемый результат | K1: Требование / источник | L1: Можно автоматизировать (UI) | M1: Комментарий по автоматизации | N1: Статус UI-автоматизации | O1: Автотест (класс#метод) | P1: Результат прогона | Q1: Комментарий / ссылка на баг
A2: AUTH-001 | B2: Авторизация и сессия | C2: Вход по паролю | D2: Успешный вход по номеру телефона и паролю | E2: P1 | F2: Smoke | G2: Пользователь НЕ авторизован | H2: 1. Открыть главную страницу 2. Нажать «Войти» в шапке 3. Переключиться на вход по паролю 4. Ввести телефон и пароль мастера 5. Нажать «Войти» | I2: Телефон: +998998987882 Пароль: <пароль в .env> в .env> | J2: Модальное окно закрылось, в шапке отображается имя пользователя «Шохрух», в профиле статус «Мастер» | L2: Да | M2: Стабильный сценарий, тестовые креды в .env | N2: Автоматизирован | O2: storefront/auth/LoginTest#successfulLoginWithValidCredentials | P2: Не выполнен
A3: AUTH-002 | B3: Авторизация и сессия | C3: Вход по паролю | D3: Вход с неверным паролем | E3: P1 | F3: Negative | G3: Пользователь НЕ авторизован | H3: 1. Открыть форму входа, режим «по паролю» 2. Ввести валидный телефон и неверный пароль 3. Нажать «Войти» | I3: Пароль: WrongPass123 | J3: Показано сообщение об ошибке, пользователь не авторизован, форма остаётся открытой | L3: Да | N3: Автоматизирован | O3: storefront/auth/LoginTest#loginFailsWithWrongPassword | P3: Не выполнен
A4: AUTH-003 | B4: Авторизация и сессия | C4: Вход по паролю | D4: Вход с некорректным форматом телефона | E4: P2 | F4: Negative | G4: Пользователь НЕ авторизован | H4: 1. Открыть форму входа 2. Ввести телефон неверного формата (короткий, буквы) 3. Ввести пароль, нажать «Войти» | I4: Набор: 123, abc, +99899 | J4: Валидация поля телефона, запрос на вход не отправляется / ошибка, вход не выполнен | L4: Да | M4: Параметризованный тест | N4: Автоматизирован | O4: storefront/auth/LoginTest#loginFailsWithInvalidPhoneFormat | P4: Не выполнен
A5: AUTH-004 | B5: Авторизация и сессия | C5: Вход по паролю | D5: Вход с пустым паролем | E5: P2 | F5: Negative | G5: Пользователь НЕ авторизован | H5: 1. Открыть форму входа (по паролю) 2. Ввести телефон, пароль оставить пустым 3. Нажать «Войти» | J5: Кнопка неактивна или показана ошибка «обязательное поле», вход не выполнен | L5: Да | N5: Автоматизирован | O5: storefront/auth/LoginTest#loginFailsWithEmptyPassword | P5: Не выполнен
A6: AUTH-005 | B6: Авторизация и сессия | C6: Вход по паролю | D6: Вход с пустым номером телефона | E6: P2 | F6: Negative | G6: Пользователь НЕ авторизован | H6: 1. Открыть форму входа (по паролю) 2. Телефон оставить пустым, ввести пароль 3. Нажать «Войти» | J6: Кнопка неактивна или показана ошибка валидации, вход не выполнен | L6: Да | N6: Автоматизирован | O6: storefront/auth/LoginTest#loginFailsWithEmptyPhoneNumber | P6: Не выполнен
A7: AUTH-006 | B7: Авторизация и сессия | C7: Вход по паролю | D7: Маскировка пароля и кнопка «показать/скрыть» | E7: P3 | F7: UI | G7: Пользователь НЕ авторизован | H7: 1. Открыть форму входа (по паролю) 2. Ввести пароль 3. Нажать на иконку «глаз» дважды | J7: По умолчанию пароль скрыт (type=password); после 1-го клика виден, после 2-го снова скрыт | L7: Да | N7: Автоматизирован | O7: storefront/auth/LoginTest#passwordIsMaskedByDefaultAndToggleRevealsIt | P7: Не выполнен
A8: AUTH-007 | B8: Авторизация и сессия | C8: Режимы входа | D8: Переключение между входом по SMS и по паролю | E8: P2 | F8: Functional | G8: Пользователь НЕ авторизован | H8: 1. Открыть форму входа 2. Переключиться на «по паролю» 3. Переключиться обратно на «по телефону» | J8: Поля формы меняются в соответствии с режимом, введённый телефон не теряется | L8: Да | N8: Автоматизирован | O8: storefront/auth/LoginTest#switchingBetweenPhoneAndPasswordLoginModes | P8: Не выполнен
A9: AUTH-008 | B9: Авторизация и сессия | C9: Вход по SMS | D9: Успешный вход по SMS-коду (OTP) | E9: P1 | F9: Smoke | G9: Пользователь НЕ авторизован | H9: 1. Открыть форму входа (по телефону) 2. Ввести номер мастера, нажать «Получить код» 3. Ввести код из SMS 4. Подтвердить | I9: Телефон: +998998987882 | J9: Пользователь авторизован, в шапке имя пользователя | L9: Частично | M9: OTP по SMS отложен (решение по планированию): нужен тестовый шлюз или фиксированный код | N9: Не автоматизирован | P9: Не выполнен
A10: AUTH-009 | B10: Авторизация и сессия | C10: Вход по SMS | D10: Вход с неверным SMS-кодом | E10: P2 | F10: Negative | G10: Пользователь НЕ авторизован | H10: 1. Запросить код на номер мастера 2. Ввести неверный код 3. Подтвердить | I10: Код: 000000 | J10: Сообщение «Неверный код», вход не выполнен | L10: Частично | M10: OTP по SMS отложен (решение по планированию) | N10: Не автоматизирован | P10: Не выполнен
A11: AUTH-010 | B11: Авторизация и сессия | C11: Вход по SMS | D11: Таймер и повторная отправка SMS-кода | E11: P3 | F11: Functional | G11: Пользователь НЕ авторизован | H11: 1. Запросить код 2. Дождаться окончания таймера 3. Нажать «Отправить повторно» | J11: До окончания таймера повторная отправка недоступна; после — код отправляется повторно, таймер перезапускается | L11: Частично | M11: OTP по SMS отложен (решение по планированию) | N11: Не автоматизирован | P11: Не выполнен
A12: AUTH-011 | B12: Авторизация и сессия | C12: Восстановление пароля | D12: Восстановление пароля через «Забыли пароль?» | E12: P2 | F12: Functional | G12: Пользователь НЕ авторизован | H12: 1. Открыть форму входа (по паролю) 2. Нажать «Забыли пароль?» 3. Ввести телефон, подтвердить SMS-кодом 4. Задать новый пароль и войти с ним | J12: Пароль изменён, вход с новым паролем успешен, со старым — нет | L12: Частично | M12: Требует SMS-код — отложено вместе с OTP | N12: Не автоматизирован | P12: Не выполнен
A13: AUTH-012 | B13: Авторизация и сессия | C13: Сессия | D13: Сессия сохраняется после перезагрузки и в новой вкладке | E13: P1 | F13: Functional | G13: Пользователь авторизован как Мастер | H13: 1. Перезагрузить страницу (F5) 2. Открыть сайт в новой вкладке | J13: Пользователь остаётся авторизован в обоих случаях, корзина и имя в шапке на месте | L13: Да | M13: storageState Playwright | N13: Автоматизирован | O13: storefront/auth/SessionTest#sessionSurvivesReloadAndNewTab | P13: Не выполнен
A14: AUTH-013 | B14: Авторизация и сессия | C14: Выход | D14: Выход из системы | E14: P1 | F14: Smoke | G14: Пользователь авторизован как Мастер | H14: 1. Открыть «Профиль» 2. Нажать «Выйти из системы» 3. Подтвердить (если есть диалог) | J14: Пользователь разлогинен, в шапке кнопка «Войти», страницы /profile/* недоступны | L14: Да | N14: Автоматизирован | O14: storefront/auth/SessionTest#logoutReturnsToGuestState | P14: Не выполнен
A15: AUTH-014 | B15: Авторизация и сессия | C15: Доступ | D15: Закрытые страницы недоступны без авторизации | E15: P2 | F15: Security | G15: Пользователь НЕ авторизован | H15: 1. Открыть напрямую /ru/profile/account, /ru/profile/orders, /ru/confirmation | J15: Показывается форма входа или редирект на главную; личные данные не отображаются | L15: Да | M15: Проверено, что данные не показываются; но гость остаётся на пустом экране (AUTH-X03) | N15: Частично автоматизирован | O15: storefront/auth/GuestAccessTest#privatePagesShowNoDataToGuest | P15: Не выполнен
A16: AUTH-015 | B16: Авторизация и сессия | C16: Доступ | D16: Оформление заказа неавторизованным пользователем требует входа | E16: P2 | F16: Functional | G16: Пользователь НЕ авторизован | H16: 1. Добавить товар в корзину 2. Перейти в корзину 3. Нажать «Оформить» | J16: Открывается форма входа; после входа пользователь возвращается к оформлению, корзина сохранена | L16: Да | N16: Автоматизирован | O16: storefront/auth/GuestAccessTest#checkoutAsGuestRequiresSignIn | P16: Не выполнен
A17: HDR-001 | B17: Шапка, футер и навигация | C17: Шапка | D17: Логотип ведёт на главную | E17: P3 | F17: UI | G17: Пользователь авторизован как Мастер | H17: 1. Открыть любую внутреннюю страницу 2. Нажать на логотип Aros | J17: Открыта главная страница /ru | L17: Да | N17: Автоматизирован | O17: storefront/header/HeaderFooterTest#logoLeadsToHome | P17: Не выполнен
A18: HDR-002 | B18: Шапка, футер и навигация | C18: Шапка | D18: Контакты и режим работы в шапке | E18: P3 | F18: UI | G18: Пользователь авторизован как Мастер | H18: 1. Открыть главную 2. Проверить блок «Связаться» и «Режим работы» | J18: Телефон +998 91 812 77 70 (ссылка tel:), режим 09:00–20:00 (Пн–Сб) | L18: Да | M18: Проверка текста и href | N18: Автоматизирован | O18: storefront/header/HeaderFooterTest#topBarShowsPhoneAndWorkingHours | P18: Не выполнен
A19: HDR-003 | B19: Шапка, футер и навигация | C19: Выбор магазина | D19: Открытие окна выбора магазина | E19: P2 | F19: Functional | G19: Пользователь авторизован как Мастер | H19: 1. Нажать на название магазина в шапке («Урикзор Мобильный Центр») | J19: Открыто окно «Выберите адрес»: поля «Область», «Район/Город», список магазинов с адресом, ориентиром, телефоном; кнопка «Сохранить» | L19: Да | M19: Проверено открытие окна и состав; фильтрация — HDR-004 вручную | N19: Частично автоматизирован | O19: storefront/header/HeaderFooterTest#storeDialogOpensWithShopList | P19: Не выполнен
A20: HDR-004 | B20: Шапка, футер и навигация | C20: Выбор магазина | D20: Фильтрация магазинов по области и району | E20: P2 | F20: Functional | G20: Пользователь авторизован как Мастер | H20: 1. Открыть окно выбора магазина 2. Выбрать область 3. Выбрать район/город | I20: Область: г. Ташкент | J20: Список магазинов отфильтрован по выбранной локации | L20: Да | M20: Каскад «область → район → магазины» нужно изучить отдельно; смена магазина влияет на остатки | N20: Не автоматизирован | P20: Не выполнен
A21: HDR-005 | B21: Шапка, футер и навигация | C21: Выбор магазина | D21: Смена магазина и сохранение | E21: P1 | F21: Functional | G21: Пользователь авторизован как Мастер | H21: 1. Открыть окно выбора магазина 2. Выбрать другой магазин (например, «Изза Шоурум») 3. Нажать «Сохранить» 4. Открыть любой товар | J21: В шапке отображается выбранный магазин; наличие и сроки доставки товаров пересчитаны под него; выбор сохраняется после перезагрузки | L21: Частично | M21: Смена магазина меняет данные пользователя — проверять вручную | N21: Не автоматизирован | P21: Не выполнен
A22: HDR-006 | B22: Шапка, футер и навигация | C22: Шапка | D22: Иконки корзины, избранного и профиля | E22: P2 | F22: UI | G22: Пользователь авторизован как Мастер | H22: 1. Нажать иконку корзины 2. Нажать иконку сердца 3. Нажать на имя пользователя | J22: Открываются /ru/cart, /ru/favourites, /ru/profile/account; на корзине бейдж с количеством позиций | L22: Да | N22: Автоматизирован | O22: storefront/header/HeaderFooterTest#headerIconsArePresent | P22: Не выполнен
A23: HDR-007 | B23: Шапка, футер и навигация | C23: Футер | D23: Ссылки блока «О нас» и «Для клиента» | E23: P2 | F23: Functional | G23: Пользователь авторизован как Мастер | H23: 1. Прокрутить вниз 2. По очереди открыть: О нас, Методы оплаты, Сотрудничество, Система баллов, Политика конфиденциальности, Публичная оферта, Доставка, Статус продукта, Гарантия продукта, Тип оплаты, Отзыв | J23: Каждая ссылка открывает страницу с контентом (не 404); страницы-заглушки /coming-soon зафиксировать как известные | L23: Да | M23: Проверка статуса и заголовков страниц | N23: Автоматизирован | O23: storefront/header/HeaderFooterTest#footerLinksAreReachable | P23: Не выполнен
A24: HDR-008 | B24: Шапка, футер и навигация | C24: Футер | D24: Контакты и соцсети в футере | E24: P3 | F24: UI | G24: Пользователь авторизован как Мастер | H24: 1. Проверить телефон, e-mail, адрес, Telegram, иконки соцсетей | J24: tel:, mailto:, ссылки Telegram/Instagram/YouTube/LinkedIn ведут на корректные внешние адреса и открываются в новой вкладке | L24: Частично | M24: Проверяем только href, внешние сайты не открываем | N24: Автоматизирован | O24: storefront/header/HeaderFooterTest#footerContactsArePresent | P24: Не выполнен
A25: HDR-009 | B25: Шапка, футер и навигация | C25: Футер | D25: QR-код для скачивания приложения | E25: P3 | F25: UI | G25: Пользователь авторизован как Мастер | H25: 1. Найти блок «Наведите камеру и скачайте приложение» 2. Отсканировать QR-код телефоном | J25: QR-код отображается; при сканировании открывается страница приложения Aros Market в сторе | L25: Нет | M25: QR-код — визуальная проверка | N25: Не автоматизирован | P25: Не выполнен
A26: HOME-001 | B26: Главная страница | C26: Загрузка | D26: Главная страница загружается со всеми секциями | E26: P1 | F26: Smoke | G26: Пользователь авторизован как Мастер | H26: 1. Открыть https://staging.aros.uz/ru | J26: Отображаются: шапка, баннер-слайдер, «Товары со скидкой», «Новинки», «Популярное», футер; нет ошибок в консоли и 5xx запросов | L26: Да | N26: Автоматизирован | O26: storefront/home/HomeTest#homeLoadsWithAllSections | P26: Не выполнен
A27: HOME-002 | B27: Главная страница | C27: Баннеры | D27: Баннер-слайдер: стрелки и индикаторы | E27: P3 | F27: UI | G27: Пользователь авторизован как Мастер | H27: 1. Нажать стрелки влево/вправо 2. Нажать на точки-индикаторы 3. Подождать автопрокрутку | J27: Слайды переключаются; активная точка соответствует слайду; изображения не битые | L27: Частично | M27: Слайдер: нужен отдельный разбор (стрелки и точки без стабильных селекторов) | N27: Не автоматизирован | P27: Не выполнен
A28: HOME-003 | B28: Главная страница | C28: Секции | D28: «Товары со скидкой» → «Все» | E28: P2 | F28: Functional | G28: Пользователь авторизован как Мастер | H28: 1. В секции «Товары со скидкой» нажать «Все» | J28: Открыта /ru/sections/onsale со списком товаров со скидкой | L28: Да | N28: Автоматизирован | O28: storefront/home/HomeTest#allLinkOpensSectionPage | P28: Не выполнен
A29: HOME-004 | B29: Главная страница | C29: Секции | D29: «Новинки» → «Все» | E29: P2 | F29: Functional | G29: Пользователь авторизован как Мастер | H29: 1. В секции «Новинки» нажать «Все» | J29: Открыт список новинок, товары отсортированы от новых к старым | L29: Да | N29: Автоматизирован | O29: storefront/home/HomeTest#allLinkOpensSectionPage | P29: Не выполнен
A30: HOME-005 | B30: Главная страница | C30: Секции | D30: «Популярное» → «Все» | E30: P2 | F30: Functional | G30: Пользователь авторизован как Мастер | H30: 1. В секции «Популярное» нажать «Все» | J30: Открыт список популярных товаров | L30: Да | N30: Автоматизирован | O30: storefront/home/HomeTest#allLinkOpensSectionPage | P30: Не выполнен
A31: HOME-006 | B31: Главная страница | C31: Карточка товара | D31: Содержимое карточки товара в списке | E31: P2 | F31: UI | G31: Пользователь авторизован как Мастер | H31: 1. Осмотреть карточки на главной | J31: У каждой карточки: изображение, название с ID, рейтинг и кол-во комментариев, цена в сумах, (если скидка) зачёркнутая старая цена и бейдж «-N%», кнопка корзины, сердечко | L31: Да | N31: Автоматизирован | O31: storefront/home/HomeTest#productCardContainsMainElements | P31: Не выполнен
A32: HOME-007 | B32: Главная страница | C32: Карточка товара | D32: Корректность процента скидки | E32: P2 | F32: Functional | G32: Пользователь авторизован как Мастер | H32: 1. Взять карточку со скидкой 2. Посчитать (старая − новая) / старая × 100 | I32: Пример: 30 000 → 25 000 = -17% | J32: Бейдж совпадает с расчётом (с округлением) | L32: Да | M32: Расчёт в коде теста | N32: Автоматизирован | O32: storefront/home/HomeTest#discountBadgeMatchesPrices | P32: Не выполнен
A33: HOME-008 | B33: Главная страница | C33: Карточка товара | D33: Клик по карточке открывает страницу товара | E33: P1 | F33: Functional | G33: Пользователь авторизован как Мастер | H33: 1. Нажать на название/изображение карточки | J33: Открыта страница товара с тем же pvId и названием | L33: Да | N33: Автоматизирован | O33: storefront/home/HomeTest#clickingCardOpensProductPage | P33: Не выполнен
A34: CAT-001 | B34: Каталог, категории и фильтры | C34: Меню каталога | D34: Открытие меню «Каталог» | E34: P1 | F34: Smoke | G34: Пользователь авторизован как Мастер | H34: 1. Нажать «Каталог» в шапке | J34: Открыто меню: слева список категорий, справа плитки категорий с количеством разделов; иконки отображаются | L34: Да | N34: Автоматизирован | O34: storefront/catalog/CatalogTest#catalogMenuOpensWithCategories | P34: Не выполнен
A35: CAT-002 | B35: Каталог, категории и фильтры | C35: Меню каталога | D35: Навигация по подкатегориям | E35: P2 | F35: Functional | G35: Пользователь авторизован как Мастер | H35: 1. Открыть «Каталог» 2. Навести/нажать на категорию слева (например, «Запчасти для телефонов») | J35: Отображаются подкатегории выбранной категории | L35: Да | M35: Структура подменю категорий требует разведки (глубина вложенности меняется) | N35: Не автоматизирован | P35: Не выполнен
A36: CAT-003 | B36: Каталог, категории и фильтры | C36: Страница категории | D36: Переход в категорию | E36: P1 | F36: Smoke | G36: Пользователь авторизован как Мастер | H36: 1. Открыть «Каталог» 2. Выбрать «Запчасти для телефонов» | J36: Открыта /ru/filter?categories=45, заголовок категории, хлебные крошки, фильтры, товары только этой категории | L36: Да | M36: Структура подменю категорий требует разведки | N36: Не автоматизирован | P36: Не выполнен
A37: CAT-004 | B37: Каталог, категории и фильтры | C37: Фильтры | D37: Фильтр по цене (ввод значений) | E37: P1 | F37: Functional | G37: Пользователь авторизован как Мастер | H37: 1. Открыть категорию 2. Ввести «от» и «до» в фильтре «Цена» 3. Применить («Показать») | I37: От 5 000 до 10 000 | J37: Все товары в выдаче имеют цену в заданном диапазоне | L37: Да | M37: Проверен ввод значения «от»; поле «до» — вручную | N37: Частично автоматизирован | O37: storefront/catalog/CatalogTest#priceFromFilterWorks | P37: Не выполнен
A38: CAT-005 | B38: Каталог, категории и фильтры | C38: Фильтры | D38: Фильтр по цене (ползунок) | E38: P2 | F38: Functional | G38: Пользователь авторизован как Мастер | H38: 1. Перетащить левый и правый ползунки цены | J38: Значения в полях синхронизируются с ползунком, выдача обновляется | L38: Частично | M38: Ползунок цены — drag-and-drop, нестабилен; значения проверены в CAT-004 | N38: Не автоматизирован | P38: Не выполнен
A39: CAT-006 | B39: Каталог, категории и фильтры | C39: Фильтры | D39: Цена «от» больше цены «до» | E39: P3 | F39: Negative | G39: Пользователь авторизован как Мастер | H39: 1. Ввести «от» = 100 000, «до» = 1 000 | J39: Значения автоматически корректируются или показана ошибка; страница не ломается | L39: Да | N39: Автоматизирован | O39: storefront/catalog/CatalogTest#priceFromGreaterThanToDoesNotBreakPage | P39: Не выполнен
A40: CAT-007 | B40: Каталог, категории и фильтры | C40: Фильтры | D40: Тумблер «Только в наличии» | E40: P1 | F40: Functional | G40: Пользователь авторизован как Мастер | H40: 1. Открыть категорию 2. Включить «Только в наличии» | J40: В выдаче нет карточек с меткой «Нет в наличии»; при выключении такие товары снова видны | L40: Да | N40: Автоматизирован | O40: storefront/catalog/CatalogTest#inStockToggleSwitches | P40: Не выполнен
A41: CAT-008 | B41: Каталог, категории и фильтры | C41: Фильтры | D41: «Очистить все фильтры» | E41: P2 | F41: Functional | G41: Пользователь авторизован как Мастер | H41: 1. Применить фильтр цены и «Только в наличии» 2. Нажать «Очистить все фильтры» | J41: Все фильтры сброшены, выдача вернулась к исходной | L41: Да | N41: Автоматизирован | O41: storefront/catalog/CatalogTest#clearAllFiltersResetsSelection | P41: Не выполнен
A42: CAT-009 | B42: Каталог, категории и фильтры | C42: Сортировка | D42: Сортировка «Сначала дешевые» | E42: P2 | F42: Functional | G42: Пользователь авторизован как Мастер | H42: 1. Открыть категорию 2. В «Сортировка» выбрать «Сначала дешевые» | J42: Цены в выдаче идут по возрастанию | L42: Да | N42: Автоматизирован | O42: storefront/catalog/CatalogTest#sortingCheapFirst | P42: Не выполнен
A43: CAT-010 | B43: Каталог, категории и фильтры | C43: Сортировка | D43: Сортировка «Сначала дорогие» | E43: P2 | F43: Functional | G43: Пользователь авторизован как Мастер | H43: 1. Выбрать «Сначала дорогие» | J43: Цены в выдаче идут по убыванию | L43: Да | N43: Автоматизирован | O43: storefront/catalog/CatalogTest#sortingExpensiveFirst | P43: Не выполнен
A44: CAT-011 | B44: Каталог, категории и фильтры | C44: Сортировка | D44: Сортировка «Сначала новые» / «Сначала старые» | E44: P3 | F44: Functional | G44: Пользователь авторизован как Мастер | H44: 1. Выбрать «Сначала новые» 2. Выбрать «Сначала старые» | J44: Порядок товаров меняется (ID товаров по убыванию / возрастанию) | L44: Частично | M44: Сортировки «старые/новые» зависят от дат в данных | N44: Не автоматизирован | P44: Не выполнен
A45: CAT-012 | B45: Каталог, категории и фильтры | C45: Выдача | D45: Подгрузка товаров при прокрутке | E45: P2 | F45: Functional | G45: Пользователь авторизован как Мастер | H45: 1. Открыть категорию с большим количеством товаров 2. Прокрутить до конца страницы | J45: Подгружается следующая порция товаров, дубликатов нет | L45: Да | N45: Автоматизирован | O45: storefront/catalog/CatalogTest#showMoreLoadsNextPage | P45: Не выполнен
A46: CAT-013 | B46: Каталог, категории и фильтры | C46: Выдача | D46: Товар «Нет в наличии» в списке | E46: P1 | F46: Functional | G46: Пользователь авторизован как Мастер | H46: 1. Найти карточку с меткой «Нет в наличии» | J46: Кнопка добавления в корзину неактивна (серая), товар добавить нельзя | L46: Да | M46: Нужен заведомо отсутствующий на складе товар — данные нестабильны | N46: Не автоматизирован | P46: Не выполнен
A47: CAT-014 | B47: Каталог, категории и фильтры | C47: Выдача | D47: Быстрый просмотр товара | E47: P3 | F47: Functional | G47: Пользователь авторизован как Мастер | H47: 1. Навести на карточку 2. Нажать «Быстрый просмотр» | J47: Открыто окно с основной информацией о товаре, его можно закрыть | L47: Да | M47: «Быстрый просмотр» появляется только при наведении — нужен отдельный разбор | N47: Не автоматизирован | P47: Не выполнен
A48: CAT-015 | B48: Каталог, категории и фильтры | C48: Выдача | D48: Фильтры и сортировка сохраняются после перезагрузки | E48: P3 | F48: Functional | G48: Пользователь авторизован как Мастер | H48: 1. Применить фильтр и сортировку 2. Обновить страницу | J48: Параметры отражены в URL и восстановлены после перезагрузки | L48: Да | N48: Автоматизирован | O48: storefront/catalog/CatalogTest#filtersSurviveReload | P48: Не выполнен
A49: CAT-016 | B49: Каталог, категории и фильтры | C49: Выдача | D49: Пустая выдача по фильтру | E49: P3 | F49: Functional | G49: Пользователь авторизован как Мастер | H49: 1. Задать фильтр цены, под который нет товаров | J49: Показано понятное сообщение об отсутствии товаров, кнопка сброса фильтров | L49: Да | N49: Автоматизирован | O49: storefront/catalog/CatalogTest#emptyResultShowsMessageAndShowAll | P49: Не выполнен
A50: CAT-017 | B50: Каталог, категории и фильтры | C50: Навигация | D50: Хлебные крошки в категории | E50: P3 | F50: UI | G50: Пользователь авторизован как Мастер | H50: 1. Перейти в подкатегорию 3-го уровня 2. Нажать на родительскую категорию в крошках | J50: Открыта родительская категория | L50: Да | N50: Автоматизирован | O50: storefront/catalog/CatalogTest#breadcrumbsLeadHome | P50: Не выполнен
A51: MDL-001 | B51: Подбор по модели устройства | C51: Бренд | D51: Открытие окна «Выберите бренд» | E51: P2 | F51: Functional | G51: Пользователь авторизован как Мастер | H51: 1. Нажать «Модель» в шапке | J51: Открыто окно со списком брендов (Samsung, Xiaomi, Apple…) и полем поиска | L51: Да | N51: Автоматизирован | O51: storefront/header/HeaderFooterTest#modelDialogShowsBrands | P51: Не выполнен
A52: MDL-002 | B52: Подбор по модели устройства | C52: Бренд | D52: Поиск бренда | E52: P3 | F52: Functional | G52: Пользователь авторизован как Мастер | H52: 1. Открыть окно «Модель» 2. Ввести «Xiao» | J52: Список отфильтрован, виден Xiaomi | L52: Да | N52: Автоматизирован | O52: storefront/catalog/ModelPickerTest#brandSearchNarrowsList | P52: Не выполнен
A53: MDL-003 | B53: Подбор по модели устройства | C53: Модель | D53: Выбор бренда и поиск модели | E53: P2 | F53: Functional | G53: Пользователь авторизован как Мастер | H53: 1. Выбрать Samsung 2. Ввести в поиске «A52» | J53: Открыт список моделей Samsung; поиск находит Galaxy A52 (A525) | L53: Да | N53: Автоматизирован | O53: storefront/catalog/ModelPickerTest#selectingBrandShowsModels | P53: Не выполнен
A54: MDL-004 | B54: Подбор по модели устройства | C54: Категория | D54: Выбор модели и категории запчастей → список товаров | E54: P1 | F54: Functional | G54: Пользователь авторизован как Мастер | H54: 1. «Модель» → Samsung → Galaxy A52 (A525) 2. Выбрать категорию «Дисплеи» | J54: Открыта выдача товаров категории «Дисплеи», совместимых с Galaxy A52 | L54: Да | M54: Проверен путь Samsung → Galaxy → «Аккумуляторы» | N54: Частично автоматизирован | O54: storefront/catalog/ModelPickerTest#brandModelCategoryLeadsToProductList | P54: Не выполнен
A55: MDL-005 | B55: Подбор по модели устройства | C55: Навигация | D55: Кнопка «Назад» и закрытие окна | E55: P3 | F55: UI | G55: Пользователь авторизован как Мастер | H55: 1. Пройти бренд → модель 2. Нажать «←» 3. Нажать «×» | J55: «←» возвращает на предыдущий шаг; «×» закрывает окно | L55: Да | N55: Автоматизирован | O55: storefront/catalog/ModelPickerTest#backAndCloseButtonsWork | P55: Не выполнен
A56: SRCH-001 | B56: Поиск | C56: Поиск | D56: Поиск по точному названию товара | E56: P1 | F56: Smoke | G56: Пользователь авторизован как Мастер | H56: 1. Ввести в поиск название реального товара 2. Нажать Enter | I56: Название берётся динамически с главной | J56: Товар найден в выдаче /ru/filter?query=... | L56: Да | N56: Автоматизирован | O56: storefront/catalog/SearchTest#searchingByRealProductNameFindsThatProduct | P56: Не выполнен
A57: SRCH-002 | B57: Поиск | C57: Поиск | D57: Все результаты релевантны запросу | E57: P2 | F57: Functional | G57: Пользователь авторизован как Мастер | H57: 1. Ввести запрос (например, «Samsung») 2. Проверить названия всех карточек | J57: Каждое название содержит запрос | L57: Да | N57: Автоматизирован | O57: storefront/catalog/SearchTest#searchResultsAreRelevantToQuery | P57: Не выполнен
A58: SRCH-003 | B58: Поиск | C58: Поиск | D58: Поиск по несуществующему запросу | E58: P2 | F58: Negative | G58: Пользователь авторизован как Мастер | H58: 1. Ввести случайную строку | I58: qwertyzxcv12345 | J58: Показано пустое состояние «нет товаров» | L58: Да | N58: Автоматизирован | O58: storefront/catalog/SearchTest#searchingUnknownTermShowsEmptyState | P58: Не выполнен
A59: SRCH-004 | B59: Поиск | C59: Поиск | D59: Переход из результатов поиска на товар | E59: P1 | F59: Functional | G59: Пользователь авторизован как Мастер | H59: 1. Выполнить поиск 2. Нажать на первую карточку | J59: Открыта страница именно этого товара (pvId совпадает) | L59: Да | N59: Автоматизирован | O59: storefront/catalog/SearchTest#openingSearchResultNavigatesToMatchingProduct | P59: Не выполнен
A60: SRCH-005 | B60: Поиск | C60: Поиск | D60: Поиск по ID товара | E60: P2 | F60: Functional | G60: Пользователь авторизован как Мастер | H60: 1. Ввести ID товара | I60: 9824 | J60: В выдаче товар с ID 9824 | L60: Да | N60: Автоматизирован | O60: storefront/catalog/SearchExtraTest#searchByProductId | P60: Не выполнен
A61: SRCH-006 | B61: Поиск | C61: Поиск | D61: Запуск поиска кнопкой-лупой и клавишей Enter | E61: P3 | F61: Functional | G61: Пользователь авторизован как Мастер | H61: 1. Ввести запрос, нажать лупу 2. Повторить с Enter | J61: В обоих случаях открывается одинаковая выдача | L61: Да | N61: Автоматизирован | O61: storefront/catalog/SearchExtraTest#searchWorksViaEnterAndLoupeButton | P61: Не выполнен
A62: SRCH-007 | B62: Поиск | C62: Поиск | D62: Пустой запрос и запрос из пробелов | E62: P3 | F62: Negative | G62: Пользователь авторизован как Мастер | H62: 1. Нажать поиск с пустым полем 2. Ввести только пробелы | J62: Поиск не выполняется или открывается общий каталог без ошибок | L62: Да | N62: Автоматизирован | O62: storefront/catalog/SearchExtraTest#emptyAndWhitespaceQueries | P62: Не выполнен
A63: SRCH-008 | B63: Поиск | C63: Поиск | D63: Поиск кириллицей / латиницей / в разном регистре | E63: P3 | F63: Functional | G63: Пользователь авторизован как Мастер | H63: 1. Найти «samsung», «SAMSUNG», «Самсунг» | J63: Регистр не влияет; поведение для кириллицы соответствует ожиданиям бизнеса | L63: Да | N63: Автоматизирован | O63: storefront/catalog/SearchExtraTest#queryCaseDoesNotMatter | P63: Не выполнен
A64: SRCH-009 | B64: Поиск | C64: Поиск | D64: Фильтры и сортировка в результатах поиска | E64: P3 | F64: Functional | G64: Пользователь авторизован как Мастер | H64: 1. Выполнить поиск 2. Применить сортировку «Сначала дешевые» и «Только в наличии» | J64: Фильтры применяются к результатам поиска, запрос сохраняется | L64: Да | N64: Автоматизирован | O64: storefront/catalog/SearchExtraTest#filtersWorkInsideSearchResults | P64: Не выполнен
A65: PDP-001 | B65: Карточка товара | C65: Отображение | D65: Основные элементы страницы товара | E65: P1 | F65: Smoke | G65: Пользователь авторизован как Мастер | H65: 1. Открыть товар со скидкой | I65: pvId=9824 | J65: Название с (ID: N), хлебные крошки, галерея, цена, зачёркнутая старая цена, бейдж -%, цена в $, рейтинг, «Качество», остатки по складам, кнопки количества, избранного и «Быстрая покупка» | L65: Да | M65: Проверены название, цена, «Быстрая покупка», счётчик; галерея и склады — вручную | N65: Частично автоматизирован | O65: storefront/product/ProductPageTest#productPageShowsMainElements | P65: Не выполнен
A66: PDP-002 | B66: Карточка товара | C66: Варианты | D66: Переключение варианта «Качество» | E66: P1 | F66: Functional | G66: Пользователь авторизован как Мастер | H66: 1. Открыть товар с несколькими вариантами качества 2. Выбрать другой вариант | J66: Меняются цена, ID (pvId в URL), остатки; выбранный вариант подсвечен | L66: Да | M66: Нужен товар с несколькими вариантами «Качество» — данные нестабильны | N66: Не автоматизирован | P66: Не выполнен
A67: PDP-003 | B67: Карточка товара | C67: Наличие | D67: Остатки по складам | E67: P2 | F67: Functional | G67: Пользователь авторизован как Мастер | H67: 1. Открыть товар 2. Проверить блок складов | J67: Отображается количество по каждому складу; совпадает с данными в админке | L67: Частично | M67: Остатки по складам зависят от данных | N67: Не автоматизирован | P67: Не выполнен
A68: PDP-004 | B68: Карточка товара | C68: Количество | D68: Изменение количества (+/−/ручной ввод) | E68: P1 | F68: Functional | G68: Пользователь авторизован как Мастер | H68: 1. Нажать «+» дважды 2. Нажать «−» 3. Ввести число вручную | J68: Счётчик меняется корректно; товар добавляется в корзину; бейдж корзины обновляется | L68: Да | M68: Проверены кнопки «+» / «−»; ручной ввод — вручную | N68: Частично автоматизирован | O68: storefront/product/ProductPageTest#quantityStepperChangesValue | P68: Не выполнен
A69: PDP-005 | B69: Карточка товара | C69: Количество | D69: Нельзя добавить больше доступного остатка | E69: P1 | F69: Negative | G69: Пользователь авторизован как Мастер | H69: 1. Открыть товар с остатком N 2. Ввести количество N+1 | I69: Товар с остатком 3 | J69: Количество ограничено остатком или показано предупреждение | L69: Да | M69: Нужен товар с известным малым остатком — данные нестабильны (CART-010 проверяет то же в корзине) | N69: Не автоматизирован | P69: Не выполнен
A70: PDP-006 | B70: Карточка товара | C70: Покупка | D70: «Быстрая покупка» ведёт к оформлению | E70: P1 | F70: Functional | G70: Пользователь авторизован как Мастер | H70: 1. Открыть товар в наличии 2. Нажать «Быстрая покупка» | J70: Открыто оформление заказа с этим товаром; срок доставки на кнопке соответствует выбранному магазину | L70: Да | M70: «Быстрая покупка» может создать заказ — только вручную | N70: Не автоматизирован | P70: Не выполнен
A71: PDP-007 | B71: Карточка товара | C71: Избранное | D71: Добавление в избранное со страницы товара | E71: P2 | F71: Functional | G71: Пользователь авторизован как Мастер | H71: 1. Нажать сердечко на странице товара 2. Открыть «Избранное» | J71: Иконка закрашена, товар есть в избранном | L71: Да | M71: Страница «Избранное» на staging не найдена (/ru/favorites → 404) — функциональность требует уточнения | N71: Не автоматизирован | P71: Не выполнен
A72: PDP-008 | B72: Карточка товара | C72: Галерея | D72: Галерея изображений и полноэкранный просмотр | E72: P3 | F72: UI | G72: Пользователь авторизован как Мастер | H72: 1. Переключить миниатюры 2. Нажать иконку полноэкранного режима | J72: Изображение меняется; открывается увеличенный просмотр; изображения не битые | L72: Частично | M72: Галерея — визуальная проверка | N72: Не автоматизирован | P72: Не выполнен
A73: PDP-009 | B73: Карточка товара | C73: Нашли дешевле | D73: Форма «Нашли дешевле?» | E73: P3 | F73: Functional | G73: Пользователь авторизован как Мастер | H73: 1. Нажать «Нашли дешевле?» 2. Заполнить форму 3. Отправить | J73: Форма открывается, валидирует поля, после отправки — сообщение об успехе; заявка видна в админке | L73: Частично | M73: Форма «Нашли дешевле?» отправляет данные — вручную | N73: Не автоматизирован | P73: Не выполнен
A74: PDP-010 | B74: Карточка товара | C74: Рекомендации | D74: Блок «Ещё товары для <модель>» | E74: P3 | F74: Functional | G74: Пользователь авторизован как Мастер | H74: 1. Прокрутить к блоку рекомендаций 2. Пролистать стрелками 3. Открыть товар | J74: Карусель листается; товары относятся к той же модели; переход работает | L74: Да | N74: Автоматизирован | O74: storefront/product/ProductPageTest#moreProductsForModelBlock | P74: Не выполнен
A75: PDP-011 | B75: Карточка товара | C75: Наличие | D75: Страница товара не в наличии | E75: P1 | F75: Functional | G75: Пользователь авторизован как Мастер | H75: 1. Открыть товар, у выбранного варианта остаток 0 | J75: Кнопки количества и «Быстрая покупка» недоступны, видна метка «Нет в наличии»; авторизованному показана кнопка «Хотел бы купить» | K75: PRD Bo'lsa olar edim | L75: Да | M75: Нужен заведомо отсутствующий на складе товар | N75: Не автоматизирован | P75: Не выполнен
A76: PDP-012 | B76: Карточка товара | C76: Ошибки | D76: Несуществующий товар по прямой ссылке | E76: P3 | F76: Negative | G76: Пользователь авторизован как Мастер | H76: 1. Открыть /ru/product/xxx?pvId=99999999 | J76: Показана страница 404 / «товар не найден», без ошибки приложения | L76: Да | N76: Автоматизирован | O76: storefront/product/ProductPageTest#unknownProductShowsNotFound | P76: Не выполнен
A77: PDP-013 | B77: Карточка товара | C77: Хотел бы купить | D77: «Хотел бы купить» для товара без остатка | E77: P2 | F77: Functional | G77: Пользователь авторизован как Мастер; у выбранного варианта остаток 0 | H77: 1. Нажать «Хотел бы купить» 2. Указать количество 2 и комментарий 3. Отправить | J77: Окно с пояснением (без обязательств), количество по умолчанию 1 (минимум 1), необязательный комментарий; после отправки — «Спасибо за отзыв!», окно закрывается через ~2 с; кнопка остаётся; гостю кнопка не показывается | K77: PRD Bo'lsa olar edim §5–6 | L77: Да | M77: Нужен товар без остатка и вход пользователя | N77: Не автоматизирован | P77: Не выполнен
A78: FAV-001 | B78: Избранное | C78: Избранное | D78: Пустое избранное | E78: P3 | F78: UI | G78: Пользователь авторизован как Мастер; избранное пусто | H78: 1. Открыть /ru/favourites | J78: Сообщение «Ваших любимых товаров пока нет» и кнопка «Главная страница» | L78: Да | M78: Страница избранного не найдена на staging (см. PDP-007) | N78: Не автоматизирован | P78: Не выполнен
A79: FAV-002 | B79: Избранное | C79: Избранное | D79: Добавление товара в избранное из списка | E79: P2 | F79: Functional | G79: Пользователь авторизован как Мастер | H79: 1. На главной нажать сердечко у карточки 2. Открыть «Избранное» | J79: Товар отображается в избранном | L79: Да | M79: Страница избранного не найдена на staging; гость видит окно входа (FAV-X01) | N79: Не автоматизирован | P79: Не выполнен
A80: FAV-003 | B80: Избранное | C80: Избранное | D80: Удаление товара из избранного | E80: P2 | F80: Functional | G80: Пользователь авторизован как Мастер; в избранном есть товар | H80: 1. Нажать на закрашенное сердечко | J80: Товар удалён из избранного, иконка не закрашена | L80: Да | M80: Страница избранного не найдена на staging | N80: Не автоматизирован | P80: Не выполнен
A81: FAV-004 | B81: Избранное | C81: Избранное | D81: Избранное сохраняется после выхода и входа | E81: P3 | F81: Functional | G81: Пользователь авторизован как Мастер; в избранном есть товар | H81: 1. Выйти 2. Войти снова 3. Открыть «Избранное» | J81: Товар по-прежнему в избранном (хранится на сервере) | L81: Да | M81: Страница избранного не найдена на staging | N81: Не автоматизирован | P81: Не выполнен
A82: FAV-005 | B82: Избранное | C82: Избранное | D82: Добавление в корзину из избранного | E82: P3 | F82: Functional | G82: Пользователь авторизован как Мастер; в избранном есть товар | H82: 1. Нажать кнопку корзины на карточке в избранном | J82: Товар добавлен в корзину, бейдж обновился | L82: Да | M82: Страница избранного не найдена на staging | N82: Не автоматизирован | P82: Не выполнен
A83: CART-001 | B83: Корзина | C83: Добавление | D83: Добавление товара с карточки: степпер и бейдж | E83: P1 | F83: Smoke | G83: Пользователь авторизован как Мастер; корзина пуста | H83: 1. На главной нажать кнопку корзины у товара | J83: На карточке появился степпер с 1, бейдж корзины = 1, тост «Товар добавлен» | L83: Да | N83: Автоматизирован | O83: storefront/cart/CartTest#addingProductShowsStepperOnCardAndUpdatesCartBadge | P83: Не выполнен
A84: CART-002 | B84: Корзина | C84: Добавление | D84: Добавленный товар появляется в корзине с верным количеством | E84: P1 | F84: Smoke | G84: Пользователь авторизован как Мастер; корзина пуста | H84: 1. Добавить товар 2. Открыть корзину | J84: Товар в корзине, количество 1 | L84: Да | N84: Автоматизирован | O84: storefront/cart/CartTest#addedProductAppearsInCartPageWithCorrectQuantity | P84: Не выполнен
A85: CART-003 | B85: Корзина | C85: Количество | D85: Увеличение количества в корзине | E85: P1 | F85: Functional | G85: Пользователь авторизован как Мастер; в корзине 1 товар | H85: 1. Нажать «+» в строке товара | J85: Количество 2, «Количество товаров» и суммы пересчитаны | L85: Да | N85: Автоматизирован | O85: storefront/cart/CartTest#increasingQuantityInCartUpdatesItemsCount | P85: Не выполнен
A86: CART-004 | B86: Корзина | C86: Количество | D86: Уменьшение количества до нуля удаляет товар | E86: P2 | F86: Functional | G86: Пользователь авторизован как Мастер; в корзине 1 товар с кол-вом 1 | H86: 1. Нажать «−» | J86: Товар удалён, корзина пуста (empty state) | L86: Да | N86: Автоматизирован | O86: storefront/cart/CartTest#decreasingQuantityToZeroRemovesItemAndEmptiesCart | P86: Не выполнен
A87: CART-005 | B87: Корзина | C87: Удаление | D87: Удаление одного товара не затрагивает остальные | E87: P2 | F87: Functional | G87: Пользователь авторизован как Мастер; в корзине 2+ товара в наличии | H87: 1. Отметить один товар 2. Нажать «Удалить» | J87: Удалён только отмеченный товар, остальные на месте | L87: Да | N87: Автоматизирован | O87: storefront/cart/CartTest#removingOneItemKeepsOthersInCart | P87: Не выполнен
A88: CART-006 | B88: Корзина | C88: Расчёт | D88: Корректность расчёта итогов корзины | E88: P1 | F88: Functional | G88: Пользователь авторизован как Мастер; в корзине 2+ товара в наличии | H88: 1. Открыть корзину 2. Сверить блок итогов | J88: «Количество товаров» = сумма количеств; «Цена товаров» = Σ(цена × кол-во); «Итого» = Цена товаров − Скидка | L88: Да | N88: Автоматизирован | O88: storefront/cart/CartSummaryTest#cartTotalsAreConsistent | P88: Не выполнен
A89: CART-007 | B89: Корзина | C89: Выбор | D89: Снятие отметки с товара пересчитывает итог | E89: P1 | F89: Functional | G89: Пользователь авторизован как Мастер; в корзине 2+ товара в наличии | H89: 1. Снять чекбокс с одного товара | J89: Итог считается только по отмеченным товарам; в оформление переходят только они | L89: Да | N89: Автоматизирован | O89: storefront/cart/CartSummaryTest#uncheckingItemRecalculatesTotal | P89: Не выполнен
A90: CART-008 | B90: Корзина | C90: Выбор | D90: «Выбрать все» | E90: P2 | F90: Functional | G90: Пользователь авторизован как Мастер; в корзине 2+ товара в наличии | H90: 1. Снять «Выбрать все» 2. Поставить снова | J90: Все чекбоксы снимаются / ставятся; итог пересчитывается | L90: Да | N90: Автоматизирован | O90: storefront/cart/CartSummaryTest#selectAllTogglesEveryRow | P90: Не выполнен
A91: CART-009 | B91: Корзина | C91: Удаление | D91: Массовое удаление выбранных товаров | E91: P2 | F91: Functional | G91: Пользователь авторизован как Мастер; в корзине 2+ товара в наличии | H91: 1. Отметить «Выбрать все» 2. Нажать «Удалить» | J91: Корзина пуста, бейдж в шапке исчез/0 | L91: Да | M91: Частично покрыто CART-005; массовое удаление — вручную | N91: Частично | O91: storefront/cart/CartTest#removingOneItemKeepsOthersInCart (удаление одного) | P91: Не выполнен
A92: CART-010 | B92: Корзина | C92: Количество | D92: Ручной ввод количества больше остатка | E92: P1 | F92: Negative | G92: Пользователь авторизован как Мастер; в корзине товар с остатком N | H92: 1. Ввести в поле количества N+10 | J92: Количество ограничено остатком или показано предупреждение; итог не превышает доступное | L92: Да | N92: Автоматизирован | O92: storefront/cart/CartSummaryTest#manualQuantityAboveStockIsRejected | P92: Не выполнен
A93: CART-011 | B93: Корзина | C93: Сохранение | D93: Корзина сохраняется после перезагрузки и повторного входа | E93: P1 | F93: Functional | G93: Пользователь авторизован как Мастер; в корзине 2+ товара в наличии | H93: 1. Обновить страницу 2. Выйти и войти снова | J93: Состав и количество товаров не изменились | L93: Да | M93: Проверены перезагрузка и новая вкладка; «повторный вход» — вручную | N93: Частично автоматизирован | O93: storefront/cart/CartSummaryTest#cartPersistsAcrossReloadAndTabs | P93: Не выполнен
A94: CART-012 | B94: Корзина | C94: Отображение | D94: Строка товара в корзине | E94: P3 | F94: UI | G94: Пользователь авторизован как Мастер; в корзине 2+ товара в наличии | H94: 1. Осмотреть строку товара | J94: Изображение, название с ID, магазин/склад и остаток, цена, степпер количества, чекбокс | L94: Да | N94: Автоматизирован | O94: storefront/cart/CartSummaryTest#cartRowShowsMainElements | P94: Не выполнен
A95: CART-013 | B95: Корзина | C95: Оформление | D95: Кнопка «Оформить» без выбранных товаров | E95: P2 | F95: Negative | G95: Пользователь авторизован как Мастер; в корзине 2+ товара в наличии | H95: 1. Снять все отметки 2. Нажать «Оформить» | J95: Кнопка неактивна или показано сообщение «Выберите товары» | L95: Да | N95: Автоматизирован | O95: storefront/cart/CartSummaryTest#checkoutWithoutSelectedItems | P95: Не выполнен
A96: CART-014 | B96: Корзина | C96: Изменения цен | D96: Изменение цены/наличия товара после добавления в корзину | E96: P2 | F96: Functional | G96: Пользователь авторизован как Мастер; товар в корзине; доступ к админке | H96: 1. Изменить цену/обнулить остаток товара в админке 2. Обновить корзину | J96: Отображается актуальная цена; недоступный товар помечен и не может быть оформлен | L96: Частично | M96: Нужно менять цену/остаток через админку | N96: Не автоматизирован | P96: Не выполнен
A97: CHK-001 | B97: Оформление заказа | C97: Открытие | D97: Переход к оформлению заказа | E97: P1 | F97: Smoke | G97: Пользователь авторизован как Мастер; в корзине 2+ товара в наличии | H97: 1. В корзине нажать «Оформить» | J97: Открыта /ru/confirmation: ФИО и телефон мастера, способ оплаты, адрес/способ доставки, комментарий, товары, итоги | L97: Да | N97: Автоматизирован | O97: storefront/checkout/CheckoutViewTest#cartLeadsToCheckout | P97: Не выполнен
A98: CHK-002 | B98: Оформление заказа | C98: Оплата | D98: Плитки способов оплаты и предвыбор | E98: P1 | F98: Functional | G98: Пользователь авторизован как Мастер; в корзине 2+ товара в наличии | H98: 1. Открыть оформление 2. Посмотреть плитки «Способ оплаты» | J98: Плитки: Наличные, Балл (с балансом баллов), Hamyon/Кошелёк (с балансом кошелька) — только если кошелёк открыт. Предвыбран последний использованный способ (у нового пользователя — Наличные). У каждой плитки 3 различимых состояния: выбрана / доступна / недоступна (с причиной) | K98: PRD Client Confirmation Page §7 | L98: Да | M98: Проверены способ оплаты «Наличные» и блоки; плитки баллов/кошелька — вручную | N98: Частично автоматизирован | O98: storefront/checkout/CheckoutViewTest#checkoutShowsPaymentAndDelivery | P98: Не выполнен
A99: CHK-003 | B99: Оформление заказа | C99: Оплата | D99: Балл недоступен, если баллов меньше суммы заказа | E99: P2 | F99: Negative | G99: Пользователь авторизован как Мастер; в корзине 2+ товара в наличии; баллов меньше суммы заказа (у тестового мастера 0) | H99: 1. Открыть оформление 2. Попробовать выбрать «Балл» | J99: Плитка «Балл» недоступна, рядом — короткая причина; заказ баллами оформить нельзя. Баллы — целым числом, без «сум» и дробей | K99: PRD Client Confirmation Page §7, §15 | L99: Да | M99: Нужен аккаунт с балансом баллов меньше суммы заказа | N99: Не автоматизирован | P99: Не выполнен
A100: CHK-004 | B100: Оформление заказа | C100: Оплата | D100: Оплата баллами при достаточном балансе | E100: P2 | F100: Functional | G100: Пользователь авторизован как Мастер; в корзине 2+ товара в наличии; баллов ≥ суммы заказа | H100: 1. Выбрать «Балл» 2. Оформить заказ | J100: Заказ оформлен, баллы списаны на сумму заказа, способ оплаты в заказе — «Балл» | L100: Частично | M100: Нужен аккаунт с достаточным балансом баллов | N100: Не автоматизирован | P100: Не выполнен
...

Sheet Замечания
A1: № | B1: Категория | C1: Описание | D1: Где | E1: Серьёзность | F1: Комментарий | G1: Статус
A2: 1 | B2: Локализация | C2: Плейсхолдер поиска на RU-версии на узбекском: «Mahsulot nomini kiriting...» | D2: Профиль, каталог (/ru/filter?categories=45), главная после навигации | E2: Medium | F2: Ожидается «Введите название продукта...» | G2: Новое
A3: 2 | B3: Локализация | C3: «Мой кошелёк»: в пустом состоянии выводится технический ключ «no_orders» | D3: /ru/profile/wallet | E3: Medium | F3: Ключ перевода отсутствует | G3: Новое
A4: 3 | B4: Локализация | C4: Статус оплаты «canceled» не переведён | D4: /ru/profile/orders, /ru/profile/orders/334581 | E4: Low | F4: Ожидается «Отменён» | G4: Новое
A5: 4 | B5: Локализация | C5: Вкладка «Hamkor» в «Мои запросы» не переведена | D5: /ru/profile/request | E5: Low | F5: Ожидается «Партнёр» | G5: Новое
A6: 5 | B6: Локализация | C6: Название склада «Asosiy ombor» на RU-версии | D6: Страница товара pvId=9824 | E6: Low | F6: Ожидается «Основной склад» | G6: Новое
A7: 6 | B7: Текст | C7: Опечатка в сортировке: «Сначало дешевые/дорогие/старые/новые» | D7: Каталог → «Сортировка» | E7: Low | F7: Правильно: «Сначала» | G7: Новое
A8: 7 | B8: Изображения | C8: Битые иконки категорий «Электроника» и «Мебель» в меню каталога | D8: Меню «Каталог» | E8: Low | G8: Новое
A9: 8 | B9: Изображения | C9: Нет основного фото товара (alt «Product image») | D9: Страница товара pvId=9824 | E9: Low | F9: Возможно, проблема данных на staging | G9: Новое
A10: 9 | B10: Изображения | C10: В корзине у товаров не отображаются миниатюры | D10: /ru/cart | E10: Low | F10: Уточнить, предусмотрены ли миниатюры дизайном | G10: Новое
A11: 10 | B11: Данные | C11: В заказе со способом «В офис Ароса» адрес доставки — домашний адрес клиента | D11: /ru/profile/orders/334581 | E11: Info | F11: В новом заказе #518190 адрес офиса правильный — вероятно, старые данные; перепроверить на свежем заказе | G11: Новое
A12: 11 | B12: Фильтры | C12: Границы фильтра цены не согласованы: поля 0–100 000, плейсхолдер «50 000 000», ползунок max 99 000 | D12: /ru/filter?categories=45 | E12: Low | F12: Проверить, не отсекаются ли товары дороже 99 000 | G12: Новое
A13: 12 | B13: URL | C13: Разные параметры категорий: меню использует ?categories=, хлебные крошки — ?category= | D13: Каталог / страница товара | E13: Low | F13: Проверить, что обе ссылки дают одинаковую выдачу | G13: Новое
A14: 13 | B14: Навигация | C14: Часть ссылок футера ведёт на заглушку /coming-soon | D14: Футер | E14: Info | F14: Зафиксировать список ожидаемых заглушек | G14: Новое
A15: 14 | B15: Заказы | C15: После отмены заказа список «Мои заказы» показывает старый статус «Готов» до перезагрузки страницы | D15: Детали заказа → «Отменить заказ» → список (#518190) | E15: Medium | F15: После F5 статус «Отменен» | G15: Новое
A16: 15 | B16: Уведомления | C16: Текст уведомления об отмене — только причина «Заказал(а) по ошибке», без шаблона «Вы отменили заказ. Причина: заказ оформлен по ошибке.» | D16: /ru/profile/notifications | E16: Low | F16: PRD «Buyurtmani bekor qilish» §6.2 (AIDT-645) — уточнить, внедрено ли | G16: Новое
A17: 16 | B17: Смена оплаты | C17: В окне «Изменить способ оплаты» в списке есть текущий способ «Наличные» | D17: Детали заказа #518190 | E17: Low | F17: PRD Change Payment Method: текущий способ не выбирается — проверить, активен ли он | G17: Новое
A18: 17 | B18: Локализация | C18: Один способ оплаты назван по-разному: «Балл» при оформлении и «Кешбек» в окне смены оплаты | D18: /ru/confirmation, детали заказа | E18: Low | F18: Ожидается единое название «Балл» | G18: Новое
A19: 18 | B19: Заказы | C19: В деталях заказа нет «Цены заказа», «Скидки» и «Начисленных баллов» | D19: /ru/profile/orders/{id} | E19: Medium | F19: PRD My Orders §4.5 | G19: Новое
A20: 19 | B20: Заказы | C20: На вебе в «Мои заказы» нет поиска по ID и фильтра по типу оплаты — только период «С/До» | D20: /ru/profile/orders → «Фильтры» | E20: Low | F20: PRD My Orders §4.3–4.4 — уточнить, только ли для мобильного | G20: Новое
... A22: 21 | B22: Оформление | C22: При способе «В офис Ароса» показана кнопка «Добавить адрес» | D22: /ru/confirmation | E22: Low | F22: PRD Client Confirmation CHK-006.3 (DRAFT): для офиса должна быть скрыта | G22: Новое
A23: 22 | B23: Локализация | C23: Формат даты в уведомлениях «28-октябрь» вместо «28 октября» | D23: /ru/profile/notifications | E23: Low | G23: Новое
A24: 23 | B24: Авторизация | C24: Выход из системы на странице профиля, открытой прямой ссылкой (новая вкладка), оставляет пустой экран about:blank | D24: /ru/profile → «Выйти из системы» | E24: Medium | F24: Похоже, выход делает «назад по истории». Автотест AUTH-X02. Через переход с главной выход работает. | G24: Новое
A25: 24 | B25: Авторизация | C25: Гость, открывший закрытую страницу (/profile/..., /confirmation), остаётся на пустом экране — нет ни окна входа, ни редиректа | D25: /ru/profile/orders без входа | E25: Medium | F25: Данные не показываются, но UX сломан. Автотест AUTH-X03. | G25: Новое
A26: 25 | B26: Авторизация | C26: После входа язык переключается на сохранённый в профиле (localStorage 'language'); если он отличается от языка в адресе, страница /ru показывается на английском | D26: Вход на /ru под аккаунтом с языком en | E26: Medium | F26: Адрес и интерфейс расходятся. Уточнить у разработчиков, задумано ли так. | G26: Новое
A27: 26 | B27: Каталог | C27: У страницы каталога/поиска пустая подстановка в title вкладки: «- купить в Aros» | D27: /ru/filter?query=… | E27: Low | F27: Автотест GEN-003. | G27: Новое
A28: 27 | B28: Каталог | C28: Товар «под заказ» показан с ценой «0 сум» при включённом «Только в наличии» (пример: Tashqi akkumulyator Xiaomi pb200szm Qora, ID 9932) | D28: /ru/filter?query=akkumulyator | E28: Medium | F28: Автотест CAT-X01. | G28: Новое
A29: 28 | B29: Локализация | C29: Гость на /ru видит названия товаров на узбекском (запросы идут с lang=uz): «Akkumulyator Samsung…» вместо «Аккумуляторы Samsung…». У вошедшего — на русском | D29: /ru, гость | E29: Medium | F29: В запросах списка товаров параметр lang=uz независимо от языка в адресе. | G29: Новое
A30: 29 | B30: Локализация | C30: Страница 404 на /ru показана по-английски («It seems that the product you are looking for is not available…») | D30: /ru/favorites и другие несуществующие адреса | E30: Low | F30: Не переведена. | G30: Новое
A31: 30 | B31: Локализация | C31: Фильтр цены в каталоге: подпись «Цена (so'm)» на узбекском в русской версии | D31: /ru/filter | E31: Low | F31: Автотест L10N-X01. | G31: Новое
A32: 31 | B32: Корзина | C32: На странице корзины два блока «Итого:», один из них скрыт и не пересчитывается при снятии отметок (показывает старую сумму) | D32: /ru/cart | E32: Low | F32: Видимый блок считает верно. Если скрытый — мобильная панель, на телефоне сумма может быть неверной (проверить MOB-003). | G32: Новое
A33: 32 | B33: Подбор по модели | C33: Первая категория в списке (например, «Защитные стёкла» у Samsung Galaxy A52) при клике ничего не делает — нет ни перехода, ни сообщения | D33: Модель → Samsung → Galaxy… → первая категория | E33: Low | F33: Ожидается переход со списком или сообщение «нет товаров». | G33: Новое
A34: 33 | B34: API | C34: Запросы с некорректными значениями: sidebar-filters отвечает 500 (?brands=undefined&product_models=undefined); …/warehouses/null/workers/ — 404; …/product-variants/quantities/ — 400 | D34: /ru/filter, главная (вошедший пользователь) | E34: Medium | F34: Фронт отправляет undefined/null. Нужны проверки на стороне фронта и бэка. Автотест GEN-002 ловит 5xx. | G34: Новое
A35: 34 | B35: Избранное | C35: Страница избранного не найдена: /ru/favorites возвращает 404; у вошедшего клик по «сердцу» в шапке ничего не открывает | D35: Шапка → «сердце» | E35: Medium | F35: Уточнить у разработчиков: функциональность не реализована или маршрут другой. Автотесты FAV-* не написаны. | G35: Новое
B37: Замечания найдены при исследовании staging 28.10.2026 под аккаунтом мастера. Перед заведением бага — перепроверить.

Sheet Источники
A1: PRD / страница | B1: О чём | C1: Ссылка
A2: 13. Qarz va hamyon | B2: Раздел админки: долг и кошелёк | C2: https://arositdepartment.atlassian.net/wiki/spaces/~ArosMarket/pages/354320395
A3: Debt Limit and Payment Deadline Management (B2B/B2M) | B3: Лимит суммы и дней, срок долга, блокировка Hamyon | C3: https://arositdepartment.atlassian.net/wiki/spaces/~ArosMarket/pages/305004559
A4: Muddati o'tgan qarzda ball bilan savdo cheklovi (DRAFT) | B4: Запрет оплаты баллами при просроченном долге | C4: https://arositdepartment.atlassian.net/wiki/spaces/~ArosMarket/pages/346292227
A5: Pay Debt | B5: Погашение долга (админка), статусы оплаты | C5: https://arositdepartment.atlassian.net/wiki/spaces/~ArosMarket/pages/292421633
A6: Wallet / Point | B6: Транзакции кошелька и баллов (админка) | C6: https://arositdepartment.atlassian.net/wiki/spaces/~ArosMarket/pages/324108289
A7: 4. Buyurtmalar | B7: Раздел админки: заказы | C7: https://arositdepartment.atlassian.net/wiki/spaces/~ArosMarket/pages/354582529
A8: Client Confirmation Page (DRAFT) | B8: Оформление: оплата, доставка, Яндекс, склады | C8: https://arositdepartment.atlassian.net/wiki/spaces/~ArosMarket/pages/317849606
A9: Buyurtmani bekor qilish | B9: Причины отмены и тексты уведомлений | C9: https://arositdepartment.atlassian.net/wiki/spaces/~ArosMarket/pages/340525071
A10: Change Payment Method | B10: Смена способа оплаты заказа | C10: https://arositdepartment.atlassian.net/wiki/spaces/~ArosMarket/pages/319750146
A11: Client Order Comment | B11: Комментарий к заказу | C11: https://arositdepartment.atlassian.net/wiki/spaces/~ArosMarket/pages/330104833
A12: Product Return | B12: Возвраты (админка) | C12: https://arositdepartment.atlassian.net/wiki/spaces/~ArosMarket/pages/298024961
... A20: Hisobni o'chirish (AIDT-692) | B20: Проверки при удалении аккаунта | C20: https://arositdepartment.atlassian.net/wiki/spaces/~ArosMarket/pages/361005057

Sheet Доп. проверки (авто)
A1: ID | B1: Название | C1: Автотест (класс#метод) | D1: Известный дефект? | E1: Результат прогона
A2: AUTH-X02 | B2: Выход на странице профиля, открытой прямой ссылкой, не оставляет пустой экран | C2: storefront/auth/SessionTest#logoutFromDirectlyOpenedProfileDoesNotLeaveBlankPage | D2: Да | E2: Не выполнен
A3: AUTH-X03 | B3: Гостя со закрытой страницы переводят на вход/главную, а не оставляют на пустом экране | C3: storefront/auth/GuestAccessTest#guestOnPrivatePageIsRedirectedNotLeftBlank | D3: Да | E3: Не выполнен
A4: CAT-X01 | B4: В выдаче нет товаров с ценой «0 сум» | C4: storefront/catalog/CatalogTest#noZeroPriceProductsInResults | D4: Да | E4: Не выполнен
A5: CAT-X02 | B5: Пункты меню сортировки без орфографических ошибок | C5: storefront/catalog/CatalogTest#sortMenuHasNoTypos | D5: Да | E5: Не выполнен
A6: FAV-X01 | B6: Гость, нажав на «сердце» в шапке, видит окно входа | C6: storefront/header/HeaderFooterTest#guestClickingFavoritesSeesSignIn | D6: Нет | E6: Не выполнен
A7: L10N-X01 | B7: Фильтр цены в каталоге на /ru не содержит узбекских подписей «so'm» | C7: storefront/l10n/LocalizationTest#catalogPriceFilterLabelIsLocalized | D7: Да | E7: Не выполнен
A8: L10N-X02 | B8: Поле поиска в шапке на /ru имеет русский placeholder на всех страницах | C8: storefront/l10n/LocalizationTest#searchPlaceholderIsRussianOnCart | D8: Да | E8: Не выполнен
