Workbook

Sheet Xulosa
A1: Aros — admin panel uchun regression test-keyslar
A2: Admin panel, UI. Confluence dagi PRD va staging-admin bilan solishtirilgan (28.10.2026). Vitrina — alohida fayl.
A4: Muhit | B4: https://staging-admin.aros.uz (til: O'zbekcha)
A5: Rol | B5: Administrator (to'liq huquqlar)
A6: Test akkaunti | B6: Login: +998998987882 Parol: <пароль в .env> в .env>
A7: Hujjatlar | B7: Confluence → admin panel mantiqi papkasi; havolalar «Manbalar» varag'ida
A8: Avtotestlar | B8: aros-ui repozitoriyasi: Java 21 + Playwright + JUnit5 + Allure
A9: Reliz / versiya | J9: ← sariq maydonlar har bir progondan oldin to'ldiriladi
A10: Progon sanasi
A11: Testchi
A12: Modullar bo'yicha qamrov
A13: Modul | B13: Jami | C13: P1 | D13: P2 | E13: P3 | F13: Avto mumkin: Ha | G13: Qisman | H13: Yo'q | I13: Avtomatlashtirilgan | J13: Avtotestlar qamrovi % | K13: Passed | L13: Failed | M13: Blocked | N13: Skipped | O13: Bajarilmagan
A14: AUTH — Avtorizatsiya va ruxsat | B14: =COUNTIF('Test-keyslar'!$B$2:$B$167,"Avtorizatsiya va ruxsat") | C14: =COUNTIFS('Test-keyslar'!$B$2:$B$167,"Avtorizatsiya va ruxsat",'Test-keyslar'!$E$2:$E$167,"P1") | D14: =COUNTIFS('Test-keyslar'!$B$2:$B$167,"Avtorizatsiya va ruxsat",'Test-keyslar'!$E$2:$E$167,"P2") | E14: =COUNTIFS('Test-keyslar'!$B$2:$B$167,"Avtorizatsiya va ruxsat",'Test-keyslar'!$E$2:$E$167,"P3") | F14: =COUNTIFS('Test-keyslar'!$B$2:$B$167,"Avtorizatsiya va ruxsat",'Test-keyslar'!$L$2:$L$167,"Ha") | G14: =COUNTIFS('Test-keyslar'!$B$2:$B$167,"Avtorizatsiya va ruxsat",'Test-keyslar'!$L$2:$L$167,"Qisman") | H14: =COUNTIFS('Test-keyslar'!$B$2:$B$167,"Avtorizatsiya va ruxsat",'Test-keyslar'!$L$2:$L$167,"Yo'q") | I14: =COUNTIFS('Test-keyslar'!$B$2:$B$167,"Avtorizatsiya va ruxsat",'Test-keyslar'!$N$2:$N$167,"Avtomatlashtirilgan") | J14: =IF(B14=0,0,I14/B14) | K14: =COUNTIFS('Test-keyslar'!$B$2:$B$167,"Avtorizatsiya va ruxsat",'Test-keyslar'!$P$2:$P$167,"Passed") | L14: =COUNTIFS('Test-keyslar'!$B$2:$B$167,"Avtorizatsiya va ruxsat",'Test-keyslar'!$P$2:$P$167,"Failed") | M14: =COUNTIFS('Test-keyslar'!$B$2:$B$167,"Avtorizatsiya va ruxsat",'Test-keyslar'!$P$2:$P$167,"Blocked") | N14: =COUNTIFS('Test-keyslar'!$B$2:$B$167,"Avtorizatsiya va ruxsat",'Test-keyslar'!$P$2:$P$167,"Skipped") | O14: =COUNTIFS('Test-keyslar'!$B$2:$B$167,"Avtorizatsiya va ruxsat",'Test-keyslar'!$P$2:$P$167,"Bajarilmagan")
A15: DASH — Bosh sahifa (Dashboard) | B15: =COUNTIF('Test-keyslar'!$B$2:$B$167,"Bosh sahifa (Dashboard)") | C15: =COUNTIFS('Test-keyslar'!$B$2:$B$167,"Bosh sahifa (Dashboard)",'Test-keyslar'!$E$2:$E$167,"P1") | D15: =COUNTIFS('Test-keyslar'!$B$2:$B$167,"Bosh sahifa (Dashboard)",'Test-keyslar'!$E$2:$E$167,"P2") | E15: =COUNTIFS('Test-keyslar'!$B$2:$B$167,"Bosh sahifa (Dashboard)",'Test-keyslar'!$E$2:$E$167,"P3") | F15: =COUNTIFS('Test-keyslar'!$B$2:$B$167,"Bosh sahifa (Dashboard)",'Test-keyslar'!$L$2:$L$167,"Ha") | G15: =COUNTIFS('Test-keyslar'!$B$2:$B$167,"Bosh sahifa (Dashboard)",'Test-keyslar'!$L$2:$L$167,"Qisman") | H15: =COUNTIFS('Test-keyslar'!$B$2:$B$167,"Bosh sahifa (Dashboard)",'Test-keyslar'!$L$2:$L$167,"Yo'q") | I15: =COUNTIFS('Test-keyslar'!$B$2:$B$167,"Bosh sahifa (Dashboard)",'Test-keyslar'!$N$2:$N$167,"Avtomatlashtirilgan") | J15: =IF(B15=0,0,I15/B15) | K15: =COUNTIFS('Test-keyslar'!$B$2:$B$167,"Bosh sahifa (Dashboard)",'Test-keyslar'!$P$2:$P$167,"Passed") | L15: =COUNTIFS('Test-keyslar'!$B$2:$B$167,"Bosh sahifa (Dashboard)",'Test-keyslar'!$P$2:$P$167,"Failed") | M15: =COUNTIFS('Test-keyslar'!$B$2:$B$167,"Bosh sahifa (Dashboard)",'Test-keyslar'!$P$2:$P$167,"Blocked") | N15: =COUNTIFS('Test-keyslar'!$B$2:$B$167,"Bosh sahifa (Dashboard)",'Test-keyslar'!$P$2:$P$167,"Skipped") | O15: =COUNTIFS('Test-keyslar'!$B$2:$B$167,"Bosh sahifa (Dashboard)",'Test-keyslar'!$P$2:$P$167,"Bajarilmagan")
A16: PINC — Qabul qilingan mahsulot (kirim) | B16: =COUNTIF('Test-keyslar'!$B$2:$B$167,"Qabul qilingan mahsulot (kirim)") | C16: =COUNTIFS('Test-keyslar'!$B$2:$B$167,"Qabul qilingan mahsulot (kirim)",'Test-keyslar'!$E$2:$E$167,"P1") | D16: =COUNTIFS('Test-keyslar'!$B$2:$B$167,"Qabul qilingan mahsulot (kirim)",'Test-keyslar'!$E$2:$E$167,"P2") | E16: =COUNTIFS('Test-keyslar'!$B$2:$B$167,"Qabul qilingan mahsulot (kirim)",'Test-keyslar'!$E$2:$E$167,"P3") | F16: =COUNTIFS('Test-keyslar'!$B$2:$B$167,"Qabul qilingan mahsulot (kirim)",'Test-keyslar'!$L$2:$L$167,"Ha") | G16: =COUNTIFS('Test-keyslar'!$B$2:$B$167,"Qabul qilingan mahsulot (kirim)",'Test-keyslar'!$L$2:$L$167,"Qisman") | H16: =COUNTIFS('Test-keyslar'!$B$2:$B$167,"Qabul qilingan mahsulot (kirim)",'Test-keyslar'!$L$2:$L$167,"Yo'q") | I16: =COUNTIFS('Test-keyslar'!$B$2:$B$167,"Qabul qilingan mahsulot (kirim)",'Test-keyslar'!$N$2:$N$167,"Avtomatlashtirilgan") | J16: =IF(B16=0,0,I16/B16) | K16: =COUNTIFS('Test-keyslar'!$B$2:$B$167,"Qabul qilingan mahsulot (kirim)",'Test-keyslar'!$P$2:$P$167,"Passed") | L16: =COUNTIFS('Test-keyslar'!$B$2:$B$167,"Qabul qilingan mahsulot (kirim)",'Test-keyslar'!$P$2:$P$167,"Failed") | M16: =COUNTIFS('Test-keyslar'!$B$2:$B$167,"Qabul qilingan mahsulot (kirim)",'Test-keyslar'!$P$2:$P$167,"Blocked") | N16: =COUNTIFS('Test-keyslar'!$B$2:$B$167,"Qabul qilingan mahsulot (kirim)",'Test-keyslar'!$P$2:$P$167,"Skipped") | O16: =COUNTIFS('Test-keyslar'!$B$2:$B$167,"Qabul qilingan mahsulot (kirim)",'Test-keyslar'!$P$2:$P$167,"Bajarilmagan")
A17: PRICE — Narxni o'zgartirish | B17: =COUNTIF('Test-keyslar'!$B$2:$B$167,"Narxni o'zgartirish") | C17: =COUNTIFS('Test-keyslar'!$B$2:$B$167,"Narxni o'zgartirish",'Test-keyslar'!$E$2:$E$167,"P1") | D17: =COUNTIFS('Test-keyslar'!$B$2:$B$167,"Narxni o'zgartirish",'Test-keyslar'!$E$2:$E$167,"P2") | E17: =COUNTIFS('Test-keyslar'!$B$2:$B$167,"Narxni o'zgartirish",'Test-keyslar'!$E$2:$E$167,"P3") | F17: =COUNTIFS('Test-keyslar'!$B$2:$B$167,"Narxni o'zgartirish",'Test-keyslar'!$L$2:$L$167,"Ha") | G17: =COUNTIFS('Test-keyslar'!$B$2:$B$167,"Narxni o'zgartirish",'Test-keyslar'!$L$2:$L$167,"Qisman") | H17: =COUNTIFS('Test-keyslar'!$B$2:$B$167,"Narxni o'zgartirish",'Test-keyslar'!$L$2:$L$167,"Yo'q") | I17: =COUNTIFS('Test-keyslar'!$B$2:$B$167,"Narxni o'zgartirish",'Test-keyslar'!$N$2:$N$167,"Avtomatlashtirilgan") | J17: =IF(B17=0,0,I17/B17) | K17: =COUNTIFS('Test-keyslar'!$B$2:$B$167,"Narxni o'zgartirish",'Test-keyslar'!$P$2:$P$167,"Passed") | L17: =COUNTIFS('Test-keyslar'!$B$2:$B$167,"Narxni o'zgartirish",'Test-keyslar'!$P$2:$P$167,"Failed") | M17: =COUNTIFS('Test-keyslar'!$B$2:$B$167,"Narxni o'zgartirish",'Test-keyslar'!$P$2:$P$167,"Blocked") | N17: =COUNTIFS('Test-keyslar'!$B$2:$B$167,"Narxni o'zgartirish",'Test-keyslar'!$P$2:$P$167,"Skipped") | O17: =COUNTIFS('Test-keyslar'!$B$2:$B$167,"Narxni o'zgartirish",'Test-keyslar'!$P$2:$P$167,"Bajarilmagan")
A18: INV — Inventarizatsiya | B18: =COUNTIF('Test-keyslar'!$B$2:$B$167,"Inventarizatsiya") | C18: =COUNTIFS('Test-keyslar'!$B$2:$B$167,"Inventarizatsiya",'Test-keyslar'!$E$2:$E$167,"P1") | D18: =COUNTIFS('Test-keyslar'!$B$2:$B$167,"Inventarizatsiya",'Test-keyslar'!$E$2:$E$167,"P2") | E18: =COUNTIFS('Test-keyslar'!$B$2:$B$167,"Inventarizatsiya",'Test-keyslar'!$E$2:$E$167,"P3") | F18: =COUNTIFS('Test-keyslar'!$B$2:$B$167,"Inventarizatsiya",'Test-keyslar'!$L$2:$L$167,"Ha") | G18: =COUNTIFS('Test-keyslar'!$B$2:$B$167,"Inventarizatsiya",'Test-keyslar'!$L$2:$L$167,"Qisman") | H18: =COUNTIFS('Test-keyslar'!$B$2:$B$167,"Inventarizatsiya",'Test-keyslar'!$L$2:$L$167,"Yo'q") | I18: =COUNTIFS('Test-keyslar'!$B$2:$B$167,"Inventarizatsiya",'Test-keyslar'!$N$2:$N$167,"Avtomatlashtirilgan") | J18: =IF(B18=0,0,I18/B18) | K18: =COUNTIFS('Test-keyslar'!$B$2:$B$167,"Inventarizatsiya",'Test-keyslar'!$P$2:$P$167,"Passed") | L18: =COUNTIFS('Test-keyslar'!$B$2:$B$167,"Inventarizatsiya",'Test-keyslar'!$P$2:$P$167,"Failed") | M18: =COUNTIFS('Test-keyslar'!$B$2:$B$167,"Inventarizatsiya",'Test-keyslar'!$P$2:$P$167,"Blocked") | N18: =COUNTIFS('Test-keyslar'!$B$2:$B$167,"Inventarizatsiya",'Test-keyslar'!$P$2:$P$167,"Skipped") | O18: =COUNTIFS('Test-keyslar'!$B$2:$B$167,"Inventarizatsiya",'Test-keyslar'!$P$2:$P$167,"Bajarilmagan")
A19: TRF — Mahsulot yuborish (o'tkazma) | B19: =COUNTIF('Test-keyslar'!$B$2:$B$167,"Mahsulot yuborish (o'tkazma)") | C19: =COUNTIFS('Test-keyslar'!$B$2:$B$167,"Mahsulot yuborish (o'tkazma)",'Test-keyslar'!$E$2:$E$167,"P1") | D19: =COUNTIFS('Test-keyslar'!$B$2:$B$167,"Mahsulot yuborish (o'tkazma)",'Test-keyslar'!$E$2:$E$167,"P2") | E19: =COUNTIFS('Test-keyslar'!$B$2:$B$167,"Mahsulot yuborish (o'tkazma)",'Test-keyslar'!$E$2:$E$167,"P3") | F19: =COUNTIFS('Test-keyslar'!$B$2:$B$167,"Mahsulot yuborish (o'tkazma)",'Test-keyslar'!$L$2:$L$167,"Ha") | G19: =COUNTIFS('Test-keyslar'!$B$2:$B$167,"Mahsulot yuborish (o'tkazma)",'Test-keyslar'!$L$2:$L$167,"Qisman") | H19: =COUNTIFS('Test-keyslar'!$B$2:$B$167,"Mahsulot yuborish (o'tkazma)",'Test-keyslar'!$L$2:$L$167,"Yo'q") | I19: =COUNTIFS('Test-keyslar'!$B$2:$B$167,"Mahsulot yuborish (o'tkazma)",'Test-keyslar'!$N$2:$N$167,"Avtomatlashtirilgan") | J19: =IF(B19=0,0,I19/B19) | K19: =COUNTIFS('Test-keyslar'!$B$2:$B$167,"Mahsulot yuborish (o'tkazma)",'Test-keyslar'!$P$2:$P$167,"Passed") | L19: =COUNTIFS('Test-keyslar'!$B$2:$B$167,"Mahsulot yuborish (o'tkazma)",'Test-keyslar'!$P$2:$P$167,"Failed") | M19: =COUNTIFS('Test-keyslar'!$B$2:$B$167,"Mahsulot yuborish (o'tkazma)",'Test-keyslar'!$P$2:$P$167,"Blocked") | N19: =COUNTIFS('Test-keyslar'!$B$2:$B$167,"Mahsulot yuborish (o'tkazma)",'Test-keyslar'!$P$2:$P$167,"Skipped") | O19: =COUNTIFS('Test-keyslar'!$B$2:$B$167,"Mahsulot yuborish (o'tkazma)",'Test-keyslar'!$P$2:$P$167,"Bajarilmagan")
A20: PVAR — Mahsulot varianti (ehtiyoj) | B20: =COUNTIF('Test-keyslar'!$B$2:$B$167,"Mahsulot varianti (ehtiyoj)") | C20: =COUNTIFS('Test-keyslar'!$B$2:$B$167,"Mahsulot varianti (ehtiyoj)",'Test-keyslar'!$E$2:$E$167,"P1") | D20: =COUNTIFS('Test-keyslar'!$B$2:$B$167,"Mahsulot varianti (ehtiyoj)",'Test-keyslar'!$E$2:$E$167,"P2") | E20: =COUNTIFS('Test-keyslar'!$B$2:$B$167,"Mahsulot varianti (ehtiyoj)",'Test-keyslar'!$E$2:$E$167,"P3") | F20: =COUNTIFS('Test-keyslar'!$B$2:$B$167,"Mahsulot varianti (ehtiyoj)",'Test-keyslar'!$L$2:$L$167,"Ha") | G20: =COUNTIFS('Test-keyslar'!$B$2:$B$167,"Mahsulot varianti (ehtiyoj)",'Test-keyslar'!$L$2:$L$167,"Qisman") | H20: =COUNTIFS('Test-keyslar'!$B$2:$B$167,"Mahsulot varianti (ehtiyoj)",'Test-keyslar'!$L$2:$L$167,"Yo'q") | I20: =COUNTIFS('Test-keyslar'!$B$2:$B$167,"Mahsulot varianti (ehtiyoj)",'Test-keyslar'!$N$2:$N$167,"Avtomatlashtirilgan") | J20: =IF(B20=0,0,I20/B20) | K20: =COUNTIFS('Test-keyslar'!$B$2:$B$167,"Mahsulot varianti (ehtiyoj)",'Test-keyslar'!$P$2:$P$167,"Passed") | L20: =COUNTIFS('Test-keyslar'!$B$2:$B$167,"Mahsulot varianti (ehtiyoj)",'Test-keyslar'!$P$2:$P$167,"Failed") | M20: =COUNTIFS('Test-keyslar'!$B$2:$B$167,"Mahsulot varianti (ehtiyoj)",'Test-keyslar'!$P$2:$P$167,"Blocked") | N20: =COUNTIFS('Test-keyslar'!$B$2:$B$167,"Mahsulot varianti (ehtiyoj)",'Test-keyslar'!$P$2:$P$167,"Skipped") | O20: =COUNTIFS('Test-keyslar'!$B$2:$B$167,"Mahsulot varianti (ehtiyoj)",'Test-keyslar'!$P$2:$P$167,"Bajarilmagan")
A21: DISC — Chegirma va aksiyalar | B21: =COUNTIF('Test-keyslar'!$B$2:$B$167,"Chegirma va aksiyalar") | C21: =COUNTIFS('Test-keyslar'!$B$2:$B$167,"Chegirma va aksiyalar",'Test-keyslar'!$E$2:$E$167,"P1") | D21: =COUNTIFS('Test-keyslar'!$B$2:$B$167,"Chegirma va aksiyalar",'Test-keyslar'!$E$2:$E$167,"P2") | E21: =COUNTIFS('Test-keyslar'!$B$2:$B$167,"Chegirma va aksiyalar",'Test-keyslar'!$E$2:$E$167,"P3") | F21: =COUNTIFS('Test-keyslar'!$B$2:$B$167,"Chegirma va aksiyalar",'Test-keyslar'!$L$2:$L$167,"Ha") | G21: =COUNTIFS('Test-keyslar'!$B$2:$B$167,"Chegirma va aksiyalar",'Test-keyslar'!$L$2:$L$167,"Qisman") | H21: =COUNTIFS('Test-keyslar'!$B$2:$B$167,"Chegirma va aksiyalar",'Test-keyslar'!$L$2:$L$167,"Yo'q") | I21: =COUNTIFS('Test-keyslar'!$B$2:$B$167,"Chegirma va aksiyalar",'Test-keyslar'!$N$2:$N$167,"Avtomatlashtirilgan") | J21: =IF(B21=0,0,I21/B21) | K21: =COUNTIFS('Test-keyslar'!$B$2:$B$167,"Chegirma va aksiyalar",'Test-keyslar'!$P$2:$P$167,"Passed") | L21: =COUNTIFS('Test-keyslar'!$B$2:$B$167,"Chegirma va aksiyalar",'Test-keyslar'!$P$2:$P$167,"Failed") | M21: =COUNTIFS('Test-keyslar'!$B$2:$B$167,"Chegirma va aksiyalar",'Test-keyslar'!$P$2:$P$167,"Blocked") | N21: =COUNTIFS('Test-keyslar'!$B$2:$B$167,"Chegirma va aksiyalar",'Test-keyslar'!$P$2:$P$167,"Skipped") | O21: =COUNTIFS('Test-keyslar'!$B$2:$B$167,"Chegirma va aksiyalar",'Test-keyslar'!$P$2:$P$167,"Bajarilmagan")
A22: PROD — Mahsulotlar va variantlar | B22: =COUNTIF('Test-keyslar'!$B$2:$B$167,"Mahsulotlar va variantlar") | C22: =COUNTIFS('Test-keyslar'!$B$2:$B$167,"Mahsulotlar va variantlar",'Test-keyslar'!$E$2:$E$167,"P1") | D22: =COUNTIFS('Test-keyslar'!$B$2:$B$167,"Mahsulotlar va variantlar",'Test-keyslar'!$E$2:$E$167,"P2") | E22: =COUNTIFS('Test-keyslar'!$B$2:$B$167,"Mahsulotlar va variantlar",'Test-keyslar'!$E$2:$E$167,"P3") | F22: =COUNTIFS('Test-keyslar'!$B$2:$B$167,"Mahsulotlar va variantlar",'Test-keyslar'!$L$2:$L$167,"Ha") | G22: =COUNTIFS('Test-keyslar'!$B$2:$B$167,"Mahsulotlar va variantlar",'Test-keyslar'!$L$2:$L$167,"Qisman") | H22: =COUNTIFS('Test-keyslar'!$B$2:$B$167,"Mahsulotlar va variantlar",'Test-keyslar'!$L$2:$L$167,"Yo'q") | I22: =COUNTIFS('Test-keyslar'!$B$2:$B$167,"Mahsulotlar va variantlar",'Test-keyslar'!$N$2:$N$167,"Avtomatlashtirilgan") | J22: =IF(B22=0,0,I22/B22) | K22: =COUNTIFS('Test-keyslar'!$B$2:$B$167,"Mahsulotlar va variantlar",'Test-keyslar'!$P$2:$P$167,"Passed") | L22: =COUNTIFS('Test-keyslar'!$B$2:$B$167,"Mahsulotlar va variantlar",'Test-keyslar'!$P$2:$P$167,"Failed") | M22: =COUNTIFS('Test-keyslar'!$B$2:$B$167,"Mahsulotlar va variantlar",'Test-keyslar'!$P$2:$P$167,"Blocked") | N22: =COUNTIFS('Test-keyslar'!$B$2:$B$167,"Mahsulotlar va variantlar",'Test-keyslar'!$P$2:$P$167,"Skipped") | O22: =COUNTIFS('Test-keyslar'!$B$2:$B$167,"Mahsulotlar va variantlar",'Test-keyslar'!$P$2:$P$167,"Bajarilmagan")
A23: DIR — Katalog ma'lumotnomalari | B23: =COUNTIF('Test-keyslar'!$B$2:$B$167,"Katalog ma'lumotnomalari") | C23: =COUNTIFS('Test-keyslar'!$B$2:$B$167,"Katalog ma'lumotnomalari",'Test-keyslar'!$E$2:$E$167,"P1") | D23: =COUNTIFS('Test-keyslar'!$B$2:$B$167,"Katalog ma'lumotnomalari",'Test-keyslar'!$E$2:$E$167,"P2") | E23: =COUNTIFS('Test-keyslar'!$B$2:$B$167,"Katalog ma'lumotnomalari",'Test-keyslar'!$E$2:$E$167,"P3") | F23: =COUNTIFS('Test-keyslar'!$B$2:$B$167,"Katalog ma'lumotnomalari",'Test-keyslar'!$L$2:$L$167,"Ha") | G23: =COUNTIFS('Test-keyslar'!$B$2:$B$167,"Katalog ma'lumotnomalari",'Test-keyslar'!$L$2:$L$167,"Qisman") | H23: =COUNTIFS('Test-keyslar'!$B$2:$B$167,"Katalog ma'lumotnomalari",'Test-keyslar'!$L$2:$L$167,"Yo'q") | I23: =COUNTIFS('Test-keyslar'!$B$2:$B$167,"Katalog ma'lumotnomalari",'Test-keyslar'!$N$2:$N$167,"Avtomatlashtirilgan") | J23: =IF(B23=0,0,I23/B23) | K23: =COUNTIFS('Test-keyslar'!$B$2:$B$167,"Katalog ma'lumotnomalari",'Test-keyslar'!$P$2:$P$167,"Passed") | L23: =COUNTIFS('Test-keyslar'!$B$2:$B$167,"Katalog ma'lumotnomalari",'Test-keyslar'!$P$2:$P$167,"Failed") | M23: =COUNTIFS('Test-keyslar'!$B$2:$B$167,"Katalog ma'lumotnomalari",'Test-keyslar'!$P$2:$P$167,"Blocked") | N23: =COUNTIFS('Test-keyslar'!$B$2:$B$167,"Katalog ma'lumotnomalari",'Test-keyslar'!$P$2:$P$167,"Skipped") | O23: =COUNTIFS('Test-keyslar'!$B$2:$B$167,"Katalog ma'lumotnomalari",'Test-keyslar'!$P$2:$P$167,"Bajarilmagan")
A24: ORD — Buyurtmalar | B24: =COUNTIF('Test-keyslar'!$B$2:$B$167,"Buyurtmalar") | C24: =COUNTIFS('Test-keyslar'!$B$2:$B$167,"Buyurtmalar",'Test-keyslar'!$E$2:$E$167,"P1") | D24: =COUNTIFS('Test-keyslar'!$B$2:$B$167,"Buyurtmalar",'Test-keyslar'!$E$2:$E$167,"P2") | E24: =COUNTIFS('Test-keyslar'!$B$2:$B$167,"Buyurtmalar",'Test-keyslar'!$E$2:$E$167,"P3") | F24: =COUNTIFS('Test-keyslar'!$B$2:$B$167,"Buyurtmalar",'Test-keyslar'!$L$2:$L$167,"Ha") | G24: =COUNTIFS('Test-keyslar'!$B$2:$B$167,"Buyurtmalar",'Test-keyslar'!$L$2:$L$167,"Qisman") | H24: =COUNTIFS('Test-keyslar'!$B$2:$B$167,"Buyurtmalar",'Test-keyslar'!$L$2:$L$167,"Yo'q") | I24: =COUNTIFS('Test-keyslar'!$B$2:$B$167,"Buyurtmalar",'Test-keyslar'!$N$2:$N$167,"Avtomatlashtirilgan") | J24: =IF(B24=0,0,I24/B24) | K24: =COUNTIFS('Test-keyslar'!$B$2:$B$167,"Buyurtmalar",'Test-keyslar'!$P$2:$P$167,"Passed") | L24: =COUNTIFS('Test-keyslar'!$B$2:$B$167,"Buyurtmalar",'Test-keyslar'!$P$2:$P$167,"Failed") | M24: =COUNTIFS('Test-keyslar'!$B$2:$B$167,"Buyurtmalar",'Test-keyslar'!$P$2:$P$167,"Blocked") | N24: =COUNTIFS('Test-keyslar'!$B$2:$B$167,"Buyurtmalar",'Test-keyslar'!$P$2:$P$167,"Skipped") | O24: =COUNTIFS('Test-keyslar'!$B$2:$B$167,"Buyurtmalar",'Test-keyslar'!$P$2:$P$167,"Bajarilmagan")
A25: SW — Sotuv oynasi | B25: =COUNTIF('Test-keyslar'!$B$2:$B$167,"Sotuv oynasi") | C25: =COUNTIFS('Test-keyslar'!$B$2:$B$167,"Sotuv oynasi",'Test-keyslar'!$E$2:$E$167,"P1") | D25: =COUNTIFS('Test-keyslar'!$B$2:$B$167,"Sotuv oynasi",'Test-keyslar'!$E$2:$E$167,"P2") | E25: =COUNTIFS('Test-keyslar'!$B$2:$B$167,"Sotuv oynasi",'Test-keyslar'!$E$2:$E$167,"P3") | F25: =COUNTIFS('Test-keyslar'!$B$2:$B$167,"Sotuv oynasi",'Test-keyslar'!$L$2:$L$167,"Ha") | G25: =COUNTIFS('Test-keyslar'!$B$2:$B$167,"Sotuv oynasi",'Test-keyslar'!$L$2:$L$167,"Qisman") | H25: =COUNTIFS('Test-keyslar'!$B$2:$B$167,"Sotuv oynasi",'Test-keyslar'!$L$2:$L$167,"Yo'q") | I25: =COUNTIFS('Test-keyslar'!$B$2:$B$167,"Sotuv oynasi",'Test-keyslar'!$N$2:$N$167,"Avtomatlashtirilgan") | J25: =IF(B25=0,0,I25/B25) | K25: =COUNTIFS('Test-keyslar'!$B$2:$B$167,"Sotuv oynasi",'Test-keyslar'!$P$2:$P$167,"Passed") | L25: =COUNTIFS('Test-keyslar'!$B$2:$B$167,"Sotuv oynasi",'Test-keyslar'!$P$2:$P$167,"Failed") | M25: =COUNTIFS('Test-keyslar'!$B$2:$B$167,"Sotuv oynasi",'Test-keyslar'!$P$2:$P$167,"Blocked") | N25: =COUNTIFS('Test-keyslar'!$B$2:$B$167,"Sotuv oynasi",'Test-keyslar'!$P$2:$P$167,"Skipped") | O25: =COUNTIFS('Test-keyslar'!$B$2:$B$167,"Sotuv oynasi",'Test-keyslar'!$P$2:$P$167,"Bajarilmagan")
A26: RET — Mahsulot qaytarish | B26: =COUNTIF('Test-keyslar'!$B$2:$B$167,"Mahsulot qaytarish") | C26: =COUNTIFS('Test-keyslar'!$B$2:$B$167,"Mahsulot qaytarish",'Test-keyslar'!$E$2:$E$167,"P1") | D26: =COUNTIFS('Test-keyslar'!$B$2:$B$167,"Mahsulot qaytarish",'Test-keyslar'!$E$2:$E$167,"P2") | E26: =COUNTIFS('Test-keyslar'!$B$2:$B$167,"Mahsulot qaytarish",'Test-keyslar'!$E$2:$E$167,"P3") | F26: =COUNTIFS('Test-keyslar'!$B$2:$B$167,"Mahsulot qaytarish",'Test-keyslar'!$L$2:$L$167,"Ha") | G26: =COUNTIFS('Test-keyslar'!$B$2:$B$167,"Mahsulot qaytarish",'Test-keyslar'!$L$2:$L$167,"Qisman") | H26: =COUNTIFS('Test-keyslar'!$B$2:$B$167,"Mahsulot qaytarish",'Test-keyslar'!$L$2:$L$167,"Yo'q") | I26: =COUNTIFS('Test-keyslar'!$B$2:$B$167,"Mahsulot qaytarish",'Test-keyslar'!$N$2:$N$167,"Avtomatlashtirilgan") | J26: =IF(B26=0,0,I26/B26) | K26: =COUNTIFS('Test-keyslar'!$B$2:$B$167,"Mahsulot qaytarish",'Test-keyslar'!$P$2:$P$167,"Passed") | L26: =COUNTIFS('Test-keyslar'!$B$2:$B$167,"Mahsulot qaytarish",'Test-keyslar'!$P$2:$P$167,"Failed") | M26: =COUNTIFS('Test-keyslar'!$B$2:$B$167,"Mahsulot qaytarish",'Test-keyslar'!$P$2:$P$167,"Blocked") | N26: =COUNTIFS('Test-keyslar'!$B$2:$B$167,"Mahsulot qaytarish",'Test-keyslar'!$P$2:$P$167,"Skipped") | O26: =COUNTIFS('Test-keyslar'!$B$2:$B$167,"Mahsulot qaytarish",'Test-keyslar'!$P$2:$P$167,"Bajarilmagan")
A27: BIL — Hisob-kitob (kassa) | B27: =COUNTIF('Test-keyslar'!$B$2:$B$167,"Hisob-kitob (kassa)") | C27: =COUNTIFS('Test-keyslar'!$B$2:$B$167,"Hisob-kitob (kassa)",'Test-keyslar'!$E$2:$E$167,"P1") | D27: =COUNTIFS('Test-keyslar'!$B$2:$B$167,"Hisob-kitob (kassa)",'Test-keyslar'!$E$2:$E$167,"P2") | E27: =COUNTIFS('Test-keyslar'!$B$2:$B$167,"Hisob-kitob (kassa)",'Test-keyslar'!$E$2:$E$167,"P3") | F27: =COUNTIFS('Test-keyslar'!$B$2:$B$167,"Hisob-kitob (kassa)",'Test-keyslar'!$L$2:$L$167,"Ha") | G27: =COUNTIFS('Test-keyslar'!$B$2:$B$167,"Hisob-kitob (kassa)",'Test-keyslar'!$L$2:$L$167,"Qisman") | H27: =COUNTIFS('Test-keyslar'!$B$2:$B$167,"Hisob-kitob (kassa)",'Test-keyslar'!$L$2:$L$167,"Yo'q") | I27: =COUNTIFS('Test-keyslar'!$B$2:$B$167,"Hisob-kitob (kassa)",'Test-keyslar'!$N$2:$N$167,"Avtomatlashtirilgan") | J27: =IF(B27=0,0,I27/B27) | K27: =COUNTIFS('Test-keyslar'!$B$2:$B$167,"Hisob-kitob (kassa)",'Test-keyslar'!$P$2:$P$167,"Passed") | L27: =COUNTIFS('Test-keyslar'!$B$2:$B$167,"Hisob-kitob (kassa)",'Test-keyslar'!$P$2:$P$167,"Failed") | M27: =COUNTIFS('Test-keyslar'!$B$2:$B$167,"Hisob-kitob (kassa)",'Test-keyslar'!$P$2:$P$167,"Blocked") | N27: =COUNTIFS('Test-keyslar'!$B$2:$B$167,"Hisob-kitob (kassa)",'Test-keyslar'!$P$2:$P$167,"Skipped") | O27: =COUNTIFS('Test-keyslar'!$B$2:$B$167,"Hisob-kitob (kassa)",'Test-keyslar'!$P$2:$P$167,"Bajarilmagan")
A28: USR — Foydalanuvchilar va mijoz rollari | B28: =COUNTIF('Test-keyslar'!$B$2:$B$167,"Foydalanuvchilar va mijoz rollari") | C28: =COUNTIFS('Test-keyslar'!$B$2:$B$167,"Foydalanuvchilar va mijoz rollari",'Test-keyslar'!$E$2:$E$167,"P1") | D28: =COUNTIFS('Test-keyslar'!$B$2:$B$167,"Foydalanuvchilar va mijoz rollari",'Test-keyslar'!$E$2:$E$167,"P2") | E28: =COUNTIFS('Test-keyslar'!$B$2:$B$167,"Foydalanuvchilar va mijoz rollari",'Test-keyslar'!$E$2:$E$167,"P3") | F28: =COUNTIFS('Test-keyslar'!$B$2:$B$167,"Foydalanuvchilar va mijoz rollari",'Test-keyslar'!$L$2:$L$167,"Ha") | G28: =COUNTIFS('Test-keyslar'!$B$2:$B$167,"Foydalanuvchilar va mijoz rollari",'Test-keyslar'!$L$2:$L$167,"Qisman") | H28: =COUNTIFS('Test-keyslar'!$B$2:$B$167,"Foydalanuvchilar va mijoz rollari",'Test-keyslar'!$L$2:$L$167,"Yo'q") | I28: =COUNTIFS('Test-keyslar'!$B$2:$B$167,"Foydalanuvchilar va mijoz rollari",'Test-keyslar'!$N$2:$N$167,"Avtomatlashtirilgan") | J28: =IF(B28=0,0,I28/B28) | K28: =COUNTIFS('Test-keyslar'!$B$2:$B$167,"Foydalanuvchilar va mijoz rollari",'Test-keyslar'!$P$2:$P$167,"Passed") | L28: =COUNTIFS('Test-keyslar'!$B$2:$B$167,"Foydalanuvchilar va mijoz rollari",'Test-keyslar'!$P$2:$P$167,"Failed") | M28: =COUNTIFS('Test-keyslar'!$B$2:$B$167,"Foydalanuvchilar va mijoz rollari",'Test-keyslar'!$P$2:$P$167,"Blocked") | N28: =COUNTIFS('Test-keyslar'!$B$2:$B$167,"Foydalanuvchilar va mijoz rollari",'Test-keyslar'!$P$2:$P$167,"Skipped") | O28: =COUNTIFS('Test-keyslar'!$B$2:$B$167,"Foydalanuvchilar va mijoz rollari",'Test-keyslar'!$P$2:$P$167,"Bajarilmagan")
A29: REQ — Mijoz so'rovlari | B29: =COUNTIF('Test-keyslar'!$B$2:$B$167,"Mijoz so'rovlari") | C29: =COUNTIFS('Test-keyslar'!$B$2:$B$167,"Mijoz so'rovlari",'Test-keyslar'!$E$2:$E$167,"P1") | D29: =COUNTIFS('Test-keyslar'!$B$2:$B$167,"Mijoz so'rovlari",'Test-keyslar'!$E$2:$E$167,"P2") | E29: =COUNTIFS('Test-keyslar'!$B$2:$B$167,"Mijoz so'rovlari",'Test-keyslar'!$E$2:$E$167,"P3") | F29: =COUNTIFS('Test-keyslar'!$B$2:$B$167,"Mijoz so'rovlari",'Test-keyslar'!$L$2:$L$167,"Ha") | G29: =COUNTIFS('Test-keyslar'!$B$2:$B$167,"Mijoz so'rovlari",'Test-keyslar'!$L$2:$L$167,"Qisman") | H29: =COUNTIFS('Test-keyslar'!$B$2:$B$167,"Mijoz so'rovlari",'Test-keyslar'!$L$2:$L$167,"Yo'q") | I29: =COUNTIFS('Test-keyslar'!$B$2:$B$167,"Mijoz so'rovlari",'Test-keyslar'!$N$2:$N$167,"Avtomatlashtirilgan") | J29: =IF(B29=0,0,I29/B29) | K29: =COUNTIFS('Test-keyslar'!$B$2:$B$167,"Mijoz so'rovlari",'Test-keyslar'!$P$2:$P$167,"Passed") | L29: =COUNTIFS('Test-keyslar'!$B$2:$B$167,"Mijoz so'rovlari",'Test-keyslar'!$P$2:$P$167,"Failed") | M29: =COUNTIFS('Test-keyslar'!$B$2:$B$167,"Mijoz so'rovlari",'Test-keyslar'!$P$2:$P$167,"Blocked") | N29: =COUNTIFS('Test-keyslar'!$B$2:$B$167,"Mijoz so'rovlari",'Test-keyslar'!$P$2:$P$167,"Skipped") | O29: =COUNTIFS('Test-keyslar'!$B$2:$B$167,"Mijoz so'rovlari",'Test-keyslar'!$P$2:$P$167,"Bajarilmagan")
A30: WH — Omborlar | B30: =COUNTIF('Test-keyslar'!$B$2:$B$167,"Omborlar") | C30: =COUNTIFS('Test-keyslar'!$B$2:$B$167,"Omborlar",'Test-keyslar'!$E$2:$E$167,"P1") | D30: =COUNTIFS('Test-keyslar'!$B$2:$B$167,"Omborlar",'Test-keyslar'!$E$2:$E$167,"P2") | E30: =COUNTIFS('Test-keyslar'!$B$2:$B$167,"Omborlar",'Test-keyslar'!$E$2:$E$167,"P3") | F30: =COUNTIFS('Test-keyslar'!$B$2:$B$167,"Omborlar",'Test-keyslar'!$L$2:$L$167,"Ha") | G30: =COUNTIFS('Test-keyslar'!$B$2:$B$167,"Omborlar",'Test-keyslar'!$L$2:$L$167,"Qisman") | H30: =COUNTIFS('Test-keyslar'!$B$2:$B$167,"Omborlar",'Test-keyslar'!$L$2:$L$167,"Yo'q") | I30: =COUNTIFS('Test-keyslar'!$B$2:$B$167,"Omborlar",'Test-keyslar'!$N$2:$N$167,"Avtomatlashtirilgan") | J30: =IF(B30=0,0,I30/B30) | K30: =COUNTIFS('Test-keyslar'!$B$2:$B$167,"Omborlar",'Test-keyslar'!$P$2:$P$167,"Passed") | L30: =COUNTIFS('Test-keyslar'!$B$2:$B$167,"Omborlar",'Test-keyslar'!$P$2:$P$167,"Failed") | M30: =COUNTIFS('Test-keyslar'!$B$2:$B$167,"Omborlar",'Test-keyslar'!$P$2:$P$167,"Blocked") | N30: =COUNTIFS('Test-keyslar'!$B$2:$B$167,"Omborlar",'Test-keyslar'!$P$2:$P$167,"Skipped") | O30: =COUNTIFS('Test-keyslar'!$B$2:$B$167,"Omborlar",'Test-keyslar'!$P$2:$P$167,"Bajarilmagan")
A31: CUR — Valyuta | B31: =COUNTIF('Test-keyslar'!$B$2:$B$167,"Valyuta") | C31: =COUNTIFS('Test-keyslar'!$B$2:$B$167,"Valyuta",'Test-keyslar'!$E$2:$E$167,"P1") | D31: =COUNTIFS('Test-keyslar'!$B$2:$B$167,"Valyuta",'Test-keyslar'!$E$2:$E$167,"P2") | E31: =COUNTIFS('Test-keyslar'!$B$2:$B$167,"Valyuta",'Test-keyslar'!$E$2:$E$167,"P3") | F31: =COUNTIFS('Test-keyslar'!$B$2:$B$167,"Valyuta",'Test-keyslar'!$L$2:$L$167,"Ha") | G31: =COUNTIFS('Test-keyslar'!$B$2:$B$167,"Valyuta",'Test-keyslar'!$L$2:$L$167,"Qisman") | H31: =COUNTIFS('Test-keyslar'!$B$2:$B$167,"Valyuta",'Test-keyslar'!$L$2:$L$167,"Yo'q") | I31: =COUNTIFS('Test-keyslar'!$B$2:$B$167,"Valyuta",'Test-keyslar'!$N$2:$N$167,"Avtomatlashtirilgan") | J31: =IF(B31=0,0,I31/B31) | K31: =COUNTIFS('Test-keyslar'!$B$2:$B$167,"Valyuta",'Test-keyslar'!$P$2:$P$167,"Passed") | L31: =COUNTIFS('Test-keyslar'!$B$2:$B$167,"Valyuta",'Test-keyslar'!$P$2:$P$167,"Failed") | M31: =COUNTIFS('Test-keyslar'!$B$2:$B$167,"Valyuta",'Test-keyslar'!$P$2:$P$167,"Blocked") | N31: =COUNTIFS('Test-keyslar'!$B$2:$B$167,"Valyuta",'Test-keyslar'!$P$2:$P$167,"Skipped") | O31: =COUNTIFS('Test-keyslar'!$B$2:$B$167,"Valyuta",'Test-keyslar'!$P$2:$P$167,"Bajarilmagan")
A32: BAN — Bannerlar | B32: =COUNTIF('Test-keyslar'!$B$2:$B$167,"Bannerlar") | C32: =COUNTIFS('Test-keyslar'!$B$2:$B$167,"Bannerlar",'Test-keyslar'!$E$2:$E$167,"P1") | D32: =COUNTIFS('Test-keyslar'!$B$2:$B$167,"Bannerlar",'Test-keyslar'!$E$2:$E$167,"P2") | E32: =COUNTIFS('Test-keyslar'!$B$2:$B$167,"Bannerlar",'Test-keyslar'!$E$2:$E$167,"P3") | F32: =COUNTIFS('Test-keyslar'!$B$2:$B$167,"Bannerlar",'Test-keyslar'!$L$2:$L$167,"Ha") | G32: =COUNTIFS('Test-keyslar'!$B$2:$B$167,"Bannerlar",'Test-keyslar'!$L$2:$L$167,"Qisman") | H32: =COUNTIFS('Test-keyslar'!$B$2:$B$167,"Bannerlar",'Test-keyslar'!$L$2:$L$167,"Yo'q") | I32: =COUNTIFS('Test-keyslar'!$B$2:$B$167,"Bannerlar",'Test-keyslar'!$N$2:$N$167,"Avtomatlashtirilgan") | J32: =IF(B32=0,0,I32/B32) | K32: =COUNTIFS('Test-keyslar'!$B$2:$B$167,"Bannerlar",'Test-keyslar'!$P$2:$P$167,"Passed") | L32: =COUNTIFS('Test-keyslar'!$B$2:$B$167,"Bannerlar",'Test-keyslar'!$P$2:$P$167,"Failed") | M32: =COUNTIFS('Test-keyslar'!$B$2:$B$167,"Bannerlar",'Test-keyslar'!$P$2:$P$167,"Blocked") | N32: =COUNTIFS('Test-keyslar'!$B$2:$B$167,"Bannerlar",'Test-keyslar'!$P$2:$P$167,"Skipped") | O32: =COUNTIFS('Test-keyslar'!$B$2:$B$167,"Bannerlar",'Test-keyslar'!$P$2:$P$167,"Bajarilmagan")
A33: DEBT — Qarz va hamyon | B33: =COUNTIF('Test-keyslar'!$B$2:$B$167,"Qarz va hamyon") | C33: =COUNTIFS('Test-keyslar'!$B$2:$B$167,"Qarz va hamyon",'Test-keyslar'!$E$2:$E$167,"P1") | D33: =COUNTIFS('Test-keyslar'!$B$2:$B$167,"Qarz va hamyon",'Test-keyslar'!$E$2:$E$167,"P2") | E33: =COUNTIFS('Test-keyslar'!$B$2:$B$167,"Qarz va hamyon",'Test-keyslar'!$E$2:$E$167,"P3") | F33: =COUNTIFS('Test-keyslar'!$B$2:$B$167,"Qarz va hamyon",'Test-keyslar'!$L$2:$L$167,"Ha") | G33: =COUNTIFS('Test-keyslar'!$B$2:$B$167,"Qarz va hamyon",'Test-keyslar'!$L$2:$L$167,"Qisman") | H33: =COUNTIFS('Test-keyslar'!$B$2:$B$167,"Qarz va hamyon",'Test-keyslar'!$L$2:$L$167,"Yo'q") | I33: =COUNTIFS('Test-keyslar'!$B$2:$B$167,"Qarz va hamyon",'Test-keyslar'!$N$2:$N$167,"Avtomatlashtirilgan") | J33: =IF(B33=0,0,I33/B33) | K33: =COUNTIFS('Test-keyslar'!$B$2:$B$167,"Qarz va hamyon",'Test-keyslar'!$P$2:$P$167,"Passed") | L33: =COUNTIFS('Test-keyslar'!$B$2:$B$167,"Qarz va hamyon",'Test-keyslar'!$P$2:$P$167,"Failed") | M33: =COUNTIFS('Test-keyslar'!$B$2:$B$167,"Qarz va hamyon",'Test-keyslar'!$P$2:$P$167,"Blocked") | N33: =COUNTIFS('Test-keyslar'!$B$2:$B$167,"Qarz va hamyon",'Test-keyslar'!$P$2:$P$167,"Skipped") | O33: =COUNTIFS('Test-keyslar'!$B$2:$B$167,"Qarz va hamyon",'Test-keyslar'!$P$2:$P$167,"Bajarilmagan")
A34: MSG — Xabarlar (push, chat) | B34: =COUNTIF('Test-keyslar'!$B$2:$B$167,"Xabarlar (push, chat)") | C34: =COUNTIFS('Test-keyslar'!$B$2:$B$167,"Xabarlar (push, chat)",'Test-keyslar'!$E$2:$E$167,"P1") | D34: =COUNTIFS('Test-keyslar'!$B$2:$B$167,"Xabarlar (push, chat)",'Test-keyslar'!$E$2:$E$167,"P2") | E34: =COUNTIFS('Test-keyslar'!$B$2:$B$167,"Xabarlar (push, chat)",'Test-keyslar'!$E$2:$E$167,"P3") | F34: =COUNTIFS('Test-keyslar'!$B$2:$B$167,"Xabarlar (push, chat)",'Test-keyslar'!$L$2:$L$167,"Ha") | G34: =COUNTIFS('Test-keyslar'!$B$2:$B$167,"Xabarlar (push, chat)",'Test-keyslar'!$L$2:$L$167,"Qisman") | H34: =COUNTIFS('Test-keyslar'!$B$2:$B$167,"Xabarlar (push, chat)",'Test-keyslar'!$L$2:$L$167,"Yo'q") | I34: =COUNTIFS('Test-keyslar'!$B$2:$B$167,"Xabarlar (push, chat)",'Test-keyslar'!$N$2:$N$167,"Avtomatlashtirilgan") | J34: =IF(B34=0,0,I34/B34) | K34: =COUNTIFS('Test-keyslar'!$B$2:$B$167,"Xabarlar (push, chat)",'Test-keyslar'!$P$2:$P$167,"Passed") | L34: =COUNTIFS('Test-keyslar'!$B$2:$B$167,"Xabarlar (push, chat)",'Test-keyslar'!$P$2:$P$167,"Failed") | M34: =COUNTIFS('Test-keyslar'!$B$2:$B$167,"Xabarlar (push, chat)",'Test-keyslar'!$P$2:$P$167,"Blocked") | N34: =COUNTIFS('Test-keyslar'!$B$2:$B$167,"Xabarlar (push, chat)",'Test-keyslar'!$P$2:$P$167,"Skipped") | O34: =COUNTIFS('Test-keyslar'!$B$2:$B$167,"Xabarlar (push, chat)",'Test-keyslar'!$P$2:$P$167,"Bajarilmagan")
A35: PERM — Ruxsatlar | B35: =COUNTIF('Test-keyslar'!$B$2:$B$167,"Ruxsatlar") | C35: =COUNTIFS('Test-keyslar'!$B$2:$B$167,"Ruxsatlar",'Test-keyslar'!$E$2:$E$167,"P1") | D35: =COUNTIFS('Test-keyslar'!$B$2:$B$167,"Ruxsatlar",'Test-keyslar'!$E$2:$E$167,"P2") | E35: =COUNTIFS('Test-keyslar'!$B$2:$B$167,"Ruxsatlar",'Test-keyslar'!$E$2:$E$167,"P3") | F35: =COUNTIFS('Test-keyslar'!$B$2:$B$167,"Ruxsatlar",'Test-keyslar'!$L$2:$L$167,"Ha") | G35: =COUNTIFS('Test-keyslar'!$B$2:$B$167,"Ruxsatlar",'Test-keyslar'!$L$2:$L$167,"Qisman") | H35: =COUNTIFS('Test-keyslar'!$B$2:$B$167,"Ruxsatlar",'Test-keyslar'!$L$2:$L$167,"Yo'q") | I35: =COUNTIFS('Test-keyslar'!$B$2:$B$167,"Ruxsatlar",'Test-keyslar'!$N$2:$N$167,"Avtomatlashtirilgan") | J35: =IF(B35=0,0,I35/B35) | K35: =COUNTIFS('Test-keyslar'!$B$2:$B$167,"Ruxsatlar",'Test-keyslar'!$P$2:$P$167,"Passed") | L35: =COUNTIFS('Test-keyslar'!$B$2:$B$167,"Ruxsatlar",'Test-keyslar'!$P$2:$P$167,"Failed") | M35: =COUNTIFS('Test-keyslar'!$B$2:$B$167,"Ruxsatlar",'Test-keyslar'!$P$2:$P$167,"Blocked") | N35: =COUNTIFS('Test-keyslar'!$B$2:$B$167,"Ruxsatlar",'Test-keyslar'!$P$2:$P$167,"Skipped") | O35: =COUNTIFS('Test-keyslar'!$B$2:$B$167,"Ruxsatlar",'Test-keyslar'!$P$2:$P$167,"Bajarilmagan")
A36: REP — Hisobotlar | B36: =COUNTIF('Test-keyslar'!$B$2:$B$167,"Hisobotlar") | C36: =COUNTIFS('Test-keyslar'!$B$2:$B$167,"Hisobotlar",'Test-keyslar'!$E$2:$E$167,"P1") | D36: =COUNTIFS('Test-keyslar'!$B$2:$B$167,"Hisobotlar",'Test-keyslar'!$E$2:$E$167,"P2") | E36: =COUNTIFS('Test-keyslar'!$B$2:$B$167,"Hisobotlar",'Test-keyslar'!$E$2:$E$167,"P3") | F36: =COUNTIFS('Test-keyslar'!$B$2:$B$167,"Hisobotlar",'Test-keyslar'!$L$2:$L$167,"Ha") | G36: =COUNTIFS('Test-keyslar'!$B$2:$B$167,"Hisobotlar",'Test-keyslar'!$L$2:$L$167,"Qisman") | H36: =COUNTIFS('Test-keyslar'!$B$2:$B$167,"Hisobotlar",'Test-keyslar'!$L$2:$L$167,"Yo'q") | I36: =COUNTIFS('Test-keyslar'!$B$2:$B$167,"Hisobotlar",'Test-keyslar'!$N$2:$N$167,"Avtomatlashtirilgan") | J36: =IF(B36=0,0,I36/B36) | K36: =COUNTIFS('Test-keyslar'!$B$2:$B$167,"Hisobotlar",'Test-keyslar'!$P$2:$P$167,"Passed") | L36: =COUNTIFS('Test-keyslar'!$B$2:$B$167,"Hisobotlar",'Test-keyslar'!$P$2:$P$167,"Failed") | M36: =COUNTIFS('Test-keyslar'!$B$2:$B$167,"Hisobotlar",'Test-keyslar'!$P$2:$P$167,"Blocked") | N36: =COUNTIFS('Test-keyslar'!$B$2:$B$167,"Hisobotlar",'Test-keyslar'!$P$2:$P$167,"Skipped") | O36: =COUNTIFS('Test-keyslar'!$B$2:$B$167,"Hisobotlar",'Test-keyslar'!$P$2:$P$167,"Bajarilmagan")
A37: E2E — Admin ↔ vitrina stsenariylari | B37: =COUNTIF('Test-keyslar'!$B$2:$B$167,"Admin ↔ vitrina stsenariylari") | C37: =COUNTIFS('Test-keyslar'!$B$2:$B$167,"Admin ↔ vitrina stsenariylari",'Test-keyslar'!$E$2:$E$167,"P1") | D37: =COUNTIFS('Test-keyslar'!$B$2:$B$167,"Admin ↔ vitrina stsenariylari",'Test-keyslar'!$E$2:$E$167,"P2") | E37: =COUNTIFS('Test-keyslar'!$B$2:$B$167,"Admin ↔ vitrina stsenariylari",'Test-keyslar'!$E$2:$E$167,"P3") | F37: =COUNTIFS('Test-keyslar'!$B$2:$B$167,"Admin ↔ vitrina stsenariylari",'Test-keyslar'!$L$2:$L$167,"Ha") | G37: =COUNTIFS('Test-keyslar'!$B$2:$B$167,"Admin ↔ vitrina stsenariylari",'Test-keyslar'!$L$2:$L$167,"Qisman") | H37: =COUNTIFS('Test-keyslar'!$B$2:$B$167,"Admin ↔ vitrina stsenariylari",'Test-keyslar'!$L$2:$L$167,"Yo'q") | I37: =COUNTIFS('Test-keyslar'!$B$2:$B$167,"Admin ↔ vitrina stsenariylari",'Test-keyslar'!$N$2:$N$167,"Avtomatlashtirilgan") | J37: =IF(B37=0,0,I37/B37) | K37: =COUNTIFS('Test-keyslar'!$B$2:$B$167,"Admin ↔ vitrina stsenariylari",'Test-keyslar'!$P$2:$P$167,"Passed") | L37: =COUNTIFS('Test-keyslar'!$B$2:$B$167,"Admin ↔ vitrina stsenariylari",'Test-keyslar'!$P$2:$P$167,"Failed") | M37: =COUNTIFS('Test-keyslar'!$B$2:$B$167,"Admin ↔ vitrina stsenariylari",'Test-keyslar'!$P$2:$P$167,"Blocked") | N37: =COUNTIFS('Test-keyslar'!$B$2:$B$167,"Admin ↔ vitrina stsenariylari",'Test-keyslar'!$P$2:$P$167,"Skipped") | O37: =COUNTIFS('Test-keyslar'!$B$2:$B$167,"Admin ↔ vitrina stsenariylari",'Test-keyslar'!$P$2:$P$167,"Bajarilmagan")
A38: GEN — Interfeysning umumiy tekshiruvlari | B38: =COUNTIF('Test-keyslar'!$B$2:$B$167,"Interfeysning umumiy tekshiruvlari") | C38: =COUNTIFS('Test-keyslar'!$B$2:$B$167,"Interfeysning umumiy tekshiruvlari",'Test-keyslar'!$E$2:$E$167,"P1") | D38: =COUNTIFS('Test-keyslar'!$B$2:$B$167,"Interfeysning umumiy tekshiruvlari",'Test-keyslar'!$E$2:$E$167,"P2") | E38: =COUNTIFS('Test-keyslar'!$B$2:$B$167,"Interfeysning umumiy tekshiruvlari",'Test-keyslar'!$E$2:$E$167,"P3") | F38: =COUNTIFS('Test-keyslar'!$B$2:$B$167,"Interfeysning umumiy tekshiruvlari",'Test-keyslar'!$L$2:$L$167,"Ha") | G38: =COUNTIFS('Test-keyslar'!$B$2:$B$167,"Interfeysning umumiy tekshiruvlari",'Test-keyslar'!$L$2:$L$167,"Qisman") | H38: =COUNTIFS('Test-keyslar'!$B$2:$B$167,"Interfeysning umumiy tekshiruvlari",'Test-keyslar'!$L$2:$L$167,"Yo'q") | I38: =COUNTIFS('Test-keyslar'!$B$2:$B$167,"Interfeysning umumiy tekshiruvlari",'Test-keyslar'!$N$2:$N$167,"Avtomatlashtirilgan") | J38: =IF(B38=0,0,I38/B38) | K38: =COUNTIFS('Test-keyslar'!$B$2:$B$167,"Interfeysning umumiy tekshiruvlari",'Test-keyslar'!$P$2:$P$167,"Passed") | L38: =COUNTIFS('Test-keyslar'!$B$2:$B$167,"Interfeysning umumiy tekshiruvlari",'Test-keyslar'!$P$2:$P$167,"Failed") | M38: =COUNTIFS('Test-keyslar'!$B$2:$B$167,"Interfeysning umumiy tekshiruvlari",'Test-keyslar'!$P$2:$P$167,"Blocked") | N38: =COUNTIFS('Test-keyslar'!$B$2:$B$167,"Interfeysning umumiy tekshiruvlari",'Test-keyslar'!$P$2:$P$167,"Skipped") | O38: =COUNTIFS('Test-keyslar'!$B$2:$B$167,"Interfeysning umumiy tekshiruvlari",'Test-keyslar'!$P$2:$P$167,"Bajarilmagan")
A39: JAMI | B39: =SUM(B14:B38) | C39: =SUM(C14:C38) | D39: =SUM(D14:D38) | E39: =SUM(E14:E38) | F39: =SUM(F14:F38) | G39: =SUM(G14:G38) | H39: =SUM(H14:H38) | I39: =SUM(I14:I38) | J39: =IF(B39=0,0,I39/B39) | K39: =SUM(K14:K38) | L39: =SUM(L14:L38) | M39: =SUM(M14:M38) | N39: =SUM(N14:N38) | O39: =SUM(O14:O38)
A41: Izohlar
A42: P1 — kritik | B42: Relizni bloklaydi. Smoke-to'plam: har doim bajariladi.
A43: P2 — yuqori | B43: Muhim funksional, to'liq regressda bajariladi.
A44: P3 — o'rta | B44: UI/ikkinchi darajali, vaqt yetmasa keyinga qoldirish mumkin.
A45: Avtomatlashtirish: Ha | B45: Stsenariy barqaror va UI orqali to'liq tekshiriladi (Playwright).
A46: Avtomatlashtirish: Qisman | B46: SMS/OTP, ma'lumot tayyorlash uchun admin panel/API yoki vizual baho kerak.
A47: Avtomatlashtirish: Yo'q | B47: Haqiqiy qurilma kerak yoki destruktiv — faqat qo'lda.
A48: Holat: Avtomatlashtirilgan | B48: aros-ui repozitoriyasida avtotest bor («Avtotest» ustuni).
A49: Progon natijasi | B49: Ro'yxatdan tanlanadi: Passed / Failed / Blocked / Skipped / Bajarilmagan.
A50: Turi | B50: Smoke, Functional, Negative, UI, Security, Integration, Technical, Non-functional.
A51: Talab / manba | B51: Confluence dagi PRD («Manbalar» varag'i) yoki «staging'da tekshirilgan». Integration — admin panelda qadam kerak.

Sheet Test-keyslar
A1: ID | B1: Modul | C1: Submodul | D1: Test-keys nomi | E1: Ustuvorlik | F1: Turi | G1: Dastlabki shartlar | H1: Qadamlar | I1: Test ma'lumotlari | J1: Kutilgan natija | K1: Talab / manba | L1: Avtomatlashtirish mumkinmi (UI) | M1: Avtomatlashtirish bo'yicha izoh | N1: UI-avtomatlashtirish holati | O1: Avtotest (klass#metod) | P1: Progon natijasi | Q1: Izoh / bagga havola
A2: AUTH-001 | B2: Avtorizatsiya va ruxsat | C2: Kirish | D2: Admin panelga muvaffaqiyatli kirish | E2: P1 | F2: Smoke | G2: Foydalanuvchi tizimga kirmagan | H2: 1. https://staging-admin.aros.uz ni ochish 2. Username va parolni kiritish 3. «Login»ni bosish | I2: +998998987882 / <пароль в .env> | J2: Bosh sahifa ochiladi, yuqorida foydalanuvchi avatari, «Successfully completed» xabari | K2: Staging admin panel, 28.10.2026 | L2: Ha | M2: .env da ADMIN_USERNAME/ADMIN_PASSWORD bo'lmasa test o'tkazib yuboriladi | N2: Avtomatlashtirilgan | O2: admin/AdminLoginTest#successfulLogin | P2: Bajarilmagan
A3: AUTH-002 | B3: Avtorizatsiya va ruxsat | C3: Kirish | D3: Noto'g'ri parol bilan kirish | E3: P1 | F3: Negative | G3: Foydalanuvchi tizimga kirmagan | H3: 1. To'g'ri username va noto'g'ri parol kiritish 2. «Login» | J3: Avtorizatsiya xatosi, kirish formasi qoladi, sahifalarga kirish yo'q | L3: Ha | M3: .env da ADMIN_* kerak | N3: Avtomatlashtirilgan | O3: admin/AdminLoginTest#loginFailsWithWrongPassword | P3: Bajarilmagan
A4: AUTH-003 | B4: Avtorizatsiya va ruxsat | C4: Kirish | D4: Bo'sh maydonlar bilan kirish | E4: P2 | F4: Negative | G4: Foydalanuvchi tizimga kirmagan | H4: 1. Bo'sh maydonlar bilan «Login»ni bosish 2. Faqat username ni to'ldirish | J4: Majburiy maydonlar validatsiyasi, so'rov yuborilmaydi | L4: Ha | N4: Avtomatlashtirilmagan | P4: Bajarilmagan
A5: AUTH-004 | B5: Avtorizatsiya va ruxsat | C5: Kirish | D5: Parolni yashirish | E5: P3 | F5: UI | G5: Kirish sahifasi ochiq | H5: 1. Parol kiritish 2. Ko'z belgisini bosish | J5: Parol odatda yashirin; belgi uni ko'rsatadi/yashiradi | L5: Ha | N5: Avtomatlashtirilmagan | P5: Bajarilmagan
A6: AUTH-005 | B6: Avtorizatsiya va ruxsat | C6: Kirish | D6: «Forgot password?» | E6: P3 | F6: Functional | G6: Kirish sahifasi ochiq | H6: 1. «Forgot password?»ni bosish | J6: /forgot-password ochiladi, tiklash formasi ishlaydi | L6: Qisman | M6: SMS/OTP ga bog'liq | N6: Avtomatlashtirilmagan | P6: Bajarilmagan
A7: AUTH-006 | B7: Avtorizatsiya va ruxsat | C7: Sessiya | D7: Avtorizatsiyasiz to'g'ridan-to'g'ri URL | E7: P1 | F7: Security | G7: Foydalanuvchi tizimga kirmagan | H7: 1. /orders/orders-list, /users/user ni to'g'ridan-to'g'ri ochish | J7: /sign-in ga yo'naltiriladi, ma'lumotlar ko'rinmaydi | L7: Ha | N7: Avtomatlashtirilmagan | P7: Bajarilmagan
A8: AUTH-007 | B8: Avtorizatsiya va ruxsat | C8: Sessiya | D8: Sahifa yangilanganda sessiya saqlanadi | E8: P2 | F8: Functional | G8: Admin panelga test akkaunti bilan kirilgan (to'liq huquqlar) | H8: 1. Sahifani yangilash 2. Yangi tabda ochish | J8: Foydalanuvchi tizimda qoladi | L8: Ha | N8: Avtomatlashtirilmagan | P8: Bajarilmagan
A9: AUTH-008 | B9: Avtorizatsiya va ruxsat | C9: Sessiya | D9: Admin paneldan chiqish | E9: P1 | F9: Smoke | G9: Admin panelga test akkaunti bilan kirilgan (to'liq huquqlar) | H9: 1. Avatar menyusi → Logout | J9: Sessiya tugaydi, /sign-in ga yo'naltiriladi; brauzerda «Orqaga» ma'lumotlarni ochmaydi | L9: Ha | N9: Avtomatlashtirilmagan | P9: Bajarilmagan
A10: AUTH-009 | B10: Avtorizatsiya va ruxsat | C10: Ruxsat | D10: Admin panelga ruxsati yo'q foydalanuvchi (mijoz) | E10: P2 | F10: Security | G10: Xodim roli yo'q mijoz akkaunti | H10: 1. Admin panelga mijoz akkaunti bilan kirish | J10: Kirish taqiqlanadi yoki birorta modul ko'rinmaydi | L10: Qisman | M10: Huquqsiz akkaunt kerak | N10: Avtomatlashtirilmagan | P10: Bajarilmagan
A11: DASH-001 | B11: Bosh sahifa (Dashboard) | C11: Filial limiti | D11: «Filial qarz limiti» bloki | E11: P2 | F11: Functional | G11: Admin panelga test akkaunti bilan kirilgan (to'liq huquqlar) | H11: 1. Bosh sahifani ochish 2. Filial tablarini almashtirish | J11: Kartalar: umumiy limit, limitli filiallar qarzi, limitdan oshganlar, limitga yaqin (80–100%), limitsiz filiallar; filial bo'yicha: limit, joriy qarz, qolgan, bandlik %; «Ro'yxatga o'tish» → /debt/warehouse-debt-limits | K11: PRD Filial qarz limiti | L11: Ha | N11: Avtomatlashtirilmagan | P11: Bajarilmagan
A12: DASH-002 | B12: Bosh sahifa (Dashboard) | C12: Kassa | D12: «Kassa hisoboti» bloki: tablar va «Yangilash» | E12: P2 | F12: Functional | G12: Admin panelga test akkaunti bilan kirilgan (to'liq huquqlar) | H12: 1. Ombor tabini tanlash 2. «Yangilash»ni bosish | J12: Faqat tanlangan ombor hisoblanadi; ma'lumot faqat «Yangilash» bosilganda qayta hisoblanadi; xato bo'lsa eski holat xabar bilan qoladi; vaqt yangilanadi | K12: PRD Bosh sahifa — Kassa bloki | L12: Qisman | M12: Summalarni kassa hisoboti bilan solishtirish | N12: Avtomatlashtirilmagan | P12: Bajarilmagan
A13: DASH-003 | B13: Bosh sahifa (Dashboard) | C13: Reyting | D13: Omborlar reytingi bloki | E13: P3 | F13: UI | G13: Admin panelga test akkaunti bilan kirilgan (to'liq huquqlar) | H13: 1. Bosh sahifani pastga aylantirish 2. «Barchasi»ni bosish | J13: Blok ko'rinadi; «Barchasi» → /warehouse/warehouse-rating | L13: Ha | N13: Avtomatlashtirilmagan | P13: Bajarilmagan
A14: DASH-004 | B14: Bosh sahifa (Dashboard) | C14: Ruxsat | D14: Bosh sahifadagi omborlar foydalanuvchi huquqiga qarab | E14: P2 | F14: Security | G14: Foydalanuvchi — bitta ombor sotuvchisi | H14: 1. Bosh sahifani ochish | J14: Faqat o'z omborining tabi ko'rinadi | L14: Qisman | M14: Sotuvchi akkaunti kerak | N14: Avtomatlashtirilmagan | P14: Bajarilmagan
A15: PINC-001 | B15: Qabul qilingan mahsulot (kirim) | C15: Ro'yxat | D15: Kirimlar ro'yxati va filtrlari | E15: P2 | F15: Functional | G15: Admin panelga test akkaunti bilan kirilgan (to'liq huquqlar) | H15: 1. Mahsulotlar amallari → Qabul qilingan mahsulot 2. Filtr: sana oralig'i, ombor, yetkazib beruvchi, status, yetkazish holati | J15: Ro'yxat filtrlanadi; ustunlar: ID, yaratilgan sana, ombor, yetkazib beruvchi, narx, status, yetkazish holati, nashr statusi, nashr qilingan vaqti; sahifalash ishlaydi | L15: Ha | N15: Avtomatlashtirilmagan | P15: Bajarilmagan
A16: PINC-002 | B16: Qabul qilingan mahsulot (kirim) | C16: Yaratish | D16: Kirim hujjatini yaratish | E16: P1 | F16: Smoke | G16: Admin panelga test akkaunti bilan kirilgan (to'liq huquqlar) | H16: 1. «Yaratish» 2. Ombor, yetkazib beruvchi, yetkazish holati, yetkazish sanasi, valyutani tanlash 3. «Add» — variant, miqdor, kirim narxini qo'shish 4. «Saqlash» | I16: Ombor: Asosiy ombor; yetkazib beruvchi — istalgan | J16: Hujjat «Yaratilgan» statusida; qatorga oxirgi kirim narxi, o'rtacha narx, B2B/B2M/B2C narxlari tortiladi | L16: Ha | N16: Avtomatlashtirilmagan | P16: Bajarilmagan
A17: PINC-003 | B17: Qabul qilingan mahsulot (kirim) | C17: Narxlar | D17: O'rtacha narx va ustama hisobi | E17: P1 | F17: Functional | G17: Admin panelga test akkaunti bilan kirilgan (to'liq huquqlar); kirim hujjati ochiq | H17: 1. Kirim narxi, Fare percent, Custom clearance kiritish 2. «Fill income price» / «Apply»ni bosish | J17: O'rtacha narx qayta hisoblanadi; B2B/B2M/B2C narxlari ≥ 1 va [o'rtacha narx; o'rtacha × (1 + Max margin %)] oralig'ida | K17: PRD Product Income Excel Import | L17: Qisman | M17: Formulani calculate-average-prices API orqali solishtirish | N17: Avtomatlashtirilmagan | P17: Bajarilmagan
A18: PINC-004 | B18: Qabul qilingan mahsulot (kirim) | C18: Narxlar | D18: Ruxsat etilgan oraliqdan tashqari sotuv narxi | E18: P1 | F18: Negative | G18: Admin panelga test akkaunti bilan kirilgan (to'liq huquqlar); kirim hujjati ochiq | H18: 1. B2C narxini o'rtacha narxdan past qo'yish 2. «Saqlash» | J18: Saqlash bloklanadi, qatorda xato | L18: Ha | N18: Avtomatlashtirilmagan | P18: Bajarilmagan
A19: PINC-005 | B19: Qabul qilingan mahsulot (kirim) | C19: Excel | D19: Yetkazib beruvchi Excel faylidan qatorlarni import qilish | E19: P2 | F19: Functional | G19: Admin panelga test akkaunti bilan kirilgan (to'liq huquqlar); yangi kirim hujjati ochiq | H19: 1. «Template» — shablonni yuklab olish 2. Variant, miqdor, narxni to'ldirish 3. «Import» | J19: Qatorlar avtomatik to'ldiriladi va darhol saqlashga yaroqli; hosila narxlar tortiladi | K19: PRD Product Income Excel Import | L19: Ha | N19: Avtomatlashtirilmagan | P19: Bajarilmagan
A20: PINC-006 | B20: Qabul qilingan mahsulot (kirim) | C20: Excel | D20: Xatoli Excel import | E20: P2 | F20: Negative | G20: Admin panelga test akkaunti bilan kirilgan (to'liq huquqlar) | H20: 1. Mavjud bo'lmagan variant / bo'sh miqdorli fayl import qilish | J20: Import butunlay rad etiladi (hammasi yoki hech narsa), qator/ustun raqami bilan tushunarli o'zbekcha xato | L20: Ha | N20: Avtomatlashtirilmagan | P20: Bajarilmagan
A21: PINC-007 | B21: Qabul qilingan mahsulot (kirim) | C21: Statuslar | D21: «Yo'lda» → «Qabul qilingan» → «Nashr» | E21: P1 | F21: Smoke | G21: Admin panelga test akkaunti bilan kirilgan (to'liq huquqlar); kirim hujjati «Yaratilgan», yetkazish «Yo'lda» | H21: 1. Yetkazish holatini «Qabul qilingan»ga o'zgartirish 2. Saqlash 3. «Nashr» | J21: Nashr faqat «Qabul qilingan»da mumkin; nashrdan keyin ombor qoldig'i miqdorga oshadi; nashr vaqti to'ldiriladi; hujjat tahrirlash uchun qulflanadi (faqat izoh) | K21: PRD Kirim — qisman kelish | L21: Ha | N21: Avtomatlashtirilmagan | P21: Bajarilmagan
A22: PINC-008 | B22: Qabul qilingan mahsulot (kirim) | C22: Statuslar | D22: Qabul qilinmaguncha nashr qilib bo'lmaydi | E22: P2 | F22: Negative | G22: Admin panelga test akkaunti bilan kirilgan (to'liq huquqlar); hujjat «Yo'lda» | H22: 1. «Nashr»ga urinish | J22: Tugma faol emas / xato | L22: Ha | N22: Avtomatlashtirilmagan | P22: Bajarilmagan
A23: PINC-009 | B23: Qabul qilingan mahsulot (kirim) | C23: Qisman qabul | D23: Qisman kelish («Keldi») | E23: P2 | F23: Functional | G23: Admin panelga test akkaunti bilan kirilgan (to'liq huquqlar); hujjat «Yaratilgan» + «Yo'lda» | H23: 1. Qatorlarni belgilash 2. «Keldi», kelgan miqdorni kiritish (1…hujjatdagi miqdor) 3. «Qabul qilish» | J23: Kelgan miqdor bilan «Qabul qilingan» yangi hujjat yaratiladi; asl hujjatda faqat kelmaganlar qoladi; yig'indilar mos; oraliqdan tashqari — xato, tugma faol emas | K23: PRD Kirim — qisman kelish (AIDT-753) | L23: Ha | N23: Avtomatlashtirilmagan | P23: Bajarilmagan
A24: PINC-010 | B24: Qabul qilingan mahsulot (kirim) | C24: Chop etish | D24: Yorliq chop etish (Label / Yorliq nomi) | E24: P3 | F24: Functional | G24: Admin panelga test akkaunti bilan kirilgan (to'liq huquqlar); mahsulotli kirim hujjati | H24: 1. Qatordagi «Label» / «Print»ni bosish | J24: Yorliq nomi bilan yorliq chop etish oynasi ochiladi | L24: Qisman | M24: Chop etish vizual tekshiriladi | N24: Avtomatlashtirilmagan | P24: Bajarilmagan
A25: PINC-011 | B25: Qabul qilingan mahsulot (kirim) | C25: Bog'liqlik | D25: Kirim «Bo'lsa olar edim» so'rovlarini yopadi | E25: P2 | F25: Integration | G25: Qoldig'i yo'q variantga «Bo'lsa olar edim» so'rovi bor | H25: 1. Shu variant kirimini mijoz omboriga nashr qilish 2. So'rovlar → Bo'lsa olar edim ni ochish | J25: So'rov «Tugallangan», sana, ijrochi va kirim ko'rsatilgan | K25: PRD Bo'lsa olar edim (admin) | L25: Ha | N25: Avtomatlashtirilmagan | P25: Bajarilmagan
A26: PRICE-001 | B26: Narxni o'zgartirish | C26: Hujjat | D26: Narxni o'zgartirish hujjatini yaratish | E26: P1 | F26: Smoke | G26: Admin panelga test akkaunti bilan kirilgan (to'liq huquqlar) | H26: 1. Mahsulotlar amallari → Narxni o'zgartirish → «Yaratish» 2. «Add» variant 3. Yangi B2B/B2C/B2M narxlarini kiritish 4. «Saqlash» | J26: Hujjat saqlanadi; uchta tur bo'yicha eski va yangi narxlar ko'rinadi | L26: Ha | N26: Avtomatlashtirilmagan | P26: Bajarilmagan
A27: PRICE-002 | B27: Narxni o'zgartirish | C27: Nashr | D27: Nashr vitrinadagi narxlarni yangilaydi | E27: P1 | F27: Integration | G27: Admin panelga test akkaunti bilan kirilgan (to'liq huquqlar); narx hujjati saqlangan | H27: 1. «Nashr» 2. Vitrinada mahsulotni mijoz va usta sifatida ochish | J27: Nashr sanasi to'ldiriladi; vitrinada yangi B2C (mijoz) va B2M (usta) narxlari | L27: Ha | N27: Avtomatlashtirilmagan | P27: Bajarilmagan
A28: PRICE-003 | B28: Narxni o'zgartirish | C28: Validatsiya | D28: Bo'sh yoki nol yangi narx | E28: P2 | F28: Negative | G28: Admin panelga test akkaunti bilan kirilgan (to'liq huquqlar) | H28: 1. Yangi narxni bo'sh yoki 0 qoldirish 2. «Saqlash» | J28: Saqlash xato bilan bloklanadi | L28: Ha | N28: Avtomatlashtirilmagan | P28: Bajarilmagan
A29: PRICE-004 | B29: Narxni o'zgartirish | C29: Ro'yxat | D29: Narx hujjatlari ro'yxati | E29: P3 | F29: UI | G29: Admin panelga test akkaunti bilan kirilgan (to'liq huquqlar) | H29: 1. Narxni o'zgartirish ni ochish 2. Qidiruv, sahifalash | J29: Ustunlar: Id, yaratilgan sana, nashr sanasi; sahifalash ishlaydi | L29: Ha | N29: Avtomatlashtirilmagan | P29: Bajarilmagan
A30: INV-001 | B30: Inventarizatsiya | C30: Yaratish | D30: Inventarizatsiyani boshlash | E30: P1 | F30: Smoke | G30: Admin panelga test akkaunti bilan kirilgan (to'liq huquqlar); omborda faol inventarizatsiya yo'q | H30: 1. Mahsulotlar amallari → Inventorizatsiya → «Yaratish» 2. Ombor, tur (Offline/Online) 3. «Start» | J30: Hujjat yaratiladi; ombor brak ombori bilan birga inventarizatsiya rejimida (muzlatilgan) | L30: Ha | N30: Avtomatlashtirilmagan | P30: Bajarilmagan
A31: INV-002 | B31: Inventarizatsiya | C31: Cheklovlar | D31: Bitta omborda ikkinchi inventarizatsiya | E31: P1 | F31: Negative | G31: Admin panelga test akkaunti bilan kirilgan (to'liq huquqlar); omborda faol inventarizatsiya bor | H31: 1. Shu omborga yana bittasini boshlash | J31: Xato bilan bloklanadi; boshqa omborda boshlash mumkin | K31: PRD Inventory | L31: Ha | N31: Avtomatlashtirilmagan | P31: Bajarilmagan
A32: INV-003 | B32: Inventarizatsiya | C32: Cheklovlar | D32: Inventarizatsiya vaqtida ombor amallari | E32: P1 | F32: Negative | G32: Admin panelga test akkaunti bilan kirilgan (to'liq huquqlar); ombor inventarizatsiya rejimida | H32: 1. Shu omborga o'tkazma yuborish / kirimni nashr qilishga urinish | J32: Amallar tushunarli xato bilan bloklanadi | L32: Qisman | N32: Avtomatlashtirilmagan | P32: Bajarilmagan
A33: INV-004 | B33: Inventarizatsiya | C33: Ochiq hujjatlar | D33: Boshlashdan oldin ochiq hujjatlar oynasi | E33: P2 | F33: Functional | G33: Admin panelga test akkaunti bilan kirilgan (to'liq huquqlar); omborda «Yaratilgan/Tayyorlandi/Yo'lda/Qaytarilgan» o'tkazmalar bor | H33: 1. Inventarizatsiyani boshlash | J33: Ochiq hujjatlar oynasi ko'rsatiladi; qaytarilganlar bloklamaydi | L33: Qisman | N33: Avtomatlashtirilmagan | P33: Bajarilmagan
A34: INV-005 | B34: Inventarizatsiya | C34: Excel | D34: Excelni yuklab olish va yuklash | E34: P1 | F34: Functional | G34: Admin panelga test akkaunti bilan kirilgan (to'liq huquqlar); faol inventarizatsiya | H34: 1. «Yuklab olish» 2. Faktni to'ldirish 3. Faylni yuklash | J34: Excelda qoldiqlar va harakat ustunlari bor (Transfer Yaratilgan / Tayyorlandi / Yo'lda / Transfer return); yuklash ma'lumotlarni tekshiradi | L34: Ha | N34: Avtomatlashtirilmagan | P34: Bajarilmagan
A35: INV-006 | B35: Inventarizatsiya | C35: Excel | D35: Noto'g'ri faylni yuklash | E35: P2 | F35: Negative | G35: Admin panelga test akkaunti bilan kirilgan (to'liq huquqlar) | H35: 1. Boshqa ombor fayli / miqdorda harf bor faylni yuklash | J35: Validatsiya xatosi, ma'lumotlar o'zgarmaydi | L35: Ha | N35: Avtomatlashtirilmagan | P35: Bajarilmagan
A36: INV-007 | B36: Inventarizatsiya | C36: Online | D36: Online inventarizatsiya: bo'sh qatorlar o'tkazib yuboriladi | E36: P2 | F36: Functional | G36: Admin panelga test akkaunti bilan kirilgan (to'liq huquqlar) | H36: 1. Tur — Online 2. Faktni faqat 2 qatorda to'ldirish 3. Nashr qilish | J36: Faqat to'ldirilgan qatorlar o'zgaradi; bo'shlarida harakat yo'q | L36: Ha | N36: Avtomatlashtirilmagan | P36: Bajarilmagan
A37: INV-008 | B37: Inventarizatsiya | C37: Nashr | D37: Inventarizatsiyani nashr qilish | E37: P1 | F37: Functional | G37: Admin panelga test akkaunti bilan kirilgan (to'liq huquqlar); fayl yuklangan | H37: 1. Nashr qilish | J37: Qoldiqlar = fakt; harakat tarixi yoziladi; ombor muzlatishdan chiqadi; status «Nashr qilingan» | L37: Ha | N37: Avtomatlashtirilmagan | P37: Bajarilmagan
A38: TRF-001 | B38: Mahsulot yuborish (o'tkazma) | C38: Ro'yxat | D38: O'tkazmalar ro'yxati va tablar | E38: P2 | F38: Functional | G38: Admin panelga test akkaunti bilan kirilgan (to'liq huquqlar) | H38: 1. Mahsulotlar amallari → Mahsulot yuborish 2. Tablar: Hammasi / O'tkazma / So'rov | J38: Ustunlar: ID, turi, yaratilgan sana, qaysi ombordan, qaysi omborga, narx, jo'natilgan, qabul qilingan sana, izoh, holat; tablar tur bo'yicha filtrlaydi | L38: Ha | N38: Avtomatlashtirilmagan | P38: Bajarilmagan
A39: TRF-002 | B39: Mahsulot yuborish (o'tkazma) | C39: O'tkazma | D39: O'tkazma yaratish | E39: P1 | F39: Smoke | G39: Admin panelga test akkaunti bilan kirilgan (to'liq huquqlar) | H39: 1. O'tkazma yaratish: jo'natuvchi (o'z ombori), qabul qiluvchi, mahsulotlar va miqdor 2. Saqlash | J39: Status «Yaratilgan»; jo'natuvchi qoldig'i band qilinadi (bo'sh qoldiq + hujjat bandi ko'rsatiladi) | K39: PRD Product Transfer | L39: Ha | N39: Avtomatlashtirilmagan | P39: Bajarilmagan
A40: TRF-003 | B40: Mahsulot yuborish (o'tkazma) | C40: O'tkazma | D40: Jo'natish va qabul qilish | E40: P1 | F40: Smoke | G40: O'tkazma «Yaratilgan» | H40: 1. Jo'natuvchi: «Jo'natish» 2. Qabul qiluvchi: «Qabul qilish» | J40: «Yo'lda» → «Qabul qilingan»; mahsulot jo'natuvchidan chiqariladi va qabul qiluvchiga qo'shiladi; jo'natish/qabul sanalari to'ldiriladi | L40: Ha | N40: Avtomatlashtirilmagan | P40: Bajarilmagan
A41: TRF-004 | B41: Mahsulot yuborish (o'tkazma) | C41: O'tkazma | D41: O'tkazmani qaytarish va qayta jo'natish | E41: P2 | F41: Functional | G41: O'tkazma «Yo'lda» | H41: 1. Qabul qiluvchi: «Qaytarish» 2. Jo'natuvchi tahrirlab qayta jo'natadi | J41: «Qaytarilgan» → yana «Yo'lda»; qabul qiluvchi «Qaytarilgan»da faqat ko'radi | L41: Ha | N41: Avtomatlashtirilmagan | P41: Bajarilmagan
A42: TRF-005 | B42: Mahsulot yuborish (o'tkazma) | C42: O'tkazma | D42: O'tkazmani bekor qilish | E42: P1 | F42: Functional | G42: O'tkazma «Yaratilgan» | H42: 1. «Bekor qilish» | J42: Status «Bekor qilingan», band jo'natuvchi omborga qaytadi | L42: Ha | N42: Avtomatlashtirilmagan | P42: Bajarilmagan
A43: TRF-006 | B43: Mahsulot yuborish (o'tkazma) | C43: Huquqlar | D43: Jo'natuvchi faqat o'z omboridan | E43: P1 | F43: Security | G43: Foydalanuvchi A omboriga biriktirilgan | H43: 1. O'tkazma yaratish | J43: Jo'natuvchida faqat A ombori; qabul qiluvchi tahrirlay/jo'nata olmaydi | K43: PRD Transfer permission | L43: Qisman | M43: Sotuvchi akkaunti kerak | N43: Avtomatlashtirilmagan | P43: Bajarilmagan
A44: TRF-007 | B44: Mahsulot yuborish (o'tkazma) | C44: So'rov | D44: Mahsulot so'rovi (So'rov) | E44: P1 | F44: Functional | G44: Qabul qiluvchi ombor foydalanuvchisi | H44: 1. «So'rov yaratish»: egasi ombor, mahsulotlar, miqdor 2. Egasi tasdiqlab jo'natadi 3. Qabul qiluvchi qabul qiladi | J44: Qoralama → So'ralgan → (tasdiq) Yaratilgan → Yo'lda → Qabul qilingan; «So'ralgan miqdor» ustuni saqlanadi; «So'rov» belgisi | L44: Ha | N44: Avtomatlashtirilmagan | P44: Bajarilmagan
A45: TRF-008 | B45: Mahsulot yuborish (o'tkazma) | C45: So'rov | D45: So'ralgan miqdordan farq izoh talab qiladi | E45: P2 | F45: Negative | G45: 10 donaga so'rov | H45: 1. Tasdiqlashda izohsiz 7 dona ko'rsatish 2. Izoh kiritish | J45: Izohsiz saqlab bo'lmaydi; izoh bilan — mumkin | L45: Ha | N45: Avtomatlashtirilmagan | P45: Bajarilmagan
A46: TRF-009 | B46: Mahsulot yuborish (o'tkazma) | C46: Bildirishnomalar | D46: Qo'ng'iroqchadagi o'tkazma bildirishnomalari | E46: P3 | F46: Functional | G46: Turli omborlarning ikki foydalanuvchisi | H46: 1. O'tkazmani jo'natish 2. Uni qaytarish | J46: Qabul qiluvchiga «Jo'natildi», jo'natuvchiga «Qaytarildi»; qo'lda yaratilgan «Yaratildi» yubormaydi | K46: PRD Transfer Notifications | L46: Qisman | N46: Avtomatlashtirilmagan | P46: Bajarilmagan
A47: TRF-010 | B47: Mahsulot yuborish (o'tkazma) | C47: Chop etish | D47: O'tkazma hujjatini chop etish | E47: P3 | F47: UI | G47: O'tkazma bor | H47: 1. Ochish 2. «Chop etish» | J47: Mahsulotlar, miqdor, omborlar bilan chop etish shakli | L47: Ha | N47: Avtomatlashtirilmagan | P47: Bajarilmagan
A48: PVAR-001 | B48: Mahsulot varianti (ehtiyoj) | C48: Ehtiyoj | D48: Kerakli / Keraksiz belgisi | E48: P3 | F48: Functional | G48: Admin panelga test akkaunti bilan kirilgan (to'liq huquqlar) | H48: 1. Mahsulotlar amallari → Mahsulot varianti 2. Qatorlarni tanlash 3. «Necessary» / «Unnecessary» | J48: Tanlanganlarda Isnecessary ustuni yangilanadi | L48: Ha | N48: Avtomatlashtirilmagan | P48: Bajarilmagan
A49: PVAR-002 | B49: Mahsulot varianti (ehtiyoj) | C49: Ehtiyoj | D49: «Add normative day» va yuklab olish | E49: P3 | F49: Functional | G49: Admin panelga test akkaunti bilan kirilgan (to'liq huquqlar) | H49: 1. Qatorlarni tanlash → «Add normative day» 2. «Yuklab olish» | J49: Normativ kunlar saqlanadi; Excel jadval bilan mos | L49: Ha | N49: Avtomatlashtirilmagan | P49: Bajarilmagan
A50: DISC-001 | B50: Chegirma va aksiyalar | C50: Yaratish | D50: Aksiya yaratish | E50: P1 | F50: Smoke | G50: Admin panelga test akkaunti bilan kirilgan (to'liq huquqlar) | H50: 1. Mahsulotlar amallari → Chegirma → «Yaratish» 2. Sanalar, omborlar, nomlar UZ/RU/EN 3. «Add» mahsulotlar, B2C/B2M/B2B chegirma narxlari 4. «Saqlash» | J50: Aksiya yaratiladi; har bir narx turi bo'yicha % hisoblanadi | K50: PRD Discount US1 | L50: Ha | N50: Avtomatlashtirilmagan | P50: Bajarilmagan
A51: DISC-002 | B51: Chegirma va aksiyalar | C51: Validatsiya | D51: Chegirma narxi joriy narxdan yuqori | E51: P1 | F51: Negative | G51: Admin panelga test akkaunti bilan kirilgan (to'liq huquqlar) | H51: 1. Chegirma narxini joriy narxdan yuqori qo'yish 2. «Saqlash» | J51: Xato; narxga teng bo'lsa ruxsat | K51: PRD Mijozga xos chegirma | L51: Ha | N51: Avtomatlashtirilmagan | P51: Bajarilmagan
A52: DISC-003 | B52: Chegirma va aksiyalar | C52: Statuslar | D52: Aksiyaning avtomatik statuslari | E52: P1 | F52: Functional | G52: Admin panelga test akkaunti bilan kirilgan (to'liq huquqlar) | H52: 1. Ertadan boshlanadigan aksiya yaratish 2. Joriy sanalar bilan 3. O'tgan sanalar bilan | J52: Upcoming / Active / Expired sanalarga qarab avtomatik | L52: Ha | N52: Avtomatlashtirilmagan | P52: Bajarilmagan
A53: DISC-004 | B53: Chegirma va aksiyalar | C53: Statuslar | D53: Tahrirlash va bekor qilish | E53: P2 | F53: Functional | G53: Upcoming, Active, Expired, Cancelled aksiyalar | H53: 1. Har birini o'zgartirish/bekor qilish | J53: Faqat Upcoming va Active tahrirlanadi/bekor qilinadi; Cancelled va Expired — faqat ko'rish | L53: Ha | N53: Avtomatlashtirilmagan | P53: Bajarilmagan
A54: DISC-005 | B54: Chegirma va aksiyalar | C54: Vitrina | D54: Aksiya vitrinada faqat o'z narx turi uchun | E54: P1 | F54: Integration | G54: Faqat B2C bo'yicha faol aksiya | H54: 1. Mahsulotni mijoz va usta sifatida ochish | J54: Mijoz -%, chizilgan narx va «N kun»ni ko'radi; usta — chegirmasiz | K54: PRD Mijozga xos chegirma (AIDT-817) | L54: Qisman | N54: Avtomatlashtirilmagan | P54: Bajarilmagan
A55: DISC-006 | B55: Chegirma va aksiyalar | C55: Vitrina | D55: Aksiya faqat tanlangan omborlarda | E55: P2 | F55: Integration | G55: A omboridagi aksiya | H55: 1. Vitrinada A, so'ng B ombori do'konini tanlash | J55: Chegirma faqat A uchun | L55: Ha | N55: Avtomatlashtirilmagan | P55: Bajarilmagan
A56: DISC-007 | B56: Chegirma va aksiyalar | C56: Avto | D56: Aksiya qoralamasi (avto taklif) | E56: P3 | F56: Functional | G56: Tizim qotib qolgan tovar bo'yicha qoralama yaratgan | H56: 1. Qoralamani ochish 2. Sanalarni qo'yib, boshlash | J56: Taklif qilingan % bilan qoralama; boshlangach — oddiy aksiya | K56: PRD Auto chegirma | L56: Qisman | N56: Avtomatlashtirilmagan | P56: Bajarilmagan
A57: PROD-001 | B57: Mahsulotlar va variantlar | C57: Ro'yxat | D57: Mahsulotlar ro'yxati | E57: P2 | F57: Functional | G57: Admin panelga test akkaunti bilan kirilgan (to'liq huquqlar) | H57: 1. Mahsulotlar ni ochish 2. Nomi/ID bo'yicha qidirish 3. Sahifalash | J57: Ustunlar: Id, nomi, variantlar soni, model, kategoriya; qidiruv va sahifalash ishlaydi | L57: Ha | N57: Avtomatlashtirilmagan | P57: Bajarilmagan
A58: PROD-002 | B58: Mahsulotlar va variantlar | C58: Mahsulot | D58: Mahsulotni tahrirlash (General) | E58: P1 | F58: Functional | G58: Admin panelga test akkaunti bilan kirilgan (to'liq huquqlar) | H58: 1. Mahsulotni ochish 2. Nomi, brend, kategoriya, model, rasmni o'zgartirish 3. «Saqlash» 4. Asl holiga qaytarish | J58: O'zgarishlar saqlanadi va vitrinada ko'rinadi | L58: Ha | N58: Avtomatlashtirilmagan | P58: Bajarilmagan
A59: PROD-003 | B59: Mahsulotlar va variantlar | C59: Mahsulot | D59: Mahsulot yaratish | E59: P1 | F59: Smoke | G59: Admin panelga test akkaunti bilan kirilgan (to'liq huquqlar) | H59: 1. Mahsulot yaratish: nomi, brend, kategoriya (Turi bo'lsa — Turigacha), model, rasm | J59: Mahsulot yaratiladi va ro'yxatda ko'rinadi | L59: Ha | N59: Avtomatlashtirilmagan | P59: Bajarilmagan
A60: PROD-004 | B60: Mahsulotlar va variantlar | C60: Variantlar | D60: Variant yaratish | E60: P1 | F60: Smoke | G60: Admin panelga test akkaunti bilan kirilgan (to'liq huquqlar); mahsulot ochiq → Variations | H60: 1. Variant qo'shish: atributlar (sifat, rang), ishlab chiqaruvchi, yorliq nomi 2. Saqlash | J60: Variant yaratiladi; bo'sh yorliq nomi avtomatik yaratiladi | K60: PRD Product Variant Check Name | L60: Ha | N60: Avtomatlashtirilmagan | P60: Bajarilmagan
A61: PROD-005 | B61: Mahsulotlar va variantlar | C61: Variantlar | D61: Variant dublikati | E61: P2 | F61: Negative | G61: Atributlari va ishlab chiqaruvchisi bir xil variant bor | H61: 1. Xuddi shunday variant yaratish | J61: Unikallik xatosi; boshqa ishlab chiqaruvchi bilan — ruxsat | K61: PRD 8.7 Ishlab chiqaruvchilar | L61: Ha | N61: Avtomatlashtirilmagan | P61: Bajarilmagan
A62: PROD-006 | B62: Mahsulotlar va variantlar | C62: Variantlar | D62: Variantni boshqa mahsulotga ko'chirish | E62: P2 | F62: Functional | G62: Variant bor | H62: 1. «Asosiy mahsulot»ni o'zgartirish 2. Tasdiqlash | J62: Kategoriya o'zgarishi haqida ogohlantirish oynasi; variant qoldiq va tarixi bilan ko'chadi | K62: PRD Mahsulot varianti — almashtirish | L62: Ha | N62: Avtomatlashtirilmagan | P62: Bajarilmagan
A63: PROD-007 | B63: Mahsulotlar va variantlar | C63: Kategoriyalar | D63: Turlari bor sub kategoriyada Turi majburiy | E63: P2 | F63: Negative | G63: Turi bor sub kategoriya | H63: 1. Turisiz mahsulot yaratish | J63: Saqlash bloklanadi | K63: PRD Product & Product Variant | L63: Ha | N63: Avtomatlashtirilmagan | P63: Bajarilmagan
A64: DIR-001 | B64: Katalog ma'lumotnomalari | C64: Brendlar | D64: Brendlar CRUD | E64: P2 | F64: Functional | G64: Admin panelga test akkaunti bilan kirilgan (to'liq huquqlar) | H64: 1. Katalog → Brendlar → «Yaratish» 2. Tahrirlash 3. Qidiruv orqali topish | J64: Brend yaratiladi/o'zgaradi, mahsulotda brend tanlovida bor | L64: Ha | N64: Avtomatlashtirilmagan | P64: Bajarilmagan
A65: DIR-002 | B65: Katalog ma'lumotnomalari | C65: Kategoriyalar | D65: Kategoriya yaratish | E65: P1 | F65: Functional | G65: Admin panelga test akkaunti bilan kirilgan (to'liq huquqlar) | H65: 1. Kategoriyalar → «Yaratish»: nomi uz/ru/en, teglar, rasm, og'irlik va o'lchamlar 2. «Yaratish» | J65: Kategoriya yaratiladi va vitrinadagi katalog menyusida ko'rinadi | L65: Ha | N65: Avtomatlashtirilmagan | P65: Bajarilmagan
A66: DIR-003 | B66: Katalog ma'lumotnomalari | C66: Kategoriyalar | D66: Kategoriya sahifasi: Sub kategoriyalar / Mahsulotlar | E66: P2 | F66: Functional | G66: Admin panelga test akkaunti bilan kirilgan (to'liq huquqlar) | H66: 1. Kategoriyani ochish 2. Tablarni almashtirish | J66: Sub kategoriyalar va biriktirilgan mahsulotlar ko'rinadi | K66: PRD AIDT-759 | L66: Ha | N66: Avtomatlashtirilmagan | P66: Bajarilmagan
A67: DIR-004 | B67: Katalog ma'lumotnomalari | C67: Kategoriyalar | D67: Kategoriyaning majburiy maydonlari | E67: P2 | F67: Negative | G67: Admin panelga test akkaunti bilan kirilgan (to'liq huquqlar) | H67: 1. Nomisiz kategoriya yaratish | J67: Validatsiya xatosi | L67: Ha | N67: Avtomatlashtirilmagan | P67: Bajarilmagan
A68: DIR-005 | B68: Katalog ma'lumotnomalari | C68: Attributlar | D68: Attributlar CRUD va holat | E68: P3 | F68: Functional | G68: Admin panelga test akkaunti bilan kirilgan (to'liq huquqlar) | H68: 1. Attributlar → «Yaratish» 2. Holatni o'zgartirish | J68: Attribut yaratiladi; nofaoli variant yaratishda tanlanmaydi | L68: Ha | N68: Avtomatlashtirilmagan | P68: Bajarilmagan
A69: DIR-006 | B69: Katalog ma'lumotnomalari | C69: Modellar | D69: Model yaratish va unikallik | E69: P2 | F69: Functional | G69: Admin panelga test akkaunti bilan kirilgan (to'liq huquqlar) | H69: 1. Model → «Yaratish» (nomi, brend, kategoriya) 2. Dublikat yaratish | J69: Model yaratiladi; bir xil brend+kategoriya juftida dublikat taqiqlanadi; model vitrinadagi «Model»da ko'rinadi | L69: Ha | N69: Avtomatlashtirilmagan | P69: Bajarilmagan
A70: DIR-007 | B70: Katalog ma'lumotnomalari | C70: Modellar | D70: Qurilma modellari | E70: P3 | F70: Functional | G70: Admin panelga test akkaunti bilan kirilgan (to'liq huquqlar) | H70: 1. Qurilma modeli → «Yaratish» | J70: Qurilma modeli yaratiladi | L70: Ha | N70: Avtomatlashtirilmagan | P70: Bajarilmagan
A71: DIR-008 | B71: Katalog ma'lumotnomalari | C71: Ta'minotchilar | D71: Ta'minotchilar CRUD | E71: P3 | F71: Functional | G71: Admin panelga test akkaunti bilan kirilgan (to'liq huquqlar) | H71: 1. Ta'minotchi → «Yaratish» (nomi, manzil, telefon) | J71: Ta'minotchi yaratiladi, kirimda tanlanadi | L71: Ha | N71: Avtomatlashtirilmagan | P71: Bajarilmagan
A72: ORD-001 | B72: Buyurtmalar | C72: Ro'yxat | D72: Buyurtmalar ro'yxati va filtrlari | E72: P1 | F72: Smoke | G72: Admin panelga test akkaunti bilan kirilgan (to'liq huquqlar) | H72: 1. Buyurtmalar → Buyurtmalar 2. Filtr: sana, ombor, foydalanuvchi, status, to'lov, yetkazish, manba 3. Tozalash | J72: Ustunlar: Id, mijoz, buyurtma turi, ombor, status, to'lov turi, yetkazish, jami narx, yaratilgan sana, izoh; yangilari yuqorida; filtrlar birga ishlaydi | L72: Ha | N72: Avtomatlashtirilmagan | P72: Bajarilmagan
A73: ORD-002 | B73: Buyurtmalar | C73: Ro'yxat | D73: Vitrinadan buyurtma admin panelda paydo bo'ladi | E73: P1 | F73: Integration | G73: Usta vitrinada buyurtma bergan | H73: 1. Buyurtmani ID / foydalanuvchi bo'yicha topish | J73: Ma'lumotlar vitrina bilan mos: mahsulotlar, summa, to'lov, yetkazish, ombor, mijoz izohi | L73: Ha | N73: Avtomatlashtirilmagan | P73: Bajarilmagan
A74: ORD-003 | B74: Buyurtmalar | C74: Tafsilotlar | D74: Buyurtma kartasi | E74: P1 | F74: Functional | G74: Admin panelga test akkaunti bilan kirilgan (to'liq huquqlar) | H74: 1. Buyurtmani ochish | J74: Buyurtma statuslari, mijoz, jo'natuvchi ombor/ombor, o'tkazma raqami, sanalar; to'lov: turi, mahsulotlar narxi, qaytarilgan, buyurtma narxi, yetkazish, muddat; yetkazish: turi, manzil; mahsulotlar: qoldiq, narx, qaytarilgan, xususiyatlar | L74: Ha | N74: Avtomatlashtirilmagan | P74: Bajarilmagan
A75: ORD-004 | B75: Buyurtmalar | C75: Statuslar | D75: Buyurtma statusini o'zgartirish | E75: P1 | F75: Smoke | G75: Admin panelga test akkaunti bilan kirilgan (to'liq huquqlar); buyurtma «Yaratilgan» | H75: 1. Yaratilgan → Yuborildi → Qabul qilindi → Bajarildi 2. Har safar «Saqlash» | J75: Status va vaqt saqlanadi; mijoz statusni vitrinada ko'radi | K75: PRD Admin Order List and Detail | L75: Ha | N75: Avtomatlashtirilmagan | P75: Bajarilmagan
A76: ORD-005 | B76: Buyurtmalar | C76: Bekor qilish | D76: Admin tomonidan sabab bilan bekor qilish | E76: P1 | F76: Functional | G76: Admin panelga test akkaunti bilan kirilgan (to'liq huquqlar); tugallanmagan buyurtma | H76: 1. «Bekor qilindi»ni tanlash 2. Sabab (bog'lana olmadik, noto'g'ri filial, dublikat, noto'g'ri mahsulot, rasmiylashtirishda xato, olib ketmadi, boshqa) 3. «Saqlash» | J76: Sababsiz bekor qilib bo'lmaydi; «Boshqa» izoh talab qiladi; mahsulot omborga qaytadi; mijozga sabab matni bilan bildirishnoma | K76: PRD Buyurtmani bekor qilish | L76: Ha | N76: Avtomatlashtirilmagan | P76: Bajarilmagan
A77: ORD-006 | B77: Buyurtmalar | C77: Bekor qilish | D77: O'tkazmali buyurtmani bekor qilish | E77: P2 | F77: Functional | G77: O'tkazmasi «Yaratilgan» / «Yo'lda» buyurtma | H77: 1. Buyurtmani bekor qilish | J77: «Yaratilgan» — o'tkazma bekor, mahsulot jo'natuvchiga qaytadi; «Yo'lda» — qabul qilinguncha o'zgarishsiz | L77: Ha | N77: Avtomatlashtirilmagan | P77: Bajarilmagan
A78: ORD-007 | B78: Buyurtmalar | C78: O'tkazma | D78: Buyurtma kartasidan o'tkazmani qabul qilish | E78: P2 | F78: Functional | G78: O'tkazmasi «Yo'lda» buyurtma, qabul qiluvchi ombor foydalanuvchisi | H78: 1. Buyurtma kartasida «Qabul qilish» | J78: O'tkazma to'liq qabul qilinadi, buyurtma «Qabul qilindi»; boshqa ombor qabul qila olmaydi | K78: PRD Admin Order ORD-010 | L78: Ha | N78: Avtomatlashtirilmagan | P78: Bajarilmagan
A79: ORD-008 | B79: Buyurtmalar | C79: To'lov | D79: To'lov holati alohida o'zgaradi | E79: P2 | F79: Functional | G79: Naqd to'lovli buyurtma | H79: 1. To'lovni to'langan deb belgilash | J79: Faqat to'lov o'zgaradi; buyurtma statusi o'zgarmaydi; mijoz «To'landi»ni ko'radi | L79: Ha | N79: Avtomatlashtirilmagan | P79: Bajarilmagan
A80: ORD-009 | B80: Buyurtmalar | C80: To'lov turini o'zgartirish | D80: Mijozga to'lov turini o'zgartirish so'rovi | E80: P1 | F80: Functional | G80: Buyurtma: Yaratilgan/Yuborildi/Qabul qilindi, to'lanmagan | H80: 1. «To'lov turini o'zgartirish»: Naqd → Hamyon (usta uchun muddat faqat o'qish) 2. «So'rov yuborish» | J80: «Mijoz tasdig'i kutilmoqda» banneri, bekor qilish mumkin; mijozga push; javobgacha to'lov turi o'zgarmaydi | K80: PRD Change Payment Method | L80: Ha | N80: Avtomatlashtirilmagan | P80: Bajarilmagan
A81: ORD-010 | B81: Buyurtmalar | C81: To'lov turini o'zgartirish | D81: Ochiq so'rov bilan status o'zgartirishdan himoya | E81: P2 | F81: Functional | G81: To'lov turini o'zgartirish so'rovi bor | H81: 1. Buyurtmani «Bajarildi»ga o'tkazish | J81: «So'rov avtomatik bekor qilinadi — davom etasizmi?» oynasi; «Ha» bosilsa so'rov bekor va status o'zgaradi | L81: Ha | N81: Avtomatlashtirilmagan | P81: Bajarilmagan
A82: ORD-011 | B82: Buyurtmalar | C82: To'lov turini o'zgartirish | D82: Yopilgan buyurtmalarda to'lov turini o'zgartirib bo'lmaydi | E82: P2 | F82: Negative | G82: Buyurtma Bajarildi / Bekor qilindi / Qaytarilgan | H82: 1. To'lov blokini ochish | J82: «Payment method cannot be changed for this order» | L82: Ha | N82: Avtomatlashtirilmagan | P82: Bajarilmagan
A83: ORD-012 | B83: Buyurtmalar | C83: Ballar | D83: Buyurtma bajarilganda 1% ball beriladi | E83: P1 | F83: Integration | G83: Mijoz buyurtmasi ball bilan to'lanmagan | H83: 1. «Bajarildi»ga o'tkazish | J83: Buyurtma narxining 1% i beriladi; Ball tranzaksiyalarida — «Buyurtma uchun berildi» | L83: Ha | N83: Avtomatlashtirilmagan | P83: Bajarilmagan
A84: ORD-013 | B84: Buyurtmalar | C84: Qarz | D84: Hamyon buyurtmasini bajarish va filial limiti | E84: P1 | F84: Integration | G84: Hamyon buyurtmasi; filial qarzi limitga yaqin | H84: 1. «Bajarildi»ga o'tkazish | J84: Limit oshsa — raqamlar bilan blok; aks holda Bajarildi, to'lov muddati = bajarilgan sana + N kun, 17:00 | K84: PRD Filial qarz limiti; PRD Debt Limit | L84: Ha | N84: Avtomatlashtirilmagan | P84: Bajarilmagan
A85: ORD-014 | B85: Buyurtmalar | C85: Chop etish | D85: Buyurtmani chop etish | E85: P3 | F85: UI | G85: Buyurtma bor | H85: 1. «Chop etish» | J85: Buyurtmaning chop etish shakli | L85: Ha | N85: Avtomatlashtirilmagan | P85: Bajarilmagan
A86: SW-001 | B86: Sotuv oynasi | C86: Ro'yxat | D86: Sotuv oynasi hujjatlari ro'yxati | E86: P2 | F86: Functional | G86: Admin panelga test akkaunti bilan kirilgan (to'liq huquqlar) | H86: 1. Buyurtmalar → Sotuv oynasi 2. Filtrlar: sana, ombor, holat, savdo turi | J86: Ustunlar: Id, mijoz, telefon, ombor, ijrochi, umumiy narx, yuborilgan, qabul qilingan sana, turi, taymer, holat | L86: Ha | N86: Avtomatlashtirilmagan | P86: Bajarilmagan
A87: SW-002 | B87: Sotuv oynasi | C87: Yaratish | D87: Hujjat yaratish va mijozga yuborish | E87: P1 | F87: Smoke | G87: Admin panelga test akkaunti bilan kirilgan (to'liq huquqlar) | H87: 1. «Yaratish»: mijoz, ombor, savdo turi (Berib yuborildi / Taklif berildi), to'lov turi yoki «Mijoz tanlaydi» 2. Mahsulotlar, miqdor ≤ mavjud 3. «Send» | J87: Holat «Jo'natilgan»; mahsulot band qilinadi; mijozga push; hujjat vitrinada «Maxsus buyurtma → Yangi»da | K87: PRD Sales window | L87: Ha | N87: Avtomatlashtirilmagan | P87: Bajarilmagan
A88: SW-003 | B88: Sotuv oynasi | C88: Validatsiya | D88: Miqdor mavjuddan ko'p | E88: P2 | F88: Negative | G88: Admin panelga test akkaunti bilan kirilgan (to'liq huquqlar) | H88: 1. Mavjuddan ko'p miqdor kiritish | J88: Xato, saqlab bo'lmaydi | L88: Ha | N88: Avtomatlashtirilmagan | P88: Bajarilmagan
A89: SW-004 | B89: Sotuv oynasi | C89: Hayot sikli | D89: Mijoz tasdiqlashi buyurtma yaratadi | E89: P1 | F89: Integration | G89: Hujjat ustaga yuborilgan | H89: 1. Usta vitrinada tasdiqlaydi 2. Hujjat va Buyurtmalar ni ochish | J89: Hujjat «Qabul qilingan», oddiy buyurtma yaratilgan | L89: Ha | N89: Avtomatlashtirilmagan | P89: Bajarilmagan
A90: SW-005 | B90: Sotuv oynasi | C90: Hayot sikli | D90: Hujjatni bekor qilish bandni qaytaradi | E90: P1 | F90: Functional | G90: Hujjat «Saqlangan» yoki «Qaytarilgan» | H90: 1. «Cancel» | J90: Holat «Bekor qilingan», mahsulot omborga qaytadi, mijozga push | L90: Ha | N90: Avtomatlashtirilmagan | P90: Bajarilmagan
A91: SW-006 | B91: Sotuv oynasi | C91: Taymer | D91: Taklifning taymer bo'yicha avtomatik qaytishi | E91: P3 | F91: Functional | G91: «Taklif berildi» hujjati yuborilgan | H91: 1. Taymer tugashini kutish | J91: Hujjat avtomatik qaytadi; «Berib yuborildi» taymersiz kutadi | L91: Yo'q | M91: Uzoq kutish | N91: Avtomatlashtirilmagan | P91: Bajarilmagan
A92: SW-007 | B92: Sotuv oynasi | C92: Turi | D92: Savdo turini o'zgartirish | E92: P3 | F92: Functional | G92: Hujjat Saqlangan / Jo'natilgan / Qaytarilgan | H92: 1. Berib yuborildi ↔ Taklif berildi o'zgartirish | J92: Taymer qayta boshlanadi / o'chadi; Qabul qilingan / Bekor qilinganda tur o'zgarmaydi | L92: Ha | N92: Avtomatlashtirilmagan | P92: Bajarilmagan
A93: RET-001 | B93: Mahsulot qaytarish | C93: Ro'yxat | D93: Qaytarishlar ro'yxati | E93: P2 | F93: Functional | G93: Admin panelga test akkaunti bilan kirilgan (to'liq huquqlar) | H93: 1. Buyurtmalar → Mahsulot qaytarish 2. Filtrlar: sana, ombor, variant | J93: Ustunlar: Id, nomi, ombor, yaratilgan sana, umumiy qaytarish summasi | L93: Ha | N93: Avtomatlashtirilmagan | P93: Bajarilmagan
A94: RET-002 | B94: Mahsulot qaytarish | C94: Yaratish | D94: Soz mahsulotni naqd pulga qaytarish | E94: P1 | F94: Smoke | G94: Mijozda bajarilgan buyurtma bor | H94: 1. «Yaratish»: mijoz, buyurtma qatori 2. Working return = 1, to'lov «Naqd» 3. «Return» | J94: Qaytarish yaratiladi; mahsulot ishchi qoldiqqa; mijozga naqd; vitrinada qaytarish «Qaytarildi» | K94: PRD Product Return | L94: Ha | N94: Avtomatlashtirilmagan | P94: Bajarilmagan
A95: RET-003 | B95: Mahsulot qaytarish | C95: Yaratish | D95: Bitta qatorda brak va soz | E95: P2 | F95: Functional | G95: 2 donali buyurtma qatori | H95: 1. Working 1, Broken 1 | J95: Soz — ishchi qoldiqqa, brak — brak omboriga | L95: Ha | N95: Avtomatlashtirilmagan | P95: Bajarilmagan
A96: RET-004 | B96: Mahsulot qaytarish | C96: Yaratish | D96: Sotilgandan ko'p qaytarish | E96: P1 | F96: Negative | G96: Qator: sotilgan 2, qaytarilgan 1 | H96: 1. 2 dona qaytarish | J96: Mumkin emas: faqat 1 ta mavjud; to'liq qaytarilgan qatorlar tanlanmaydi | L96: Ha | N96: Avtomatlashtirilmagan | P96: Bajarilmagan
A97: RET-005 | B97: Mahsulot qaytarish | C97: To'lov | D97: Hamyon va ballarga qaytarish | E97: P2 | F97: Integration | G97: Mijoz buyurtmasi Hamyon / ball bilan to'langan | H97: 1. Qaytarishni rasmiylashtirish | J97: Hamyon — qarz kamayadi/hamyon to'ldiriladi; ballar — qaytariladi; berilgan 1% chiqariladi | L97: Ha | N97: Avtomatlashtirilmagan | P97: Bajarilmagan
A98: RET-006 | B98: Mahsulot qaytarish | C98: To'lov | D98: Muddati o'tgan qarzda faqat hamyonga qaytarish | E98: P2 | F98: Integration | G98: Mijozda muddati o'tgan qarz bor | H98: 1. Qaytarishni rasmiylashtirish | J98: Faqat hamyonga qaytarish mumkin | K98: PRD Qaytarish — muddati o'tgan qarz | L98: Qisman | N98: Avtomatlashtirilmagan | P98: Bajarilmagan
A99: RET-007 | B99: Mahsulot qaytarish | C99: Chop etish | D99: Qaytarish cheki va yorliqlar | E99: P3 | F99: UI | G99: Qaytarish bor | H99: 1. «Chop etish» va «Chek chiqarish» | J99: Qaytarish cheki (naqd / hamyonga / jami) va yorliqlar | L99: Ha | N99: Avtomatlashtirilmagan | P99: Bajarilmagan
A100: BIL-001 | B100: Hisob-kitob (kassa) | C100: Kassalar | D100: Kassa yaratish | E100: P2 | F100: Functional | G100: Admin panelga test akkaunti bilan kirilgan (to'liq huquqlar) | H100: 1. Hisob-kitob → Kassa → «Yaratish»: ombor, mas'ul xodim, nomlar UZ/RU/EN 2. «Yaratish» | J100: Kassa yaratiladi, unda hujjat ochiq | L100: Ha | N100: Avtomatlashtirilmagan | P100: Bajarilmagan
...

Sheet Kamchiliklar
A1: № | B1: Kategoriya | C1: Tavsif | D1: Qayerda | E1: Jiddiylik | F1: Izoh | G1: Holat
A2: 1 | B2: Ma'lumot | C2: «Qarz cheklovi»da oddiy B2C mijozlarga ham limit qo'yilgan (B2C, 300 000 000) | D2: /debt/debt-limit | E2: Medium | F2: PRD Mijoz rollari §6.7 da ham nosozlik deb ko'rsatilgan — tasdiqlash kerak | G2: Yangi
A3: 2 | B3: Mantiq | C3: Bloklangan hamyon Hamyon bilan to'lovga to'sqinlik qilmaydi | D3: Checkout / Qarz cheklovi | E3: High | F3: PRD Debt Limit dagi kod tekshiruvi izohidan — staging da tekshirish kerak | G3: Yangi
A4: 3 | B4: Lokalizatsiya | C4: Hamyon holati «free» / «blocked» ko'rinishida tarjimasiz | D4: Hamyon tranzaksiyalari, Hamyon | E4: Low | F4: PRD Wallet (kod tekshiruvi) | G4: Yangi
A5: 4 | B5: Lokalizatsiya | C5: Omborlar nomlari turli tillarda (masalan «Урикзор Магазин №43»); UZ rejimida ham Kassa hisoboti tablari inglizcha | D5: Bosh sahifa, Mavsum, Kassa hisoboti | E5: Low | F5: 28.10.2026 da UZ tilida tekshirilgan | G5: Yangi
A6: 5 | B6: Ma'lumot | C6: Bekor qilingan #518191 buyurtmada bekor qilish sababi «abc» | D6: /orders/518191 | E6: Info | F6: Matn qayerdan kelishini tekshirish | G6: Yangi
B8: Kamchiliklar staging'ni usta akkaunti bilan o'rganishda topilgan (28.10.2026). Bag ochishdan oldin qayta tekshiring.

Sheet Manbalar
A1: PRD / sahifa | B1: Nima haqida | C1: Havola
A2: Папка логики админки (Confluence) | B2: 1–15 bo'limlar | C2: https://arositdepartment.atlassian.net/wiki/spaces/~ArosMarket/folder/354385922
A3: Admin Order List and Order Detail | B3: Buyurtmalar | C3: https://arositdepartment.atlassian.net/wiki/spaces/~ArosMarket/pages/333774849
A4: Product Transfer / Transfer permission | B4: O'tkazmalar | C4: https://arositdepartment.atlassian.net/wiki/spaces/~ArosMarket/pages/304021505
A5: Inventory PRD | B5: Inventarizatsiya | C5: https://arositdepartment.atlassian.net/wiki/spaces/~ArosMarket/pages/305135617
A6: Product Income — Excel Import | B6: Kirim, Excel import | C6: https://arositdepartment.atlassian.net/wiki/spaces/~ArosMarket/pages/324861953
A7: Kirim — qisman kelish | B7: Qisman qabul | C7: https://arositdepartment.atlassian.net/wiki/spaces/~ArosMarket/pages/376209409
A8: Discount US1 / PRD | B8: Aksiyalar | C8: https://arositdepartment.atlassian.net/wiki/spaces/~ArosMarket/pages/154632194
A9: Mijozga xos chegirma ko'rinishi | B9: Narx turi bo'yicha chegirmalar | C9: https://arositdepartment.atlassian.net/wiki/spaces/~ArosMarket/pages/377651202
A10: Product & Product Variant | B10: Mahsulotlar va variantlar | C10: https://arositdepartment.atlassian.net/wiki/spaces/~ArosMarket/pages/292356097
A11: Sales window - PRD | B11: Sotuv oynasi | C11: https://arositdepartment.atlassian.net/wiki/spaces/~ArosMarket/pages/307167233
A12: Product Return | B12: Qaytarishlar | C12: https://arositdepartment.atlassian.net/wiki/spaces/~ArosMarket/pages/298024961
... A18: Roles and Permissions Module | B18: Ruxsatlar | C18: https://arositdepartment.atlassian.net/wiki/spaces/~ArosMarket/pages/243597313
