Workbook

Sheet Сводка
A1: Aros — регрессионные тест-кейсы админ-панели
A2: Админ-панель, UI. Сверено с PRD в Confluence и staging-admin 28.10.2026. Витрина — отдельный файл.
A4: Окружение | B4: https://staging-admin.aros.uz
A5: Роль | B5: Администратор (полные права)
A6: Тестовый аккаунт | B6: Логин: +998998987882 Пароль: <пароль в .env> в .env>
A7: Документация | B7: Confluence → папка логики админки; ссылки на листе «Источники»
A8: Автотесты | B8: Репозиторий aros-ui: Java 21 + Playwright + JUnit5 + Allure
A9: Релиз / версия | J9: ← жёлтые поля заполняются перед каждым прогоном
A10: Дата прогона
A11: Тестировщик
A12: Покрытие по модулям
A13: Модуль | B13: Всего | C13: P1 | D13: P2 | E13: P3 | F13: Можно авто: Да | G13: Частично | H13: Нет | I13: Автоматизировано | J13: % покрытия автотестами | K13: Passed | L13: Failed | M13: Blocked | N13: Skipped | O13: Не выполнен
A14: AUTH — Авторизация и доступ | B14: =COUNTIF('Тест-кейсы'!$B$2:$B$167,"Авторизация и доступ") | C14: =COUNTIFS('Тест-кейсы'!$B$2:$B$167,"Авторизация и доступ",'Тест-кейсы'!$E$2:$E$167,"P1") | D14: =COUNTIFS('Тест-кейсы'!$B$2:$B$167,"Авторизация и доступ",'Тест-кейсы'!$E$2:$E$167,"P2") | E14: =COUNTIFS('Тест-кейсы'!$B$2:$B$167,"Авторизация и доступ",'Тест-кейсы'!$E$2:$E$167,"P3") | F14: =COUNTIFS('Тест-кейсы'!$B$2:$B$167,"Авторизация и доступ",'Тест-кейсы'!$L$2:$L$167,"Да") | G14: =COUNTIFS('Тест-кейсы'!$B$2:$B$167,"Авторизация и доступ",'Тест-кейсы'!$L$2:$L$167,"Частично") | H14: =COUNTIFS('Тест-кейсы'!$B$2:$B$167,"Авторизация и доступ",'Тест-кейсы'!$L$2:$L$167,"Нет") | I14: =COUNTIFS('Тест-кейсы'!$B$2:$B$167,"Авторизация и доступ",'Тест-кейсы'!$N$2:$N$167,"Автоматизирован") | J14: =IF(B14=0,0,I14/B14) | K14: =COUNTIFS('Тест-кейсы'!$B$2:$B$167,"Авторизация и доступ",'Тест-кейсы'!$P$2:$P$167,"Passed") | L14: =COUNTIFS('Тест-кейсы'!$B$2:$B$167,"Авторизация и доступ",'Тест-кейсы'!$P$2:$P$167,"Failed") | M14: =COUNTIFS('Тест-кейсы'!$B$2:$B$167,"Авторизация и доступ",'Тест-кейсы'!$P$2:$P$167,"Blocked") | N14: =COUNTIFS('Тест-кейсы'!$B$2:$B$167,"Авторизация и доступ",'Тест-кейсы'!$P$2:$P$167,"Skipped") | O14: =COUNTIFS('Тест-кейсы'!$B$2:$B$167,"Авторизация и доступ",'Тест-кейсы'!$P$2:$P$167,"Не выполнен")
A15: DASH — Главная (Dashboard) | B15: =COUNTIF('Тест-кейсы'!$B$2:$B$167,"Главная (Dashboard)") | C15: =COUNTIFS('Тест-кейсы'!$B$2:$B$167,"Главная (Dashboard)",'Тест-кейсы'!$E$2:$E$167,"P1") | D15: =COUNTIFS('Тест-кейсы'!$B$2:$B$167,"Главная (Dashboard)",'Тест-кейсы'!$E$2:$E$167,"P2") | E15: =COUNTIFS('Тест-кейсы'!$B$2:$B$167,"Главная (Dashboard)",'Тест-кейсы'!$E$2:$E$167,"P3") | F15: =COUNTIFS('Тест-кейсы'!$B$2:$B$167,"Главная (Dashboard)",'Тест-кейсы'!$L$2:$L$167,"Да") | G15: =COUNTIFS('Тест-кейсы'!$B$2:$B$167,"Главная (Dashboard)",'Тест-кейсы'!$L$2:$L$167,"Частично") | H15: =COUNTIFS('Тест-кейсы'!$B$2:$B$167,"Главная (Dashboard)",'Тест-кейсы'!$L$2:$L$167,"Нет") | I15: =COUNTIFS('Тест-кейсы'!$B$2:$B$167,"Главная (Dashboard)",'Тест-кейсы'!$N$2:$N$167,"Автоматизирован") | J15: =IF(B15=0,0,I15/B15) | K15: =COUNTIFS('Тест-кейсы'!$B$2:$B$167,"Главная (Dashboard)",'Тест-кейсы'!$P$2:$P$167,"Passed") | L15: =COUNTIFS('Тест-кейсы'!$B$2:$B$167,"Главная (Dashboard)",'Тест-кейсы'!$P$2:$P$167,"Failed") | M15: =COUNTIFS('Тест-кейсы'!$B$2:$B$167,"Главная (Dashboard)",'Тест-кейсы'!$P$2:$P$167,"Blocked") | N15: =COUNTIFS('Тест-кейсы'!$B$2:$B$167,"Главная (Dashboard)",'Тест-кейсы'!$P$2:$P$167,"Skipped") | O15: =COUNTIFS('Тест-кейсы'!$B$2:$B$167,"Главная (Dashboard)",'Тест-кейсы'!$P$2:$P$167,"Не выполнен")
A16: PINC — Приход товара (Product income) | B16: =COUNTIF('Тест-кейсы'!$B$2:$B$167,"Приход товара (Product income)") | C16: =COUNTIFS('Тест-кейсы'!$B$2:$B$167,"Приход товара (Product income)",'Тест-кейсы'!$E$2:$E$167,"P1") | D16: =COUNTIFS('Тест-кейсы'!$B$2:$B$167,"Приход товара (Product income)",'Тест-кейсы'!$E$2:$E$167,"P2") | E16: =COUNTIFS('Тест-кейсы'!$B$2:$B$167,"Приход товара (Product income)",'Тест-кейсы'!$E$2:$E$167,"P3") | F16: =COUNTIFS('Тест-кейсы'!$B$2:$B$167,"Приход товара (Product income)",'Тест-кейсы'!$L$2:$L$167,"Да") | G16: =COUNTIFS('Тест-кейсы'!$B$2:$B$167,"Приход товара (Product income)",'Тест-кейсы'!$L$2:$L$167,"Частично") | H16: =COUNTIFS('Тест-кейсы'!$B$2:$B$167,"Приход товара (Product income)",'Тест-кейсы'!$L$2:$L$167,"Нет") | I16: =COUNTIFS('Тест-кейсы'!$B$2:$B$167,"Приход товара (Product income)",'Тест-кейсы'!$N$2:$N$167,"Автоматизирован") | J16: =IF(B16=0,0,I16/B16) | K16: =COUNTIFS('Тест-кейсы'!$B$2:$B$167,"Приход товара (Product income)",'Тест-кейсы'!$P$2:$P$167,"Passed") | L16: =COUNTIFS('Тест-кейсы'!$B$2:$B$167,"Приход товара (Product income)",'Тест-кейсы'!$P$2:$P$167,"Failed") | M16: =COUNTIFS('Тест-кейсы'!$B$2:$B$167,"Приход товара (Product income)",'Тест-кейсы'!$P$2:$P$167,"Blocked") | N16: =COUNTIFS('Тест-кейсы'!$B$2:$B$167,"Приход товара (Product income)",'Тест-кейсы'!$P$2:$P$167,"Skipped") | O16: =COUNTIFS('Тест-кейсы'!$B$2:$B$167,"Приход товара (Product income)",'Тест-кейсы'!$P$2:$P$167,"Не выполнен")
A17: PRICE — Установка цен (Install prices) | B17: =COUNTIF('Тест-кейсы'!$B$2:$B$167,"Установка цен (Install prices)") | C17: =COUNTIFS('Тест-кейсы'!$B$2:$B$167,"Установка цен (Install prices)",'Тест-кейсы'!$E$2:$E$167,"P1") | D17: =COUNTIFS('Тест-кейсы'!$B$2:$B$167,"Установка цен (Install prices)",'Тест-кейсы'!$E$2:$E$167,"P2") | E17: =COUNTIFS('Тест-кейсы'!$B$2:$B$167,"Установка цен (Install prices)",'Тест-кейсы'!$E$2:$E$167,"P3") | F17: =COUNTIFS('Тест-кейсы'!$B$2:$B$167,"Установка цен (Install prices)",'Тест-кейсы'!$L$2:$L$167,"Да") | G17: =COUNTIFS('Тест-кейсы'!$B$2:$B$167,"Установка цен (Install prices)",'Тест-кейсы'!$L$2:$L$167,"Частично") | H17: =COUNTIFS('Тест-кейсы'!$B$2:$B$167,"Установка цен (Install prices)",'Тест-кейсы'!$L$2:$L$167,"Нет") | I17: =COUNTIFS('Тест-кейсы'!$B$2:$B$167,"Установка цен (Install prices)",'Тест-кейсы'!$N$2:$N$167,"Автоматизирован") | J17: =IF(B17=0,0,I17/B17) | K17: =COUNTIFS('Тест-кейсы'!$B$2:$B$167,"Установка цен (Install prices)",'Тест-кейсы'!$P$2:$P$167,"Passed") | L17: =COUNTIFS('Тест-кейсы'!$B$2:$B$167,"Установка цен (Install prices)",'Тест-кейсы'!$P$2:$P$167,"Failed") | M17: =COUNTIFS('Тест-кейсы'!$B$2:$B$167,"Установка цен (Install prices)",'Тест-кейсы'!$P$2:$P$167,"Blocked") | N17: =COUNTIFS('Тест-кейсы'!$B$2:$B$167,"Установка цен (Install prices)",'Тест-кейсы'!$P$2:$P$167,"Skipped") | O17: =COUNTIFS('Тест-кейсы'!$B$2:$B$167,"Установка цен (Install prices)",'Тест-кейсы'!$P$2:$P$167,"Не выполнен")
A18: INV — Инвентаризация | B18: =COUNTIF('Тест-кейсы'!$B$2:$B$167,"Инвентаризация") | C18: =COUNTIFS('Тест-кейсы'!$B$2:$B$167,"Инвентаризация",'Тест-кейсы'!$E$2:$E$167,"P1") | D18: =COUNTIFS('Тест-кейсы'!$B$2:$B$167,"Инвентаризация",'Тест-кейсы'!$E$2:$E$167,"P2") | E18: =COUNTIFS('Тест-кейсы'!$B$2:$B$167,"Инвентаризация",'Тест-кейсы'!$E$2:$E$167,"P3") | F18: =COUNTIFS('Тест-кейсы'!$B$2:$B$167,"Инвентаризация",'Тест-кейсы'!$L$2:$L$167,"Да") | G18: =COUNTIFS('Тест-кейсы'!$B$2:$B$167,"Инвентаризация",'Тест-кейсы'!$L$2:$L$167,"Частично") | H18: =COUNTIFS('Тест-кейсы'!$B$2:$B$167,"Инвентаризация",'Тест-кейсы'!$L$2:$L$167,"Нет") | I18: =COUNTIFS('Тест-кейсы'!$B$2:$B$167,"Инвентаризация",'Тест-кейсы'!$N$2:$N$167,"Автоматизирован") | J18: =IF(B18=0,0,I18/B18) | K18: =COUNTIFS('Тест-кейсы'!$B$2:$B$167,"Инвентаризация",'Тест-кейсы'!$P$2:$P$167,"Passed") | L18: =COUNTIFS('Тест-кейсы'!$B$2:$B$167,"Инвентаризация",'Тест-кейсы'!$P$2:$P$167,"Failed") | M18: =COUNTIFS('Тест-кейсы'!$B$2:$B$167,"Инвентаризация",'Тест-кейсы'!$P$2:$P$167,"Blocked") | N18: =COUNTIFS('Тест-кейсы'!$B$2:$B$167,"Инвентаризация",'Тест-кейсы'!$P$2:$P$167,"Skipped") | O18: =COUNTIFS('Тест-кейсы'!$B$2:$B$167,"Инвентаризация",'Тест-кейсы'!$P$2:$P$167,"Не выполнен")
A19: TRF — Перемещение товара (Transfer) | B19: =COUNTIF('Тест-кейсы'!$B$2:$B$167,"Перемещение товара (Transfer)") | C19: =COUNTIFS('Тест-кейсы'!$B$2:$B$167,"Перемещение товара (Transfer)",'Тест-кейсы'!$E$2:$E$167,"P1") | D19: =COUNTIFS('Тест-кейсы'!$B$2:$B$167,"Перемещение товара (Transfer)",'Тест-кейсы'!$E$2:$E$167,"P2") | E19: =COUNTIFS('Тест-кейсы'!$B$2:$B$167,"Перемещение товара (Transfer)",'Тест-кейсы'!$E$2:$E$167,"P3") | F19: =COUNTIFS('Тест-кейсы'!$B$2:$B$167,"Перемещение товара (Transfer)",'Тест-кейсы'!$L$2:$L$167,"Да") | G19: =COUNTIFS('Тест-кейсы'!$B$2:$B$167,"Перемещение товара (Transfer)",'Тест-кейсы'!$L$2:$L$167,"Частично") | H19: =COUNTIFS('Тест-кейсы'!$B$2:$B$167,"Перемещение товара (Transfer)",'Тест-кейсы'!$L$2:$L$167,"Нет") | I19: =COUNTIFS('Тест-кейсы'!$B$2:$B$167,"Перемещение товара (Transfer)",'Тест-кейсы'!$N$2:$N$167,"Автоматизирован") | J19: =IF(B19=0,0,I19/B19) | K19: =COUNTIFS('Тест-кейсы'!$B$2:$B$167,"Перемещение товара (Transfer)",'Тест-кейсы'!$P$2:$P$167,"Passed") | L19: =COUNTIFS('Тест-кейсы'!$B$2:$B$167,"Перемещение товара (Transfer)",'Тест-кейсы'!$P$2:$P$167,"Failed") | M19: =COUNTIFS('Тест-кейсы'!$B$2:$B$167,"Перемещение товара (Transfer)",'Тест-кейсы'!$P$2:$P$167,"Blocked") | N19: =COUNTIFS('Тест-кейсы'!$B$2:$B$167,"Перемещение товара (Transfer)",'Тест-кейсы'!$P$2:$P$167,"Skipped") | O19: =COUNTIFS('Тест-кейсы'!$B$2:$B$167,"Перемещение товара (Transfer)",'Тест-кейсы'!$P$2:$P$167,"Не выполнен")
A20: PVAR — Варианты товара (потребность) | B20: =COUNTIF('Тест-кейсы'!$B$2:$B$167,"Варианты товара (потребность)") | C20: =COUNTIFS('Тест-кейсы'!$B$2:$B$167,"Варианты товара (потребность)",'Тест-кейсы'!$E$2:$E$167,"P1") | D20: =COUNTIFS('Тест-кейсы'!$B$2:$B$167,"Варианты товара (потребность)",'Тест-кейсы'!$E$2:$E$167,"P2") | E20: =COUNTIFS('Тест-кейсы'!$B$2:$B$167,"Варианты товара (потребность)",'Тест-кейсы'!$E$2:$E$167,"P3") | F20: =COUNTIFS('Тест-кейсы'!$B$2:$B$167,"Варианты товара (потребность)",'Тест-кейсы'!$L$2:$L$167,"Да") | G20: =COUNTIFS('Тест-кейсы'!$B$2:$B$167,"Варианты товара (потребность)",'Тест-кейсы'!$L$2:$L$167,"Частично") | H20: =COUNTIFS('Тест-кейсы'!$B$2:$B$167,"Варианты товара (потребность)",'Тест-кейсы'!$L$2:$L$167,"Нет") | I20: =COUNTIFS('Тест-кейсы'!$B$2:$B$167,"Варианты товара (потребность)",'Тест-кейсы'!$N$2:$N$167,"Автоматизирован") | J20: =IF(B20=0,0,I20/B20) | K20: =COUNTIFS('Тест-кейсы'!$B$2:$B$167,"Варианты товара (потребность)",'Тест-кейсы'!$P$2:$P$167,"Passed") | L20: =COUNTIFS('Тест-кейсы'!$B$2:$B$167,"Варианты товара (потребность)",'Тест-кейсы'!$P$2:$P$167,"Failed") | M20: =COUNTIFS('Тест-кейсы'!$B$2:$B$167,"Варианты товара (потребность)",'Тест-кейсы'!$P$2:$P$167,"Blocked") | N20: =COUNTIFS('Тест-кейсы'!$B$2:$B$167,"Варианты товара (потребность)",'Тест-кейсы'!$P$2:$P$167,"Skipped") | O20: =COUNTIFS('Тест-кейсы'!$B$2:$B$167,"Варианты товара (потребность)",'Тест-кейсы'!$P$2:$P$167,"Не выполнен")
A21: DISC — Скидки и акции | B21: =COUNTIF('Тест-кейсы'!$B$2:$B$167,"Скидки и акции") | C21: =COUNTIFS('Тест-кейсы'!$B$2:$B$167,"Скидки и акции",'Тест-кейсы'!$E$2:$E$167,"P1") | D21: =COUNTIFS('Тест-кейсы'!$B$2:$B$167,"Скидки и акции",'Тест-кейсы'!$E$2:$E$167,"P2") | E21: =COUNTIFS('Тест-кейсы'!$B$2:$B$167,"Скидки и акции",'Тест-кейсы'!$E$2:$E$167,"P3") | F21: =COUNTIFS('Тест-кейсы'!$B$2:$B$167,"Скидки и акции",'Тест-кейсы'!$L$2:$L$167,"Да") | G21: =COUNTIFS('Тест-кейсы'!$B$2:$B$167,"Скидки и акции",'Тест-кейсы'!$L$2:$L$167,"Частично") | H21: =COUNTIFS('Тест-кейсы'!$B$2:$B$167,"Скидки и акции",'Тест-кейсы'!$L$2:$L$167,"Нет") | I21: =COUNTIFS('Тест-кейсы'!$B$2:$B$167,"Скидки и акции",'Тест-кейсы'!$N$2:$N$167,"Автоматизирован") | J21: =IF(B21=0,0,I21/B21) | K21: =COUNTIFS('Тест-кейсы'!$B$2:$B$167,"Скидки и акции",'Тест-кейсы'!$P$2:$P$167,"Passed") | L21: =COUNTIFS('Тест-кейсы'!$B$2:$B$167,"Скидки и акции",'Тест-кейсы'!$P$2:$P$167,"Failed") | M21: =COUNTIFS('Тест-кейсы'!$B$2:$B$167,"Скидки и акции",'Тест-кейсы'!$P$2:$P$167,"Blocked") | N21: =COUNTIFS('Тест-кейсы'!$B$2:$B$167,"Скидки и акции",'Тест-кейсы'!$P$2:$P$167,"Skipped") | O21: =COUNTIFS('Тест-кейсы'!$B$2:$B$167,"Скидки и акции",'Тест-кейсы'!$P$2:$P$167,"Не выполнен")
A22: PROD — Товары и варианты | B22: =COUNTIF('Тест-кейсы'!$B$2:$B$167,"Товары и варианты") | C22: =COUNTIFS('Тест-кейсы'!$B$2:$B$167,"Товары и варианты",'Тест-кейсы'!$E$2:$E$167,"P1") | D22: =COUNTIFS('Тест-кейсы'!$B$2:$B$167,"Товары и варианты",'Тест-кейсы'!$E$2:$E$167,"P2") | E22: =COUNTIFS('Тест-кейсы'!$B$2:$B$167,"Товары и варианты",'Тест-кейсы'!$E$2:$E$167,"P3") | F22: =COUNTIFS('Тест-кейсы'!$B$2:$B$167,"Товары и варианты",'Тест-кейсы'!$L$2:$L$167,"Да") | G22: =COUNTIFS('Тест-кейсы'!$B$2:$B$167,"Товары и варианты",'Тест-кейсы'!$L$2:$L$167,"Частично") | H22: =COUNTIFS('Тест-кейсы'!$B$2:$B$167,"Товары и варианты",'Тест-кейсы'!$L$2:$L$167,"Нет") | I22: =COUNTIFS('Тест-кейсы'!$B$2:$B$167,"Товары и варианты",'Тест-кейсы'!$N$2:$N$167,"Автоматизирован") | J22: =IF(B22=0,0,I22/B22) | K22: =COUNTIFS('Тест-кейсы'!$B$2:$B$167,"Товары и варианты",'Тест-кейсы'!$P$2:$P$167,"Passed") | L22: =COUNTIFS('Тест-кейсы'!$B$2:$B$167,"Товары и варианты",'Тест-кейсы'!$P$2:$P$167,"Failed") | M22: =COUNTIFS('Тест-кейсы'!$B$2:$B$167,"Товары и варианты",'Тест-кейсы'!$P$2:$P$167,"Blocked") | N22: =COUNTIFS('Тест-кейсы'!$B$2:$B$167,"Товары и варианты",'Тест-кейсы'!$P$2:$P$167,"Skipped") | O22: =COUNTIFS('Тест-кейсы'!$B$2:$B$167,"Товары и варианты",'Тест-кейсы'!$P$2:$P$167,"Не выполнен")
A23: DIR — Справочники | B23: =COUNTIF('Тест-кейсы'!$B$2:$B$167,"Справочники") | C23: =COUNTIFS('Тест-кейсы'!$B$2:$B$167,"Справочники",'Тест-кейсы'!$E$2:$E$167,"P1") | D23: =COUNTIFS('Тест-кейсы'!$B$2:$B$167,"Справочники",'Тест-кейсы'!$E$2:$E$167,"P2") | E23: =COUNTIFS('Тест-кейсы'!$B$2:$B$167,"Справочники",'Тест-кейсы'!$E$2:$E$167,"P3") | F23: =COUNTIFS('Тест-кейсы'!$B$2:$B$167,"Справочники",'Тест-кейсы'!$L$2:$L$167,"Да") | G23: =COUNTIFS('Тест-кейсы'!$B$2:$B$167,"Справочники",'Тест-кейсы'!$L$2:$L$167,"Частично") | H23: =COUNTIFS('Тест-кейсы'!$B$2:$B$167,"Справочники",'Тест-кейсы'!$L$2:$L$167,"Нет") | I23: =COUNTIFS('Тест-кейсы'!$B$2:$B$167,"Справочники",'Тест-кейсы'!$N$2:$N$167,"Автоматизирован") | J23: =IF(B23=0,0,I23/B23) | K23: =COUNTIFS('Тест-кейсы'!$B$2:$B$167,"Справочники",'Тест-кейсы'!$P$2:$P$167,"Passed") | L23: =COUNTIFS('Тест-кейсы'!$B$2:$B$167,"Справочники",'Тест-кейсы'!$P$2:$P$167,"Failed") | M23: =COUNTIFS('Тест-кейсы'!$B$2:$B$167,"Справочники",'Тест-кейсы'!$P$2:$P$167,"Blocked") | N23: =COUNTIFS('Тест-кейсы'!$B$2:$B$167,"Справочники",'Тест-кейсы'!$P$2:$P$167,"Skipped") | O23: =COUNTIFS('Тест-кейсы'!$B$2:$B$167,"Справочники",'Тест-кейсы'!$P$2:$P$167,"Не выполнен")
A24: ORD — Заказы | B24: =COUNTIF('Тест-кейсы'!$B$2:$B$167,"Заказы") | C24: =COUNTIFS('Тест-кейсы'!$B$2:$B$167,"Заказы",'Тест-кейсы'!$E$2:$E$167,"P1") | D24: =COUNTIFS('Тест-кейсы'!$B$2:$B$167,"Заказы",'Тест-кейсы'!$E$2:$E$167,"P2") | E24: =COUNTIFS('Тест-кейсы'!$B$2:$B$167,"Заказы",'Тест-кейсы'!$E$2:$E$167,"P3") | F24: =COUNTIFS('Тест-кейсы'!$B$2:$B$167,"Заказы",'Тест-кейсы'!$L$2:$L$167,"Да") | G24: =COUNTIFS('Тест-кейсы'!$B$2:$B$167,"Заказы",'Тест-кейсы'!$L$2:$L$167,"Частично") | H24: =COUNTIFS('Тест-кейсы'!$B$2:$B$167,"Заказы",'Тест-кейсы'!$L$2:$L$167,"Нет") | I24: =COUNTIFS('Тест-кейсы'!$B$2:$B$167,"Заказы",'Тест-кейсы'!$N$2:$N$167,"Автоматизирован") | J24: =IF(B24=0,0,I24/B24) | K24: =COUNTIFS('Тест-кейсы'!$B$2:$B$167,"Заказы",'Тест-кейсы'!$P$2:$P$167,"Passed") | L24: =COUNTIFS('Тест-кейсы'!$B$2:$B$167,"Заказы",'Тест-кейсы'!$P$2:$P$167,"Failed") | M24: =COUNTIFS('Тест-кейсы'!$B$2:$B$167,"Заказы",'Тест-кейсы'!$P$2:$P$167,"Blocked") | N24: =COUNTIFS('Тест-кейсы'!$B$2:$B$167,"Заказы",'Тест-кейсы'!$P$2:$P$167,"Skipped") | O24: =COUNTIFS('Тест-кейсы'!$B$2:$B$167,"Заказы",'Тест-кейсы'!$P$2:$P$167,"Не выполнен")
A25: SW — Окно продаж (Sales window) | B25: =COUNTIF('Тест-кейсы'!$B$2:$B$167,"Окно продаж (Sales window)") | C25: =COUNTIFS('Тест-кейсы'!$B$2:$B$167,"Окно продаж (Sales window)",'Тест-кейсы'!$E$2:$E$167,"P1") | D25: =COUNTIFS('Тест-кейсы'!$B$2:$B$167,"Окно продаж (Sales window)",'Тест-кейсы'!$E$2:$E$167,"P2") | E25: =COUNTIFS('Тест-кейсы'!$B$2:$B$167,"Окно продаж (Sales window)",'Тест-кейсы'!$E$2:$E$167,"P3") | F25: =COUNTIFS('Тест-кейсы'!$B$2:$B$167,"Окно продаж (Sales window)",'Тест-кейсы'!$L$2:$L$167,"Да") | G25: =COUNTIFS('Тест-кейсы'!$B$2:$B$167,"Окно продаж (Sales window)",'Тест-кейсы'!$L$2:$L$167,"Частично") | H25: =COUNTIFS('Тест-кейсы'!$B$2:$B$167,"Окно продаж (Sales window)",'Тест-кейсы'!$L$2:$L$167,"Нет") | I25: =COUNTIFS('Тест-кейсы'!$B$2:$B$167,"Окно продаж (Sales window)",'Тест-кейсы'!$N$2:$N$167,"Автоматизирован") | J25: =IF(B25=0,0,I25/B25) | K25: =COUNTIFS('Тест-кейсы'!$B$2:$B$167,"Окно продаж (Sales window)",'Тест-кейсы'!$P$2:$P$167,"Passed") | L25: =COUNTIFS('Тест-кейсы'!$B$2:$B$167,"Окно продаж (Sales window)",'Тест-кейсы'!$P$2:$P$167,"Failed") | M25: =COUNTIFS('Тест-кейсы'!$B$2:$B$167,"Окно продаж (Sales window)",'Тест-кейсы'!$P$2:$P$167,"Blocked") | N25: =COUNTIFS('Тест-кейсы'!$B$2:$B$167,"Окно продаж (Sales window)",'Тест-кейсы'!$P$2:$P$167,"Skipped") | O25: =COUNTIFS('Тест-кейсы'!$B$2:$B$167,"Окно продаж (Sales window)",'Тест-кейсы'!$P$2:$P$167,"Не выполнен")
A26: RET — Возврат товара | B26: =COUNTIF('Тест-кейсы'!$B$2:$B$167,"Возврат товара") | C26: =COUNTIFS('Тест-кейсы'!$B$2:$B$167,"Возврат товара",'Тест-кейсы'!$E$2:$E$167,"P1") | D26: =COUNTIFS('Тест-кейсы'!$B$2:$B$167,"Возврат товара",'Тест-кейсы'!$E$2:$E$167,"P2") | E26: =COUNTIFS('Тест-кейсы'!$B$2:$B$167,"Возврат товара",'Тест-кейсы'!$E$2:$E$167,"P3") | F26: =COUNTIFS('Тест-кейсы'!$B$2:$B$167,"Возврат товара",'Тест-кейсы'!$L$2:$L$167,"Да") | G26: =COUNTIFS('Тест-кейсы'!$B$2:$B$167,"Возврат товара",'Тест-кейсы'!$L$2:$L$167,"Частично") | H26: =COUNTIFS('Тест-кейсы'!$B$2:$B$167,"Возврат товара",'Тест-кейсы'!$L$2:$L$167,"Нет") | I26: =COUNTIFS('Тест-кейсы'!$B$2:$B$167,"Возврат товара",'Тест-кейсы'!$N$2:$N$167,"Автоматизирован") | J26: =IF(B26=0,0,I26/B26) | K26: =COUNTIFS('Тест-кейсы'!$B$2:$B$167,"Возврат товара",'Тест-кейсы'!$P$2:$P$167,"Passed") | L26: =COUNTIFS('Тест-кейсы'!$B$2:$B$167,"Возврат товара",'Тест-кейсы'!$P$2:$P$167,"Failed") | M26: =COUNTIFS('Тест-кейсы'!$B$2:$B$167,"Возврат товара",'Тест-кейсы'!$P$2:$P$167,"Blocked") | N26: =COUNTIFS('Тест-кейсы'!$B$2:$B$167,"Возврат товара",'Тест-кейсы'!$P$2:$P$167,"Skipped") | O26: =COUNTIFS('Тест-кейсы'!$B$2:$B$167,"Возврат товара",'Тест-кейсы'!$P$2:$P$167,"Не выполнен")
A27: BIL — Касса и финансы (Billing) | B27: =COUNTIF('Тест-кейсы'!$B$2:$B$167,"Касса и финансы (Billing)") | C27: =COUNTIFS('Тест-кейсы'!$B$2:$B$167,"Касса и финансы (Billing)",'Тест-кейсы'!$E$2:$E$167,"P1") | D27: =COUNTIFS('Тест-кейсы'!$B$2:$B$167,"Касса и финансы (Billing)",'Тест-кейсы'!$E$2:$E$167,"P2") | E27: =COUNTIFS('Тест-кейсы'!$B$2:$B$167,"Касса и финансы (Billing)",'Тест-кейсы'!$E$2:$E$167,"P3") | F27: =COUNTIFS('Тест-кейсы'!$B$2:$B$167,"Касса и финансы (Billing)",'Тест-кейсы'!$L$2:$L$167,"Да") | G27: =COUNTIFS('Тест-кейсы'!$B$2:$B$167,"Касса и финансы (Billing)",'Тест-кейсы'!$L$2:$L$167,"Частично") | H27: =COUNTIFS('Тест-кейсы'!$B$2:$B$167,"Касса и финансы (Billing)",'Тест-кейсы'!$L$2:$L$167,"Нет") | I27: =COUNTIFS('Тест-кейсы'!$B$2:$B$167,"Касса и финансы (Billing)",'Тест-кейсы'!$N$2:$N$167,"Автоматизирован") | J27: =IF(B27=0,0,I27/B27) | K27: =COUNTIFS('Тест-кейсы'!$B$2:$B$167,"Касса и финансы (Billing)",'Тест-кейсы'!$P$2:$P$167,"Passed") | L27: =COUNTIFS('Тест-кейсы'!$B$2:$B$167,"Касса и финансы (Billing)",'Тест-кейсы'!$P$2:$P$167,"Failed") | M27: =COUNTIFS('Тест-кейсы'!$B$2:$B$167,"Касса и финансы (Billing)",'Тест-кейсы'!$P$2:$P$167,"Blocked") | N27: =COUNTIFS('Тест-кейсы'!$B$2:$B$167,"Касса и финансы (Billing)",'Тест-кейсы'!$P$2:$P$167,"Skipped") | O27: =COUNTIFS('Тест-кейсы'!$B$2:$B$167,"Касса и финансы (Billing)",'Тест-кейсы'!$P$2:$P$167,"Не выполнен")
A28: USR — Пользователи и роли клиентов | B28: =COUNTIF('Тест-кейсы'!$B$2:$B$167,"Пользователи и роли клиентов") | C28: =COUNTIFS('Тест-кейсы'!$B$2:$B$167,"Пользователи и роли клиентов",'Тест-кейсы'!$E$2:$E$167,"P1") | D28: =COUNTIFS('Тест-кейсы'!$B$2:$B$167,"Пользователи и роли клиентов",'Тест-кейсы'!$E$2:$E$167,"P2") | E28: =COUNTIFS('Тест-кейсы'!$B$2:$B$167,"Пользователи и роли клиентов",'Тест-кейсы'!$E$2:$E$167,"P3") | F28: =COUNTIFS('Тест-кейсы'!$B$2:$B$167,"Пользователи и роли клиентов",'Тест-кейсы'!$L$2:$L$167,"Да") | G28: =COUNTIFS('Тест-кейсы'!$B$2:$B$167,"Пользователи и роли клиентов",'Тест-кейсы'!$L$2:$L$167,"Частично") | H28: =COUNTIFS('Тест-кейсы'!$B$2:$B$167,"Пользователи и роли клиентов",'Тест-кейсы'!$L$2:$L$167,"Нет") | I28: =COUNTIFS('Тест-кейсы'!$B$2:$B$167,"Пользователи и роли клиентов",'Тест-кейсы'!$N$2:$N$167,"Автоматизирован") | J28: =IF(B28=0,0,I28/B28) | K28: =COUNTIFS('Тест-кейсы'!$B$2:$B$167,"Пользователи и роли клиентов",'Тест-кейсы'!$P$2:$P$167,"Passed") | L28: =COUNTIFS('Тест-кейсы'!$B$2:$B$167,"Пользователи и роли клиентов",'Тест-кейсы'!$P$2:$P$167,"Failed") | M28: =COUNTIFS('Тест-кейсы'!$B$2:$B$167,"Пользователи и роли клиентов",'Тест-кейсы'!$P$2:$P$167,"Blocked") | N28: =COUNTIFS('Тест-кейсы'!$B$2:$B$167,"Пользователи и роли клиентов",'Тест-кейсы'!$P$2:$P$167,"Skipped") | O28: =COUNTIFS('Тест-кейсы'!$B$2:$B$167,"Пользователи и роли клиентов",'Тест-кейсы'!$P$2:$P$167,"Не выполнен")
A29: REQ — Запросы клиентов | B29: =COUNTIF('Тест-кейсы'!$B$2:$B$167,"Запросы клиентов") | C29: =COUNTIFS('Тест-кейсы'!$B$2:$B$167,"Запросы клиентов",'Тест-кейсы'!$E$2:$E$167,"P1") | D29: =COUNTIFS('Тест-кейсы'!$B$2:$B$167,"Запросы клиентов",'Тест-кейсы'!$E$2:$E$167,"P2") | E29: =COUNTIFS('Тест-кейсы'!$B$2:$B$167,"Запросы клиентов",'Тест-кейсы'!$E$2:$E$167,"P3") | F29: =COUNTIFS('Тест-кейсы'!$B$2:$B$167,"Запросы клиентов",'Тест-кейсы'!$L$2:$L$167,"Да") | G29: =COUNTIFS('Тест-кейсы'!$B$2:$B$167,"Запросы клиентов",'Тест-кейсы'!$L$2:$L$167,"Частично") | H29: =COUNTIFS('Тест-кейсы'!$B$2:$B$167,"Запросы клиентов",'Тест-кейсы'!$L$2:$L$167,"Нет") | I29: =COUNTIFS('Тест-кейсы'!$B$2:$B$167,"Запросы клиентов",'Тест-кейсы'!$N$2:$N$167,"Автоматизирован") | J29: =IF(B29=0,0,I29/B29) | K29: =COUNTIFS('Тест-кейсы'!$B$2:$B$167,"Запросы клиентов",'Тест-кейсы'!$P$2:$P$167,"Passed") | L29: =COUNTIFS('Тест-кейсы'!$B$2:$B$167,"Запросы клиентов",'Тест-кейсы'!$P$2:$P$167,"Failed") | M29: =COUNTIFS('Тест-кейсы'!$B$2:$B$167,"Запросы клиентов",'Тест-кейсы'!$P$2:$P$167,"Blocked") | N29: =COUNTIFS('Тест-кейсы'!$B$2:$B$167,"Запросы клиентов",'Тест-кейсы'!$P$2:$P$167,"Skipped") | O29: =COUNTIFS('Тест-кейсы'!$B$2:$B$167,"Запросы клиентов",'Тест-кейсы'!$P$2:$P$167,"Не выполнен")
A30: WH — Склады | B30: =COUNTIF('Тест-кейсы'!$B$2:$B$167,"Склады") | C30: =COUNTIFS('Тест-кейсы'!$B$2:$B$167,"Склады",'Тест-кейсы'!$E$2:$E$167,"P1") | D30: =COUNTIFS('Тест-кейсы'!$B$2:$B$167,"Склады",'Тест-кейсы'!$E$2:$E$167,"P2") | E30: =COUNTIFS('Тест-кейсы'!$B$2:$B$167,"Склады",'Тест-кейсы'!$E$2:$E$167,"P3") | F30: =COUNTIFS('Тест-кейсы'!$B$2:$B$167,"Склады",'Тест-кейсы'!$L$2:$L$167,"Да") | G30: =COUNTIFS('Тест-кейсы'!$B$2:$B$167,"Склады",'Тест-кейсы'!$L$2:$L$167,"Частично") | H30: =COUNTIFS('Тест-кейсы'!$B$2:$B$167,"Склады",'Тест-кейсы'!$L$2:$L$167,"Нет") | I30: =COUNTIFS('Тест-кейсы'!$B$2:$B$167,"Склады",'Тест-кейсы'!$N$2:$N$167,"Автоматизирован") | J30: =IF(B30=0,0,I30/B30) | K30: =COUNTIFS('Тест-кейсы'!$B$2:$B$167,"Склады",'Тест-кейсы'!$P$2:$P$167,"Passed") | L30: =COUNTIFS('Тест-кейсы'!$B$2:$B$167,"Склады",'Тест-кейсы'!$P$2:$P$167,"Failed") | M30: =COUNTIFS('Тест-кейсы'!$B$2:$B$167,"Склады",'Тест-кейсы'!$P$2:$P$167,"Blocked") | N30: =COUNTIFS('Тест-кейсы'!$B$2:$B$167,"Склады",'Тест-кейсы'!$P$2:$P$167,"Skipped") | O30: =COUNTIFS('Тест-кейсы'!$B$2:$B$167,"Склады",'Тест-кейсы'!$P$2:$P$167,"Не выполнен")
A31: CUR — Валюта | B31: =COUNTIF('Тест-кейсы'!$B$2:$B$167,"Валюта") | C31: =COUNTIFS('Тест-кейсы'!$B$2:$B$167,"Валюта",'Тест-кейсы'!$E$2:$E$167,"P1") | D31: =COUNTIFS('Тест-кейсы'!$B$2:$B$167,"Валюта",'Тест-кейсы'!$E$2:$E$167,"P2") | E31: =COUNTIFS('Тест-кейсы'!$B$2:$B$167,"Валюта",'Тест-кейсы'!$E$2:$E$167,"P3") | F31: =COUNTIFS('Тест-кейсы'!$B$2:$B$167,"Валюта",'Тест-кейсы'!$L$2:$L$167,"Да") | G31: =COUNTIFS('Тест-кейсы'!$B$2:$B$167,"Валюта",'Тест-кейсы'!$L$2:$L$167,"Частично") | H31: =COUNTIFS('Тест-кейсы'!$B$2:$B$167,"Валюта",'Тест-кейсы'!$L$2:$L$167,"Нет") | I31: =COUNTIFS('Тест-кейсы'!$B$2:$B$167,"Валюта",'Тест-кейсы'!$N$2:$N$167,"Автоматизирован") | J31: =IF(B31=0,0,I31/B31) | K31: =COUNTIFS('Тест-кейсы'!$B$2:$B$167,"Валюта",'Тест-кейсы'!$P$2:$P$167,"Passed") | L31: =COUNTIFS('Тест-кейсы'!$B$2:$B$167,"Валюта",'Тест-кейсы'!$P$2:$P$167,"Failed") | M31: =COUNTIFS('Тест-кейсы'!$B$2:$B$167,"Валюта",'Тест-кейсы'!$P$2:$P$167,"Blocked") | N31: =COUNTIFS('Тест-кейсы'!$B$2:$B$167,"Валюта",'Тест-кейсы'!$P$2:$P$167,"Skipped") | O31: =COUNTIFS('Тест-кейсы'!$B$2:$B$167,"Валюта",'Тест-кейсы'!$P$2:$P$167,"Не выполнен")
A32: BAN — Баннеры | B32: =COUNTIF('Тест-кейсы'!$B$2:$B$167,"Баннеры") | C32: =COUNTIFS('Тест-кейсы'!$B$2:$B$167,"Баннеры",'Тест-кейсы'!$E$2:$E$167,"P1") | D32: =COUNTIFS('Тест-кейсы'!$B$2:$B$167,"Баннеры",'Тест-кейсы'!$E$2:$E$167,"P2") | E32: =COUNTIFS('Тест-кейсы'!$B$2:$B$167,"Баннеры",'Тест-кейсы'!$E$2:$E$167,"P3") | F32: =COUNTIFS('Тест-кейсы'!$B$2:$B$167,"Баннеры",'Тест-кейсы'!$L$2:$L$167,"Да") | G32: =COUNTIFS('Тест-кейсы'!$B$2:$B$167,"Баннеры",'Тест-кейсы'!$L$2:$L$167,"Частично") | H32: =COUNTIFS('Тест-кейсы'!$B$2:$B$167,"Баннеры",'Тест-кейсы'!$L$2:$L$167,"Нет") | I32: =COUNTIFS('Тест-кейсы'!$B$2:$B$167,"Баннеры",'Тест-кейсы'!$N$2:$N$167,"Автоматизирован") | J32: =IF(B32=0,0,I32/B32) | K32: =COUNTIFS('Тест-кейсы'!$B$2:$B$167,"Баннеры",'Тест-кейсы'!$P$2:$P$167,"Passed") | L32: =COUNTIFS('Тест-кейсы'!$B$2:$B$167,"Баннеры",'Тест-кейсы'!$P$2:$P$167,"Failed") | M32: =COUNTIFS('Тест-кейсы'!$B$2:$B$167,"Баннеры",'Тест-кейсы'!$P$2:$P$167,"Blocked") | N32: =COUNTIFS('Тест-кейсы'!$B$2:$B$167,"Баннеры",'Тест-кейсы'!$P$2:$P$167,"Skipped") | O32: =COUNTIFS('Тест-кейсы'!$B$2:$B$167,"Баннеры",'Тест-кейсы'!$P$2:$P$167,"Не выполнен")
A33: DEBT — Долг и кошелёк | B33: =COUNTIF('Тест-кейсы'!$B$2:$B$167,"Долг и кошелёк") | C33: =COUNTIFS('Тест-кейсы'!$B$2:$B$167,"Долг и кошелёк",'Тест-кейсы'!$E$2:$E$167,"P1") | D33: =COUNTIFS('Тест-кейсы'!$B$2:$B$167,"Долг и кошелёк",'Тест-кейсы'!$E$2:$E$167,"P2") | E33: =COUNTIFS('Тест-кейсы'!$B$2:$B$167,"Долг и кошелёк",'Тест-кейсы'!$E$2:$E$167,"P3") | F33: =COUNTIFS('Тест-кейсы'!$B$2:$B$167,"Долг и кошелёк",'Тест-кейсы'!$L$2:$L$167,"Да") | G33: =COUNTIFS('Тест-кейсы'!$B$2:$B$167,"Долг и кошелёк",'Тест-кейсы'!$L$2:$L$167,"Частично") | H33: =COUNTIFS('Тест-кейсы'!$B$2:$B$167,"Долг и кошелёк",'Тест-кейсы'!$L$2:$L$167,"Нет") | I33: =COUNTIFS('Тест-кейсы'!$B$2:$B$167,"Долг и кошелёк",'Тест-кейсы'!$N$2:$N$167,"Автоматизирован") | J33: =IF(B33=0,0,I33/B33) | K33: =COUNTIFS('Тест-кейсы'!$B$2:$B$167,"Долг и кошелёк",'Тест-кейсы'!$P$2:$P$167,"Passed") | L33: =COUNTIFS('Тест-кейсы'!$B$2:$B$167,"Долг и кошелёк",'Тест-кейсы'!$P$2:$P$167,"Failed") | M33: =COUNTIFS('Тест-кейсы'!$B$2:$B$167,"Долг и кошелёк",'Тест-кейсы'!$P$2:$P$167,"Blocked") | N33: =COUNTIFS('Тест-кейсы'!$B$2:$B$167,"Долг и кошелёк",'Тест-кейсы'!$P$2:$P$167,"Skipped") | O33: =COUNTIFS('Тест-кейсы'!$B$2:$B$167,"Долг и кошелёк",'Тест-кейсы'!$P$2:$P$167,"Не выполнен")
A34: MSG — Сообщения (Push, чат) | B34: =COUNTIF('Тест-кейсы'!$B$2:$B$167,"Сообщения (Push, чат)") | C34: =COUNTIFS('Тест-кейсы'!$B$2:$B$167,"Сообщения (Push, чат)",'Тест-кейсы'!$E$2:$E$167,"P1") | D34: =COUNTIFS('Тест-кейсы'!$B$2:$B$167,"Сообщения (Push, чат)",'Тест-кейсы'!$E$2:$E$167,"P2") | E34: =COUNTIFS('Тест-кейсы'!$B$2:$B$167,"Сообщения (Push, чат)",'Тест-кейсы'!$E$2:$E$167,"P3") | F34: =COUNTIFS('Тест-кейсы'!$B$2:$B$167,"Сообщения (Push, чат)",'Тест-кейсы'!$L$2:$L$167,"Да") | G34: =COUNTIFS('Тест-кейсы'!$B$2:$B$167,"Сообщения (Push, чат)",'Тест-кейсы'!$L$2:$L$167,"Частично") | H34: =COUNTIFS('Тест-кейсы'!$B$2:$B$167,"Сообщения (Push, чат)",'Тест-кейсы'!$L$2:$L$167,"Нет") | I34: =COUNTIFS('Тест-кейсы'!$B$2:$B$167,"Сообщения (Push, чат)",'Тест-кейсы'!$N$2:$N$167,"Автоматизирован") | J34: =IF(B34=0,0,I34/B34) | K34: =COUNTIFS('Тест-кейсы'!$B$2:$B$167,"Сообщения (Push, чат)",'Тест-кейсы'!$P$2:$P$167,"Passed") | L34: =COUNTIFS('Тест-кейсы'!$B$2:$B$167,"Сообщения (Push, чат)",'Тест-кейсы'!$P$2:$P$167,"Failed") | M34: =COUNTIFS('Тест-кейсы'!$B$2:$B$167,"Сообщения (Push, чат)",'Тест-кейсы'!$P$2:$P$167,"Blocked") | N34: =COUNTIFS('Тест-кейсы'!$B$2:$B$167,"Сообщения (Push, чат)",'Тест-кейсы'!$P$2:$P$167,"Skipped") | O34: =COUNTIFS('Тест-кейсы'!$B$2:$B$167,"Сообщения (Push, чат)",'Тест-кейсы'!$P$2:$P$167,"Не выполнен")
A35: PERM — Права доступа | B35: =COUNTIF('Тест-кейсы'!$B$2:$B$167,"Права доступа") | C35: =COUNTIFS('Тест-кейсы'!$B$2:$B$167,"Права доступа",'Тест-кейсы'!$E$2:$E$167,"P1") | D35: =COUNTIFS('Тест-кейсы'!$B$2:$B$167,"Права доступа",'Тест-кейсы'!$E$2:$E$167,"P2") | E35: =COUNTIFS('Тест-кейсы'!$B$2:$B$167,"Права доступа",'Тест-кейсы'!$E$2:$E$167,"P3") | F35: =COUNTIFS('Тест-кейсы'!$B$2:$B$167,"Права доступа",'Тест-кейсы'!$L$2:$L$167,"Да") | G35: =COUNTIFS('Тест-кейсы'!$B$2:$B$167,"Права доступа",'Тест-кейсы'!$L$2:$L$167,"Частично") | H35: =COUNTIFS('Тест-кейсы'!$B$2:$B$167,"Права доступа",'Тест-кейсы'!$L$2:$L$167,"Нет") | I35: =COUNTIFS('Тест-кейсы'!$B$2:$B$167,"Права доступа",'Тест-кейсы'!$N$2:$N$167,"Автоматизирован") | J35: =IF(B35=0,0,I35/B35) | K35: =COUNTIFS('Тест-кейсы'!$B$2:$B$167,"Права доступа",'Тест-кейсы'!$P$2:$P$167,"Passed") | L35: =COUNTIFS('Тест-кейсы'!$B$2:$B$167,"Права доступа",'Тест-кейсы'!$P$2:$P$167,"Failed") | M35: =COUNTIFS('Тест-кейсы'!$B$2:$B$167,"Права доступа",'Тест-кейсы'!$P$2:$P$167,"Blocked") | N35: =COUNTIFS('Тест-кейсы'!$B$2:$B$167,"Права доступа",'Тест-кейсы'!$P$2:$P$167,"Skipped") | O35: =COUNTIFS('Тест-кейсы'!$B$2:$B$167,"Права доступа",'Тест-кейсы'!$P$2:$P$167,"Не выполнен")
A36: REP — Отчёты | B36: =COUNTIF('Тест-кейсы'!$B$2:$B$167,"Отчёты") | C36: =COUNTIFS('Тест-кейсы'!$B$2:$B$167,"Отчёты",'Тест-кейсы'!$E$2:$E$167,"P1") | D36: =COUNTIFS('Тест-кейсы'!$B$2:$B$167,"Отчёты",'Тест-кейсы'!$E$2:$E$167,"P2") | E36: =COUNTIFS('Тест-кейсы'!$B$2:$B$167,"Отчёты",'Тест-кейсы'!$E$2:$E$167,"P3") | F36: =COUNTIFS('Тест-кейсы'!$B$2:$B$167,"Отчёты",'Тест-кейсы'!$L$2:$L$167,"Да") | G36: =COUNTIFS('Тест-кейсы'!$B$2:$B$167,"Отчёты",'Тест-кейсы'!$L$2:$L$167,"Частично") | H36: =COUNTIFS('Тест-кейсы'!$B$2:$B$167,"Отчёты",'Тест-кейсы'!$L$2:$L$167,"Нет") | I36: =COUNTIFS('Тест-кейсы'!$B$2:$B$167,"Отчёты",'Тест-кейсы'!$N$2:$N$167,"Автоматизирован") | J36: =IF(B36=0,0,I36/B36) | K36: =COUNTIFS('Тест-кейсы'!$B$2:$B$167,"Отчёты",'Тест-кейсы'!$P$2:$P$167,"Passed") | L36: =COUNTIFS('Тест-кейсы'!$B$2:$B$167,"Отчёты",'Тест-кейсы'!$P$2:$P$167,"Failed") | M36: =COUNTIFS('Тест-кейсы'!$B$2:$B$167,"Отчёты",'Тест-кейсы'!$P$2:$P$167,"Blocked") | N36: =COUNTIFS('Тест-кейсы'!$B$2:$B$167,"Отчёты",'Тест-кейсы'!$P$2:$P$167,"Skipped") | O36: =COUNTIFS('Тест-кейсы'!$B$2:$B$167,"Отчёты",'Тест-кейсы'!$P$2:$P$167,"Не выполнен")
A37: E2E — Сквозные сценарии админка ↔ витрина | B37: =COUNTIF('Тест-кейсы'!$B$2:$B$167,"Сквозные сценарии админка ↔ витрина") | C37: =COUNTIFS('Тест-кейсы'!$B$2:$B$167,"Сквозные сценарии админка ↔ витрина",'Тест-кейсы'!$E$2:$E$167,"P1") | D37: =COUNTIFS('Тест-кейсы'!$B$2:$B$167,"Сквозные сценарии админка ↔ витрина",'Тест-кейсы'!$E$2:$E$167,"P2") | E37: =COUNTIFS('Тест-кейсы'!$B$2:$B$167,"Сквозные сценарии админка ↔ витрина",'Тест-кейсы'!$E$2:$E$167,"P3") | F37: =COUNTIFS('Тест-кейсы'!$B$2:$B$167,"Сквозные сценарии админка ↔ витрина",'Тест-кейсы'!$L$2:$L$167,"Да") | G37: =COUNTIFS('Тест-кейсы'!$B$2:$B$167,"Сквозные сценарии админка ↔ витрина",'Тест-кейсы'!$L$2:$L$167,"Частично") | H37: =COUNTIFS('Тест-кейсы'!$B$2:$B$167,"Сквозные сценарии админка ↔ витрина",'Тест-кейсы'!$L$2:$L$167,"Нет") | I37: =COUNTIFS('Тест-кейсы'!$B$2:$B$167,"Сквозные сценарии админка ↔ витрина",'Тест-кейсы'!$N$2:$N$167,"Автоматизирован") | J37: =IF(B37=0,0,I37/B37) | K37: =COUNTIFS('Тест-кейсы'!$B$2:$B$167,"Сквозные сценарии админка ↔ витрина",'Тест-кейсы'!$P$2:$P$167,"Passed") | L37: =COUNTIFS('Тест-кейсы'!$B$2:$B$167,"Сквозные сценарии админка ↔ витрина",'Тест-кейсы'!$P$2:$P$167,"Failed") | M37: =COUNTIFS('Тест-кейсы'!$B$2:$B$167,"Сквозные сценарии админка ↔ витрина",'Тест-кейсы'!$P$2:$P$167,"Blocked") | N37: =COUNTIFS('Тест-кейсы'!$B$2:$B$167,"Сквозные сценарии админка ↔ витрина",'Тест-кейсы'!$P$2:$P$167,"Skipped") | O37: =COUNTIFS('Тест-кейсы'!$B$2:$B$167,"Сквозные сценарии админка ↔ витрина",'Тест-кейсы'!$P$2:$P$167,"Не выполнен")
A38: GEN — Общие проверки интерфейса | B38: =COUNTIF('Тест-кейсы'!$B$2:$B$167,"Общие проверки интерфейса") | C38: =COUNTIFS('Тест-кейсы'!$B$2:$B$167,"Общие проверки интерфейса",'Тест-кейсы'!$E$2:$E$167,"P1") | D38: =COUNTIFS('Тест-кейсы'!$B$2:$B$167,"Общие проверки интерфейса",'Тест-кейсы'!$E$2:$E$167,"P2") | E38: =COUNTIFS('Тест-кейсы'!$B$2:$B$167,"Общие проверки интерфейса",'Тест-кейсы'!$E$2:$E$167,"P3") | F38: =COUNTIFS('Тест-кейсы'!$B$2:$B$167,"Общие проверки интерфейса",'Тест-кейсы'!$L$2:$L$167,"Да") | G38: =COUNTIFS('Тест-кейсы'!$B$2:$B$167,"Общие проверки интерфейса",'Тест-кейсы'!$L$2:$L$167,"Частично") | H38: =COUNTIFS('Тест-кейсы'!$B$2:$B$167,"Общие проверки интерфейса",'Тест-кейсы'!$L$2:$L$167,"Нет") | I38: =COUNTIFS('Тест-кейсы'!$B$2:$B$167,"Общие проверки интерфейса",'Тест-кейсы'!$N$2:$N$167,"Автоматизирован") | J38: =IF(B38=0,0,I38/B38) | K38: =COUNTIFS('Тест-кейсы'!$B$2:$B$167,"Общие проверки интерфейса",'Тест-кейсы'!$P$2:$P$167,"Passed") | L38: =COUNTIFS('Тест-кейсы'!$B$2:$B$167,"Общие проверки интерфейса",'Тест-кейсы'!$P$2:$P$167,"Failed") | M38: =COUNTIFS('Тест-кейсы'!$B$2:$B$167,"Общие проверки интерфейса",'Тест-кейсы'!$P$2:$P$167,"Blocked") | N38: =COUNTIFS('Тест-кейсы'!$B$2:$B$167,"Общие проверки интерфейса",'Тест-кейсы'!$P$2:$P$167,"Skipped") | O38: =COUNTIFS('Тест-кейсы'!$B$2:$B$167,"Общие проверки интерфейса",'Тест-кейсы'!$P$2:$P$167,"Не выполнен")
A39: ИТОГО | B39: =SUM(B14:B38) | C39: =SUM(C14:C38) | D39: =SUM(D14:D38) | E39: =SUM(E14:E38) | F39: =SUM(F14:F38) | G39: =SUM(G14:G38) | H39: =SUM(H14:H38) | I39: =SUM(I14:I38) | J39: =IF(B39=0,0,I39/B39) | K39: =SUM(K14:K38) | L39: =SUM(L14:L38) | M39: =SUM(M14:M38) | N39: =SUM(N14:N38) | O39: =SUM(O14:O38)
A41: Легенда
A42: P1 — критичный | B42: Блокирует релиз. Smoke-набор: прогоняется всегда.
A43: P2 — высокий | B43: Важный функционал, прогоняется в полном регрессе.
A44: P3 — средний | B44: UI/второстепенное, при нехватке времени можно отложить.
A45: Можно автоматизировать: Да | B45: Сценарий стабилен и полностью проверяется через UI (Playwright).
A46: Можно автоматизировать: Частично | B46: Нужны SMS/OTP, админка/API для подготовки данных или визуальная оценка.
A47: Можно автоматизировать: Нет | B47: Требует реального устройства или деструктивно — только вручную.
A48: Статус: Автоматизирован | B48: Есть автотест в репозитории aros-ui (колонка «Автотест»).
A49: Результат прогона | B49: Выбирается из списка: Passed / Failed / Blocked / Skipped / Не выполнен.
A50: Тип | B50: Smoke, Functional, Negative, UI, Security, Integration, Technical, Non-functional.
A51: Требование / источник | B51: PRD из Confluence (лист «Источники») или «Проверено на staging». Integration — нужен шаг в админке.

Sheet Тест-кейсы
A1: ID | B1: Модуль | C1: Подмодуль | D1: Название тест-кейса | E1: Приоритет | F1: Тип | G1: Предусловия | H1: Шаги | I1: Тестовые данные | J1: Ожидаемый результат | K1: Требование / источник | L1: Можно автоматизировать (UI) | M1: Комментарий по автоматизации | N1: Статус UI-автоматизации | O1: Автотест (класс#метод) | P1: Результат прогона | Q1: Комментарий / ссылка на баг
A2: AUTH-001 | B2: Авторизация и доступ | C2: Вход | D2: Успешный вход в админку | E2: P1 | F2: Smoke | G2: Пользователь не авторизован | H2: 1. Открыть https://staging-admin.aros.uz 2. Ввести username и пароль 3. Нажать «Login» | I2: +998998987882 / <пароль в .env> | J2: Открыт Dashboard, в шапке аватар пользователя, тост «Successfully completed» | K2: Админка staging 28.10.2026 | L2: Да | M2: Тест пропускается, если в .env нет ADMIN_USERNAME/ADMIN_PASSWORD | N2: Автоматизирован | O2: admin/AdminLoginTest#successfulLogin | P2: Не выполнен
A3: AUTH-002 | B3: Авторизация и доступ | C3: Вход | D3: Вход с неверным паролем | E3: P1 | F3: Negative | G3: Пользователь не авторизован | H3: 1. Ввести верный username и неверный пароль 2. «Login» | J3: Ошибка авторизации, форма входа остаётся, доступа к страницам нет | L3: Да | M3: Нужны ADMIN_* в .env | N3: Автоматизирован | O3: admin/AdminLoginTest#loginFailsWithWrongPassword | P3: Не выполнен
A4: AUTH-003 | B4: Авторизация и доступ | C4: Вход | D4: Вход с пустыми полями | E4: P2 | F4: Negative | G4: Пользователь не авторизован | H4: 1. Нажать «Login» с пустыми полями 2. Заполнить только username | J4: Валидация обязательных полей, запрос не отправляется | L4: Да | N4: Не автоматизирован | P4: Не выполнен
A5: AUTH-004 | B5: Авторизация и доступ | C5: Вход | D5: Маскировка пароля | E5: P3 | F5: UI | G5: Открыта страница входа | H5: 1. Ввести пароль 2. Нажать иконку глаза | J5: По умолчанию пароль скрыт; иконка показывает/скрывает | L5: Да | N5: Не автоматизирован | P5: Не выполнен
A6: AUTH-005 | B6: Авторизация и доступ | C6: Вход | D6: «Forgot password?» | E6: P3 | F6: Functional | G6: Открыта страница входа | H6: 1. Нажать «Forgot password?» | J6: Открыта /forgot-password, форма восстановления работает | L6: Частично | M6: Зависит от SMS/OTP | N6: Не автоматизирован | P6: Не выполнен
A7: AUTH-006 | B7: Авторизация и доступ | C7: Сессия | D7: Прямой URL без авторизации | E7: P1 | F7: Security | G7: Пользователь не авторизован | H7: 1. Открыть /orders/orders-list, /users/user напрямую | J7: Редирект на /sign-in, данные не показаны | L7: Да | N7: Не автоматизирован | P7: Не выполнен
A8: AUTH-007 | B8: Авторизация и доступ | C8: Сессия | D8: Сессия сохраняется после перезагрузки | E8: P2 | F8: Functional | G8: Вход в админку под тестовым аккаунтом (полные права) | H8: 1. Обновить страницу 2. Открыть новую вкладку | J8: Пользователь остаётся авторизован | L8: Да | N8: Не автоматизирован | P8: Не выполнен
A9: AUTH-008 | B9: Авторизация и доступ | C9: Сессия | D9: Выход из админки | E9: P1 | F9: Smoke | G9: Вход в админку под тестовым аккаунтом (полные права) | H9: 1. Меню аватара → Logout | J9: Сессия завершена, редирект на /sign-in; «Назад» в браузере не открывает данные | L9: Да | N9: Не автоматизирован | P9: Не выполнен
A10: AUTH-009 | B10: Авторизация и доступ | C10: Доступ | D10: Пользователь без доступа к админке (клиент) | E10: P2 | F10: Security | G10: Аккаунт клиента без роли сотрудника | H10: 1. Войти в админку клиентским аккаунтом | J10: Вход запрещён или нет ни одного модуля | L10: Частично | M10: Нужен аккаунт без прав | N10: Не автоматизирован | P10: Не выполнен
A11: DASH-001 | B11: Главная (Dashboard) | C11: Лимит филиалов | D11: Блок «Branch debt limit» | E11: P2 | F11: Functional | G11: Вход в админку под тестовым аккаунтом (полные права) | H11: 1. Открыть Dashboard 2. Переключить вкладки филиалов | J11: Карточки: Total limit, Debt of limited branches, Over the limit, Near the limit 80–100%, Branches without limit; по филиалу: Limit, Current debt, Remaining, Occupancy %; «Go to list» → /debt/warehouse-debt-limits | K11: PRD Filial qarz limiti | L11: Да | N11: Не автоматизирован | P11: Не выполнен
A12: DASH-002 | B12: Главная (Dashboard) | C12: Касса | D12: Блок «Cashier Report»: вкладки и «Refresh» | E12: P2 | F12: Functional | G12: Вход в админку под тестовым аккаунтом (полные права) | H12: 1. Выбрать вкладку склада 2. Нажать «Refresh» | J12: Считается только выбранный склад; данные пересчитываются только по «Refresh»; при ошибке остаётся старый снимок с сообщением; время снимка обновляется | K12: PRD Bosh sahifa — Kassa bloki | L12: Частично | M12: Суммы сверять с отчётом кассы | N12: Не автоматизирован | P12: Не выполнен
A13: DASH-003 | B13: Главная (Dashboard) | C13: Рейтинг | D13: Блок рейтинга складов | E13: P3 | F13: UI | G13: Вход в админку под тестовым аккаунтом (полные права) | H13: 1. Прокрутить Dashboard 2. Нажать «View all» | J13: Блок отображается; «View all» → /warehouse/warehouse-rating | L13: Да | N13: Не автоматизирован | P13: Не выполнен
A14: DASH-004 | B14: Главная (Dashboard) | C14: Доступ | D14: Склады на Dashboard по правам пользователя | E14: P2 | F14: Security | G14: Пользователь — продавец одного склада | H14: 1. Открыть Dashboard | J14: Видна только вкладка своего склада | L14: Частично | M14: Нужен аккаунт продавца | N14: Не автоматизирован | P14: Не выполнен
A15: PINC-001 | B15: Приход товара (Product income) | C15: Список | D15: Список и фильтры прихода | E15: P2 | F15: Functional | G15: Вход в админку под тестовым аккаунтом (полные права) | H15: 1. Открыть Products actions → Product income 2. Фильтр: Date range, Warehouse, Provider, Status, Delivery Status | J15: Список фильтруется; колонки ID, Created date, Warehouse, Provider, Price, Status, Delivery status, Post status, Posted at; пагинация | L15: Да | N15: Не автоматизирован | P15: Не выполнен
A16: PINC-002 | B16: Приход товара (Product income) | C16: Создание | D16: Создание документа прихода | E16: P1 | F16: Smoke | G16: Вход в админку под тестовым аккаунтом (полные права) | H16: 1. «Create» 2. Выбрать Warehouse, Provider, Delivery Status, Delivery date, Currency 3. «Add» — добавить вариант, количество, цену прихода 4. «Save» | I16: Склад: Asosiy ombor; поставщик — любой | J16: Документ создан в статусе «Создан»; в строке подтянуты последняя цена прихода, средняя цена, цены B2B/B2M/B2C | L16: Да | N16: Не автоматизирован | P16: Не выполнен
A17: PINC-003 | B17: Приход товара (Product income) | C17: Цены | D17: Расчёт средней цены и наценки | E17: P1 | F17: Functional | G17: Вход в админку под тестовым аккаунтом (полные права); открыт документ прихода | H17: 1. Ввести цену прихода, Fare percent, Custom clearance 2. Нажать «Fill income price» / «Apply» | J17: Средняя цена пересчитана; цены B2B/B2M/B2C ≥ 1 и в диапазоне [средняя цена; средняя × (1 + Max margin %)] | K17: PRD Product Income Excel Import | L17: Частично | M17: Формулу сверять по API calculate-average-prices | N17: Не автоматизирован | P17: Не выполнен
A18: PINC-004 | B18: Приход товара (Product income) | C18: Цены | D18: Цена продажи вне допустимого диапазона | E18: P1 | F18: Negative | G18: Вход в админку под тестовым аккаунтом (полные права); открыт документ прихода | H18: 1. Указать цену B2C ниже средней цены 2. «Save» | J18: Сохранение заблокировано, ошибка у строки | L18: Да | N18: Не автоматизирован | P18: Не выполнен
A19: PINC-005 | B19: Приход товара (Product income) | C19: Excel | D19: Импорт строк из Excel поставщика | E19: P2 | F19: Functional | G19: Вход в админку под тестовым аккаунтом (полные права); открыт новый документ прихода | H19: 1. «Template» — скачать шаблон 2. Заполнить вариант, количество, цену 3. «Import» | J19: Строки заполнены автоматически и сразу валидны для сохранения; производные цены подтянуты | K19: PRD Product Income Excel Import | L19: Да | N19: Не автоматизирован | P19: Не выполнен
A20: PINC-006 | B20: Приход товара (Product income) | C20: Excel | D20: Импорт Excel с ошибками | E20: P2 | F20: Negative | G20: Вход в админку под тестовым аккаунтом (полные права) | H20: 1. Импортировать файл с несуществующим вариантом / пустым количеством | J20: Импорт целиком отклонён (всё или ничего), понятная ошибка на узбекском с номером строки/колонки | L20: Да | N20: Не автоматизирован | P20: Не выполнен
A21: PINC-007 | B21: Приход товара (Product income) | C21: Статусы | D21: «В пути» → «Получен» → «Post» | E21: P1 | F21: Smoke | G21: Вход в админку под тестовым аккаунтом (полные права); документ прихода в статусе «Создан», доставка «Yo'lda» | H21: 1. Сменить Delivery Status на «Qabul qilingan» 2. Сохранить 3. «Post» | J21: Post доступен только при «Получен»; после Post остаток склада увеличен на количество; Posted at заполнено; документ заблокирован для редактирования (только комментарий) | K21: PRD Kirim — qisman kelish | L21: Да | N21: Не автоматизирован | P21: Не выполнен
A22: PINC-008 | B22: Приход товара (Product income) | C22: Статусы | D22: Post недоступен до получения | E22: P2 | F22: Negative | G22: Вход в админку под тестовым аккаунтом (полные права); документ «В пути» | H22: 1. Попробовать «Post» | J22: Кнопка недоступна / ошибка | L22: Да | N22: Не автоматизирован | P22: Не выполнен
A23: PINC-009 | B23: Приход товара (Product income) | C23: Частичная приёмка | D23: Частичное поступление («Keldi») | E23: P2 | F23: Functional | G23: Вход в админку под тестовым аккаунтом (полные права); документ «Создан» + «В пути» | H23: 1. Отметить строки 2. «Keldi», указать пришедшее количество (1…кол-во в документе) 3. «Qabul qilish» | J23: Создан новый документ «Получен» с пришедшим количеством; в исходном остались только недошедшие; суммы совпадают; вне диапазона — ошибка, кнопка неактивна | K23: PRD Kirim — qisman kelish (AIDT-753) | L23: Да | N23: Не автоматизирован | P23: Не выполнен
A24: PINC-010 | B24: Приход товара (Product income) | C24: Печать | D24: Печать этикеток (Label / Check name) | E24: P3 | F24: Functional | G24: Вход в админку под тестовым аккаунтом (полные права); документ прихода с товарами | H24: 1. Нажать «Label» / «Print» у строки | J24: Открывается печать этикетки с названием для чека (Check name) | L24: Частично | M24: Печать проверяется визуально | N24: Не автоматизирован | P24: Не выполнен
A25: PINC-011 | B25: Приход товара (Product income) | C25: Связи | D25: Приход закрывает запросы «Would buy» | E25: P2 | F25: Integration | G25: Есть запрос «Would buy» на вариант без остатка | H25: 1. Провести (Post) приход этого варианта в склад клиента 2. Открыть Requests → Would buy | J25: Запрос «Tugallangan», указаны дата, исполнитель, приход | K25: PRD Bo'lsa olar edim (admin) | L25: Да | N25: Не автоматизирован | P25: Не выполнен
A26: PRICE-001 | B26: Установка цен (Install prices) | C26: Документ | D26: Создание документа изменения цен | E26: P1 | F26: Smoke | G26: Вход в админку под тестовым аккаунтом (полные права) | H26: 1. Products actions → Install prices → «Create» 2. «Add» вариант 3. Ввести New price B2B/B2C/B2M 4. «Save» | J26: Документ сохранён; видны старые и новые цены по трём типам | L26: Да | N26: Не автоматизирован | P26: Не выполнен
A27: PRICE-002 | B27: Установка цен (Install prices) | C27: Проведение | D27: Проведение (Post) обновляет цены на витрине | E27: P1 | F27: Integration | G27: Вход в админку под тестовым аккаунтом (полные права); сохранён документ цен | H27: 1. «Post» 2. Открыть товар на витрине под клиентом и мастером | J27: Posted date заполнена; витрина показывает новые B2C (клиент) и B2M (мастер) | L27: Да | N27: Не автоматизирован | P27: Не выполнен
A28: PRICE-003 | B28: Установка цен (Install prices) | C28: Валидация | D28: Пустая или нулевая новая цена | E28: P2 | F28: Negative | G28: Вход в админку под тестовым аккаунтом (полные права) | H28: 1. Оставить New price пустой или 0 2. «Save» | J28: Сохранение заблокировано с ошибкой | L28: Да | N28: Не автоматизирован | P28: Не выполнен
A29: PRICE-004 | B29: Установка цен (Install prices) | C29: Список | D29: Список документов цен | E29: P3 | F29: UI | G29: Вход в админку под тестовым аккаунтом (полные права) | H29: 1. Открыть Install prices 2. Поиск, пагинация | J29: Колонки Id, Created date, Posted date; пагинация работает | L29: Да | N29: Не автоматизирован | P29: Не выполнен
A30: INV-001 | B30: Инвентаризация | C30: Создание | D30: Запуск инвентаризации | E30: P1 | F30: Smoke | G30: Вход в админку под тестовым аккаунтом (полные права); на складе нет активной инвентаризации | H30: 1. Products actions → Inventory → «Create» 2. Warehouse, Type (Offline/Online) 3. «Start» | J30: Документ создан; склад в режиме инвентаризации (заморожен) вместе со складом брака | L30: Да | N30: Не автоматизирован | P30: Не выполнен
A31: INV-002 | B31: Инвентаризация | C31: Ограничения | D31: Вторая инвентаризация на том же складе | E31: P1 | F31: Negative | G31: Вход в админку под тестовым аккаунтом (полные права); на складе активная инвентаризация | H31: 1. Запустить ещё одну на этот склад | J31: Блок с ошибкой; на другом складе запуск разрешён | K31: PRD Inventory | L31: Да | N31: Не автоматизирован | P31: Не выполнен
A32: INV-003 | B32: Инвентаризация | C32: Ограничения | D32: Операции на складе во время инвентаризации | E32: P1 | F32: Negative | G32: Вход в админку под тестовым аккаунтом (полные права); склад в режиме инвентаризации | H32: 1. Попробовать отправить перемещение / провести приход на этот склад | J32: Операции блокируются с понятной ошибкой | L32: Частично | N32: Не автоматизирован | P32: Не выполнен
A33: INV-004 | B33: Инвентаризация | C33: Открытые документы | D33: Окно открытых документов перед стартом | E33: P2 | F33: Functional | G33: Вход в админку под тестовым аккаунтом (полные права); у склада есть перемещения «Создан/Готов/В пути/Возвращён» | H33: 1. Запустить инвентаризацию | J33: Показано окно открытых документов; возвращённые не блокируют | L33: Частично | N33: Не автоматизирован | P33: Не выполнен
A34: INV-005 | B34: Инвентаризация | C34: Excel | D34: Скачивание и загрузка Excel | E34: P1 | F34: Functional | G34: Вход в админку под тестовым аккаунтом (полные права); активная инвентаризация | H34: 1. «Download» 2. Заполнить факт 3. Загрузить файл | J34: Excel содержит остатки и колонки движений (в т.ч. Transfer Yaratilgan / Tayyorlandi / Yo'lda / Transfer return); загрузка валидирует данные | L34: Да | N34: Не автоматизирован | P34: Не выполнен
A35: INV-006 | B35: Инвентаризация | C35: Excel | D35: Загрузка некорректного файла | E35: P2 | F35: Negative | G35: Вход в админку под тестовым аккаунтом (полные права) | H35: 1. Загрузить файл чужого склада / с буквами в количестве | J35: Ошибка валидации, данные не изменены | L35: Да | N35: Не автоматизирован | P35: Не выполнен
A36: INV-007 | B36: Инвентаризация | C36: Online | D36: Online-инвентаризация: пустые строки пропускаются | E36: P2 | F36: Functional | G36: Вход в админку под тестовым аккаунтом (полные права) | H36: 1. Тип Online 2. Заполнить факт только по 2 строкам 3. Провести | J36: Изменены только заполненные строки; по пустым нет движений | L36: Да | N36: Не автоматизирован | P36: Не выполнен
A37: INV-008 | B37: Инвентаризация | C37: Проведение | D37: Проведение инвентаризации | E37: P1 | F37: Functional | G37: Вход в админку под тестовым аккаунтом (полные права); файл загружен | H37: 1. Провести (Post) | J37: Остатки = факт; история движения записана; склад разморожен; статус «Проведён» | L37: Да | N37: Не автоматизирован | P37: Не выполнен
A38: TRF-001 | B38: Перемещение товара (Transfer) | C38: Список | D38: Список перемещений и вкладки | E38: P2 | F38: Functional | G38: Вход в админку под тестовым аккаунтом (полные права) | H38: 1. Products actions → Product transfer 2. Вкладки All / Transfer / Request | J38: Колонки ID, Type, Created, From, To, Price, Sent, Received, Comment, Status; вкладки фильтруют по типу | L38: Да | N38: Не автоматизирован | P38: Не выполнен
A39: TRF-002 | B39: Перемещение товара (Transfer) | C39: Перемещение | D39: Создание перемещения | E39: P1 | F39: Smoke | G39: Вход в админку под тестовым аккаунтом (полные права) | H39: 1. Создать перемещение: склад-отправитель (свой), получатель, товары и кол-во 2. Сохранить | J39: Статус «Создан»; остаток отправителя зарезервирован (показан свободный остаток + резерв документа) | K39: PRD Product Transfer | L39: Да | N39: Не автоматизирован | P39: Не выполнен
A40: TRF-003 | B40: Перемещение товара (Transfer) | C40: Перемещение | D40: Отправка и приёмка | E40: P1 | F40: Smoke | G40: Перемещение «Создан» | H40: 1. Отправитель: «Отправить» 2. Получатель: «Принять» | J40: «В пути» → «Получено»; товар списан у отправителя и добавлен получателю; даты отправки/получения заполнены | L40: Да | N40: Не автоматизирован | P40: Не выполнен
A41: TRF-004 | B41: Перемещение товара (Transfer) | C41: Перемещение | D41: Возврат перемещения и повторная отправка | E41: P2 | F41: Functional | G41: Перемещение «В пути» | H41: 1. Получатель: «Вернуть» 2. Отправитель редактирует и отправляет снова | J41: «Возвращён» → снова «В пути»; получатель в «Возвращён» только смотрит | L41: Да | N41: Не автоматизирован | P41: Не выполнен
A42: TRF-005 | B42: Перемещение товара (Transfer) | C42: Перемещение | D42: Отмена перемещения | E42: P1 | F42: Functional | G42: Перемещение «Создан» | H42: 1. «Отменить» | J42: Статус «Отменён», резерв возвращён на склад-отправитель | L42: Да | N42: Не автоматизирован | P42: Не выполнен
A43: TRF-006 | B43: Перемещение товара (Transfer) | C43: Права | D43: Отправитель только со своего склада | E43: P1 | F43: Security | G43: Пользователь привязан к складу A | H43: 1. Создать перемещение | J43: В отправителе доступен только склад A; получатель не может редактировать/отправлять | K43: PRD Transfer permission | L43: Частично | M43: Нужен аккаунт продавца | N43: Не автоматизирован | P43: Не выполнен
A44: TRF-007 | B44: Перемещение товара (Transfer) | C44: Запрос | D44: Запрос товара (Request) | E44: P1 | F44: Functional | G44: Пользователь склада-получателя | H44: 1. «Создать запрос»: склад-владелец, товары, кол-во 2. Владелец одобряет и отправляет 3. Получатель принимает | J44: Черновик → Запрошен → (одобрение) Создан → В пути → Получено; колонка «Запрошено» сохранена; бейдж «So'rov» | L44: Да | N44: Не автоматизирован | P44: Не выполнен
A45: TRF-008 | B45: Перемещение товара (Transfer) | C45: Запрос | D45: Отклонение от запрошенного кол-ва требует причину | E45: P2 | F45: Negative | G45: Запрос на 10 шт | H45: 1. При одобрении указать 7 шт без причины 2. Указать причину | J45: Без причины сохранить нельзя; с причиной — ок | L45: Да | N45: Не автоматизирован | P45: Не выполнен
A46: TRF-009 | B46: Перемещение товара (Transfer) | C46: Уведомления | D46: Уведомления о перемещениях в колокольчике | E46: P3 | F46: Functional | G46: Два пользователя разных складов | H46: 1. Отправить перемещение 2. Вернуть его | J46: Получатель получает «Отправлено», отправитель — «Возвращено»; созданное вручную не шлёт «Создано» | K46: PRD Transfer Notifications | L46: Частично | N46: Не автоматизирован | P46: Не выполнен
A47: TRF-010 | B47: Перемещение товара (Transfer) | C47: Печать | D47: Печать документа перемещения | E47: P3 | F47: UI | G47: Есть перемещение | H47: 1. Открыть 2. «Print» | J47: Печатная форма с товарами, количеством, складами | L47: Да | N47: Не автоматизирован | P47: Не выполнен
A48: PVAR-001 | B48: Варианты товара (потребность) | C48: Потребность | D48: Отметка Necessary / Unnecessary | E48: P3 | F48: Functional | G48: Вход в админку под тестовым аккаунтом (полные права) | H48: 1. Products actions → Product variant 2. Выбрать строки 3. «Necessary» / «Unnecessary» | J48: Колонка Isnecessary обновлена у выбранных | L48: Да | N48: Не автоматизирован | P48: Не выполнен
A49: PVAR-002 | B49: Варианты товара (потребность) | C49: Потребность | D49: «Add normative day» и выгрузка | E49: P3 | F49: Functional | G49: Вход в админку под тестовым аккаунтом (полные права) | H49: 1. Выбрать строки → «Add normative day» 2. «Download» | J49: Норматив дней сохранён; Excel совпадает с таблицей | L49: Да | N49: Не автоматизирован | P49: Не выполнен
A50: DISC-001 | B50: Скидки и акции | C50: Создание | D50: Создание акции | E50: P1 | F50: Smoke | G50: Вход в админку под тестовым аккаунтом (полные права) | H50: 1. Products actions → Discount → «Create» 2. Даты, склады, названия UZ/RU/EN 3. «Add» товары, скидочные цены B2C/B2M/B2B 4. «Save» | J50: Акция создана; % рассчитан по каждому типу цены | K50: PRD Discount US1 | L50: Да | N50: Не автоматизирован | P50: Не выполнен
A51: DISC-002 | B51: Скидки и акции | C51: Валидация | D51: Скидочная цена выше текущей | E51: P1 | F51: Negative | G51: Вход в админку под тестовым аккаунтом (полные права) | H51: 1. Указать Discount price > Current price 2. «Save» | J51: Ошибка; равная цене допускается | K51: PRD Mijozga xos chegirma | L51: Да | N51: Не автоматизирован | P51: Не выполнен
A52: DISC-003 | B52: Скидки и акции | C52: Статусы | D52: Автостатусы акции | E52: P1 | F52: Functional | G52: Вход в админку под тестовым аккаунтом (полные права) | H52: 1. Создать акцию с началом завтра 2. Акцию с текущими датами 3. Акцию с прошедшими датами | J52: Upcoming / Active / Expired определяются по датам автоматически | L52: Да | N52: Не автоматизирован | P52: Не выполнен
A53: DISC-004 | B53: Скидки и акции | C53: Статусы | D53: Редактирование и отмена | E53: P2 | F53: Functional | G53: Акции Upcoming, Active, Expired, Cancelled | H53: 1. Изменить/отменить каждую | J53: Редактировать/отменять можно только Upcoming и Active; Cancelled и Expired — только просмотр | L53: Да | N53: Не автоматизирован | P53: Не выполнен
A54: DISC-005 | B54: Скидки и акции | C54: Витрина | D54: Акция на витрине только для своего типа цены | E54: P1 | F54: Integration | G54: Активная акция только по B2C | H54: 1. Открыть товар под клиентом и под мастером | J54: Клиент видит -%, зачёркнутую цену и «N дней»; мастер — без скидки | K54: PRD Mijozga xos chegirma (AIDT-817) | L54: Частично | N54: Не автоматизирован | P54: Не выполнен
A55: DISC-006 | B55: Скидки и акции | C55: Витрина | D55: Акция только на выбранных складах | E55: P2 | F55: Integration | G55: Акция на складе A | H55: 1. На витрине выбрать магазин склада A, затем B | J55: Скидка только для A | L55: Да | N55: Не автоматизирован | P55: Не выполнен
A56: DISC-007 | B56: Скидки и акции | C56: Авто | D56: Черновик акции (авто-предложение) | E56: P3 | F56: Functional | G56: Система сформировала черновик по зависшему товару | H56: 1. Открыть черновик 2. Указать даты, запустить | J56: Черновик с предложенным %; после запуска — обычная акция | K56: PRD Auto chegirma | L56: Частично | N56: Не автоматизирован | P56: Не выполнен
A57: PROD-001 | B57: Товары и варианты | C57: Список | D57: Список товаров | E57: P2 | F57: Functional | G57: Вход в админку под тестовым аккаунтом (полные права) | H57: 1. Открыть Products 2. Поиск по названию/ID 3. Пагинация | J57: Колонки Id, Name, Variant count, Model, Category; поиск и пагинация работают | L57: Да | N57: Не автоматизирован | P57: Не выполнен
A58: PROD-002 | B58: Товары и варианты | C58: Товар | D58: Редактирование товара (General) | E58: P1 | F58: Functional | G58: Вход в админку под тестовым аккаунтом (полные права) | H58: 1. Открыть товар 2. Изменить Product name, Brand, Category, Model, изображение 3. «Save» 4. Вернуть исходное | J58: Изменения сохранены и видны на витрине | L58: Да | N58: Не автоматизирован | P58: Не выполнен
A59: PROD-003 | B59: Товары и варианты | C59: Товар | D59: Создание товара | E59: P1 | F59: Smoke | G59: Вход в админку под тестовым аккаунтом (полные права) | H59: 1. Создать товар: название, бренд, категория (до Type, если есть), модель, изображение | J59: Товар создан и виден в списке | L59: Да | N59: Не автоматизирован | P59: Не выполнен
A60: PROD-004 | B60: Товары и варианты | C60: Варианты | D60: Создание варианта | E60: P1 | F60: Smoke | G60: Вход в админку под тестовым аккаунтом (полные права); открыт товар → Variations | H60: 1. Добавить вариант: атрибуты (качество, цвет), производитель, Check name 2. Сохранить | J60: Вариант создан; пустой Check name генерируется автоматически | K60: PRD Product Variant Check Name | L60: Да | N60: Не автоматизирован | P60: Не выполнен
A61: PROD-005 | B61: Товары и варианты | C61: Варианты | D61: Дубль варианта | E61: P2 | F61: Negative | G61: Есть вариант с теми же атрибутами и производителем | H61: 1. Создать такой же вариант | J61: Ошибка уникальности; с другим производителем — разрешено | K61: PRD 8.7 Ishlab chiqaruvchilar | L61: Да | N61: Не автоматизирован | P61: Не выполнен
A62: PROD-006 | B62: Товары и варианты | C62: Варианты | D62: Перенос варианта к другому товару | E62: P2 | F62: Functional | G62: Есть вариант | H62: 1. Изменить «Основной товар» 2. Подтвердить | J62: Окно с предупреждением о смене категории; вариант перенесён с остатками и историей | K62: PRD Mahsulot varianti — almashtirish | L62: Да | N62: Не автоматизирован | P62: Не выполнен
A63: PROD-007 | B63: Товары и варианты | C63: Категории | D63: Обязательный Type у подкатегории с типами | E63: P2 | F63: Negative | G63: Подкатегория с Type | H63: 1. Создать товар без Type | J63: Сохранение заблокировано | K63: PRD Product & Product Variant | L63: Да | N63: Не автоматизирован | P63: Не выполнен
A64: DIR-001 | B64: Справочники | C64: Бренды | D64: CRUD брендов | E64: P2 | F64: Functional | G64: Вход в админку под тестовым аккаунтом (полные права) | H64: 1. Directory → Brands → «Create» 2. Отредактировать 3. Найти поиском | J64: Бренд создан/изменён, есть в выборе бренда у товара | L64: Да | N64: Не автоматизирован | P64: Не выполнен
A65: DIR-002 | B65: Справочники | C65: Категории | D65: Создание категории | E65: P1 | F65: Functional | G65: Вход в админку под тестовым аккаунтом (полные права) | H65: 1. Categories → «Create»: Name uz/ru/en, Tags, изображение, вес и габариты 2. «Create» | J65: Категория создана и видна в меню каталога на витрине | L65: Да | N65: Не автоматизирован | P65: Не выполнен
A66: DIR-003 | B66: Справочники | C66: Категории | D66: Страница категории: Subcategories / Products | E66: P2 | F66: Functional | G66: Вход в админку под тестовым аккаунтом (полные права) | H66: 1. Открыть категорию 2. Переключить вкладки | J66: Видны подкатегории и привязанные товары | K66: PRD AIDT-759 | L66: Да | N66: Не автоматизирован | P66: Не выполнен
A67: DIR-004 | B67: Справочники | C67: Категории | D67: Обязательные поля категории | E67: P2 | F67: Negative | G67: Вход в админку под тестовым аккаунтом (полные права) | H67: 1. Создать категорию без названия | J67: Ошибка валидации | L67: Да | N67: Не автоматизирован | P67: Не выполнен
A68: DIR-005 | B68: Справочники | C68: Атрибуты | D68: CRUD атрибутов и статус | E68: P3 | F68: Functional | G68: Вход в админку под тестовым аккаунтом (полные права) | H68: 1. Attributes → «Create» 2. Изменить статус | J68: Атрибут создан; неактивный недоступен при создании варианта | L68: Да | N68: Не автоматизирован | P68: Не выполнен
A69: DIR-006 | B69: Справочники | C69: Модели | D69: Создание модели и уникальность | E69: P2 | F69: Functional | G69: Вход в админку под тестовым аккаунтом (полные права) | H69: 1. Models → «Create» (Title, Brand, Category) 2. Создать дубль | J69: Модель создана; дубль в той же паре бренд+категория запрещён; модель видна в «Модель» на витрине | L69: Да | N69: Не автоматизирован | P69: Не выполнен
A70: DIR-007 | B70: Справочники | C70: Модели | D70: Модели устройств (Device model) | E70: P3 | F70: Functional | G70: Вход в админку под тестовым аккаунтом (полные права) | H70: 1. Device model → «Create» | J70: Модель устройства создана | L70: Да | N70: Не автоматизирован | P70: Не выполнен
A71: DIR-008 | B71: Справочники | C71: Поставщики | D71: CRUD поставщиков | E71: P3 | F71: Functional | G71: Вход в админку под тестовым аккаунтом (полные права) | H71: 1. Providers → «Create» (Name, Address, Phone) | J71: Поставщик создан, доступен в приходе | L71: Да | N71: Не автоматизирован | P71: Не выполнен
A72: ORD-001 | B72: Заказы | C72: Список | D72: Список заказов и фильтры | E72: P1 | F72: Smoke | G72: Вход в админку под тестовым аккаунтом (полные права) | H72: 1. Orders → Orders 2. Фильтр: дата, склад, пользователь, статус, оплата, доставка, источник 3. «Clear» | J72: Колонки Id, Customer, Order type, Warehouse, Status, Payment, Delivery, Total, Created, Comment; новые сверху; фильтры работают вместе | L72: Да | N72: Не автоматизирован | P72: Не выполнен
A73: ORD-002 | B73: Заказы | C73: Список | D73: Заказ с витрины появляется в админке | E73: P1 | F73: Integration | G73: Мастер оформил заказ на витрине | H73: 1. Найти заказ по ID / пользователю | J73: Данные совпадают с витриной: товары, сумма, оплата, доставка, склад, комментарий клиента | L73: Да | N73: Не автоматизирован | P73: Не выполнен
A74: ORD-003 | B74: Заказы | C74: Детали | D74: Карточка заказа | E74: P1 | F74: Functional | G74: Вход в админку под тестовым аккаунтом (полные права) | H74: 1. Открыть заказ | J74: Статусы заказа, клиент, склад-отправитель/склад, номер перемещения, даты; оплата: способ, цена товаров, возврат, цена заказа, доставка, срок; доставка: способ, адрес; товары: остаток, цена, возвращено, атрибуты | L74: Да | N74: Не автоматизирован | P74: Не выполнен
A75: ORD-004 | B75: Заказы | C75: Статусы | D75: Смена статуса заказа | E75: P1 | F75: Smoke | G75: Вход в админку под тестовым аккаунтом (полные права); заказ «Created» | H75: 1. Created → Send → Received → Completed 2. «Save» после каждого | J75: Статус и время сохраняются; клиент видит статус на витрине | K75: PRD Admin Order List and Detail | L75: Да | N75: Не автоматизирован | P75: Не выполнен
A76: ORD-005 | B76: Заказы | C76: Отмена | D76: Отмена заказа админом с причиной | E76: P1 | F76: Functional | G76: Вход в админку под тестовым аккаунтом (полные права); незавершённый заказ | H76: 1. Выбрать Canceled 2. Причину (не смогли связаться, не тот филиал, дубль, не тот товар, ошибка оформления, не забрал, другое) 3. «Save» | J76: Без причины не отменить; «Другое» требует комментарий; товар вернулся на склад; клиент получил уведомление с текстом причины | K76: PRD Buyurtmani bekor qilish | L76: Да | N76: Не автоматизирован | P76: Не выполнен
A77: ORD-006 | B77: Заказы | C77: Отмена | D77: Отмена заказа с перемещением | E77: P2 | F77: Functional | G77: Заказ с перемещением «Создан» / «В пути» | H77: 1. Отменить заказ | J77: «Создан» — перемещение отменено, товар вернулся отправителю; «В пути» — без изменений до приёмки | L77: Да | N77: Не автоматизирован | P77: Не выполнен
A78: ORD-007 | B78: Заказы | C78: Перемещение | D78: Приём перемещения из карточки заказа | E78: P2 | F78: Functional | G78: Заказ с перемещением «В пути», пользователь склада-получателя | H78: 1. В карточке заказа «Принять» | J78: Перемещение принято целиком, заказ «Received»; чужой склад не может принять | K78: PRD Admin Order ORD-010 | L78: Да | N78: Не автоматизирован | P78: Не выполнен
A79: ORD-008 | B79: Заказы | C79: Оплата | D79: Статус оплаты меняется отдельно | E79: P2 | F79: Functional | G79: Заказ с оплатой наличными | H79: 1. Отметить оплату как оплаченную | J79: Меняется только оплата; статус заказа без изменений; клиент видит «Оплачено» | L79: Да | N79: Не автоматизирован | P79: Не выполнен
A80: ORD-009 | B80: Заказы | C80: Смена оплаты | D80: Запрос клиенту на смену оплаты | E80: P1 | F80: Functional | G80: Заказ: Created/Send/Received, не оплачен | H80: 1. «Изменить способ оплаты»: Наличные → Hamyon (срок для мастера только чтение) 2. «Отправить запрос» | J80: Баннер «ожидает подтверждения», можно отменить; клиенту пришёл push; до ответа способ не меняется | K80: PRD Change Payment Method | L80: Да | N80: Не автоматизирован | P80: Не выполнен
A81: ORD-010 | B81: Заказы | C81: Смена оплаты | D81: Защита при смене статуса с открытым запросом | E81: P2 | F81: Functional | G81: Есть запрос на смену оплаты | H81: 1. Перевести заказ в Completed | J81: Окно «запрос будет отменён — продолжить?»; при «Да» запрос отменён и статус меняется | L81: Да | N81: Не автоматизирован | P81: Не выполнен
A82: ORD-011 | B82: Заказы | C82: Смена оплаты | D82: Смена оплаты недоступна для закрытых заказов | E82: P2 | F82: Negative | G82: Заказ Completed / Canceled / Returned | H82: 1. Открыть оплату | J82: «Payment method cannot be changed for this order» | L82: Да | N82: Не автоматизирован | P82: Не выполнен
A83: ORD-012 | B83: Заказы | C83: Баллы | D83: Выполнение заказа начисляет 1% баллов | E83: P1 | F83: Integration | G83: Заказ клиента не оплачен баллами | H83: 1. Перевести в Completed | J83: Начислено 1% цены заказа; в Point transactions — «Начислено за заказ» | L83: Да | N83: Не автоматизирован | P83: Не выполнен
A84: ORD-013 | B84: Заказы | C84: Долг | D84: Выполнение Hamyon-заказа и лимит филиала | E84: P1 | F84: Integration | G84: Hamyon-заказ; долг филиала у лимита | H84: 1. Перевести в Completed | J84: При превышении лимита — блок с цифрами; иначе Completed, срок оплаты = дата выполнения + N дней в 17:00 | K84: PRD Filial qarz limiti; PRD Debt Limit | L84: Да | N84: Не автоматизирован | P84: Не выполнен
A85: ORD-014 | B85: Заказы | C85: Печать | D85: Печать заказа | E85: P3 | F85: UI | G85: Есть заказ | H85: 1. «Print» | J85: Печатная форма заказа | L85: Да | N85: Не автоматизирован | P85: Не выполнен
A86: SW-001 | B86: Окно продаж (Sales window) | C86: Список | D86: Список документов окна продаж | E86: P2 | F86: Functional | G86: Вход в админку под тестовым аккаунтом (полные права) | H86: 1. Orders → Sales window 2. Фильтры: дата, склад, статус, тип продажи | J86: Колонки Id, Customer, Phone, Warehouse, Initiator, Total, Sent, Received, Type, Timer, Status | L86: Да | N86: Не автоматизирован | P86: Не выполнен
A87: SW-002 | B87: Окно продаж (Sales window) | C87: Создание | D87: Создание и отправка документа клиенту | E87: P1 | F87: Smoke | G87: Вход в админку под тестовым аккаунтом (полные права) | H87: 1. «Create»: клиент, склад, тип продажи (Передан / Предложение), способ оплаты или «Клиент выбирает» 2. Товары, кол-во ≤ доступного 3. «Send» | J87: Статус «Отправлен»; товар зарезервирован; клиенту push; документ в «Спецзаказ → Новинка» на витрине | K87: PRD Sales window | L87: Да | N87: Не автоматизирован | P87: Не выполнен
A88: SW-003 | B88: Окно продаж (Sales window) | C88: Валидация | D88: Количество больше доступного | E88: P2 | F88: Negative | G88: Вход в админку под тестовым аккаунтом (полные права) | H88: 1. Указать кол-во > доступного | J88: Ошибка, сохранить нельзя | L88: Да | N88: Не автоматизирован | P88: Не выполнен
A89: SW-004 | B89: Окно продаж (Sales window) | C89: Жизненный цикл | D89: Подтверждение клиентом создаёт заказ | E89: P1 | F89: Integration | G89: Документ отправлен мастеру | H89: 1. Мастер подтверждает на витрине 2. Открыть документ и Orders | J89: Документ «Принят», создан обычный заказ | L89: Да | N89: Не автоматизирован | P89: Не выполнен
A90: SW-005 | B90: Окно продаж (Sales window) | C90: Жизненный цикл | D90: Отмена документа возвращает резерв | E90: P1 | F90: Functional | G90: Документ «Сохранён» или «Возвращён» | H90: 1. «Cancel» | J90: Статус «Отменён», товар вернулся на склад, клиенту push | L90: Да | N90: Не автоматизирован | P90: Не выполнен
A91: SW-006 | B91: Окно продаж (Sales window) | C91: Таймер | D91: Автовозврат предложения по таймеру | E91: P3 | F91: Functional | G91: Документ «Предложение» отправлен | H91: 1. Дождаться таймера | J91: Документ возвращён автоматически; «Передан» ждёт без таймера | L91: Нет | M91: Долгое ожидание | N91: Не автоматизирован | P91: Не выполнен
A92: SW-007 | B92: Окно продаж (Sales window) | C92: Тип | D92: Смена типа продажи | E92: P3 | F92: Functional | G92: Документ Saved / Sent / Returned | H92: 1. Сменить Передан ↔ Предложение | J92: Таймер перезапускается / отключается; в Received/Cancelled тип не меняется | L92: Да | N92: Не автоматизирован | P92: Не выполнен
A93: RET-001 | B93: Возврат товара | C93: Список | D93: Список возвратов | E93: P2 | F93: Functional | G93: Вход в админку под тестовым аккаунтом (полные права) | H93: 1. Orders → Return products 2. Фильтры: дата, склад, вариант | J93: Колонки Id, Name, Warehouse, Created, Total return amount | L93: Да | N93: Не автоматизирован | P93: Не выполнен
A94: RET-002 | B94: Возврат товара | C94: Создание | D94: Возврат исправного товара наличными | E94: P1 | F94: Smoke | G94: У клиента выполненный заказ | H94: 1. «Create»: клиент, строка заказа 2. Working return = 1, оплата «Наличные» 3. «Return» | J94: Возврат создан; товар в рабочем остатке; клиенту наличные; на витрине возврат «Возвращён» | K94: PRD Product Return | L94: Да | N94: Не автоматизирован | P94: Не выполнен
A95: RET-003 | B95: Возврат товара | C95: Создание | D95: Брак и исправный в одной строке | E95: P2 | F95: Functional | G95: Строка заказа на 2 шт | H95: 1. Working 1, Broken 1 | J95: Исправный — в рабочий остаток, брак — на склад брака | L95: Да | N95: Не автоматизирован | P95: Не выполнен
A96: RET-004 | B96: Возврат товара | C96: Создание | D96: Возврат больше проданного | E96: P1 | F96: Negative | G96: Строка: продано 2, возвращено 1 | H96: 1. Вернуть 2 | J96: Нельзя: доступно только 1; полностью возвращённые строки не выбираются | L96: Да | N96: Не автоматизирован | P96: Не выполнен
A97: RET-005 | B97: Возврат товара | C97: Оплата | D97: Возврат на кошелёк и баллы | E97: P2 | F97: Integration | G97: Заказ клиента оплачен Hamyon / баллами | H97: 1. Оформить возврат | J97: Hamyon — уменьшен долг/пополнен кошелёк; баллы — возвращены; начисленный 1% списан | L97: Да | N97: Не автоматизирован | P97: Не выполнен
A98: RET-006 | B98: Возврат товара | C98: Оплата | D98: Возврат при просроченном долге — только на кошелёк | E98: P2 | F98: Integration | G98: У клиента просроченный долг | H98: 1. Оформить возврат | J98: Доступен только возврат на кошелёк | K98: PRD Qaytarish — muddati o'tgan qarz | L98: Частично | N98: Не автоматизирован | P98: Не выполнен
A99: RET-007 | B99: Возврат товара | C99: Печать | D99: Чек возврата и этикетки | E99: P3 | F99: UI | G99: Есть возврат | H99: 1. «Chop etish» и «Chek chiqarish» | J99: Чек возврата (наличные / на кошелёк / итого) и этикетки | L99: Да | N99: Не автоматизирован | P99: Не выполнен
A100: BIL-001 | B100: Касса и финансы (Billing) | C100: Кассы | D100: Создание кассы | E100: P2 | F100: Functional | G100: Вход в админку под тестовым аккаунтом (полные права) | H100: 1. Billing → Cachier → «Create»: склад, ответственный, названия UZ/RU/EN 2. «Create» | J100: Касса создана, у неё открыт документ | L100: Да | N100: Не автоматизирован | P100: Не выполнен
...

Sheet Замечания
A1: № | B1: Категория | C1: Описание | D1: Где | E1: Серьёзность | F1: Комментарий | G1: Статус
A2: 1 | B2: Данные | C2: В «Debt limit» у клиентов B2C есть лимит (B2C, 300 000 000) | D2: /debt/debt-limit | E2: Medium | F2: PRD Mijoz rollari §6.7: лимит ставится даже обычному клиенту — подтвердить | G2: Новое
A3: 2 | B3: Логика | C3: Заблокированный кошелёк не мешает оплате Hamyon | D3: Checkout / Debt limit | E3: High | F3: Из проверки кода в PRD Debt Limit — проверить на staging | G3: Новое
A4: 3 | B4: Локализация | C4: Статус кошелька показан как «free» / «blocked» | D4: Wallet transactions, Wallet | E4: Low | F4: PRD Wallet (проверка кода) | G4: Новое
A5: 4 | B5: Локализация | C5: Названия складов на разных языках (например «Урикзор Магазин №43») | D5: Dashboard, Season, Cashier report | E5: Low | G5: Новое
A6: 5 | B6: Данные | C6: У отменённого заказа #518191 причина отмены «abc» | D6: /orders/518191 | E6: Info | F6: Проверить, откуда берётся текст | G6: Новое
B8: Замечания найдены при исследовании staging 28.10.2026 под аккаунтом мастера. Перед заведением бага — перепроверить.

Sheet Источники
A1: PRD / страница | B1: О чём | C1: Ссылка
A2: Папка логики админки (Confluence) | B2: Разделы 1–15 | C2: https://arositdepartment.atlassian.net/wiki/spaces/~ArosMarket/folder/354385922
A3: Admin Order List and Order Detail | B3: Заказы | C3: https://arositdepartment.atlassian.net/wiki/spaces/~ArosMarket/pages/333774849
A4: Product Transfer / Transfer permission | B4: Перемещения | C4: https://arositdepartment.atlassian.net/wiki/spaces/~ArosMarket/pages/304021505
A5: Inventory PRD | B5: Инвентаризация | C5: https://arositdepartment.atlassian.net/wiki/spaces/~ArosMarket/pages/305135617
A6: Product Income — Excel Import | B6: Приход, импорт Excel | C6: https://arositdepartment.atlassian.net/wiki/spaces/~ArosMarket/pages/324861953
A7: Kirim — qisman kelish | B7: Частичная приёмка | C7: https://arositdepartment.atlassian.net/wiki/spaces/~ArosMarket/pages/376209409
A8: Discount US1 / PRD | B8: Акции | C8: https://arositdepartment.atlassian.net/wiki/spaces/~ArosMarket/pages/154632194
A9: Mijozga xos chegirma ko'rinishi | B9: Скидки по типу цены | C9: https://arositdepartment.atlassian.net/wiki/spaces/~ArosMarket/pages/377651202
A10: Product & Product Variant | B10: Товары и варианты | C10: https://arositdepartment.atlassian.net/wiki/spaces/~ArosMarket/pages/292356097
A11: Sales window - PRD | B11: Окно продаж | C11: https://arositdepartment.atlassian.net/wiki/spaces/~ArosMarket/pages/307167233
A12: Product Return | B12: Возвраты | C12: https://arositdepartment.atlassian.net/wiki/spaces/~ArosMarket/pages/298024961
... A18: Roles and Permissions Module | B18: Права доступа | C18: https://arositdepartment.atlassian.net/wiki/spaces/~ArosMarket/pages/243597313
